Workbook

Sheet RPA RoadMap (2)
A1: Sr# | B1: UseCase Name | C1: Average Transactions (Annual) | D1: OCR / NON-OCR | E1: Already in production | F1: Automation Required | G1: RPA Complexity | H1: Estimated Efforts(Weeks) | I1: Developer | J1: Timeline
A2: 1 | B2: Data Change – Override Manager | C2: 6089 | D2: NON-OCR | E2: Y | F2: Y | G2: Medium | I2: Varun
A3: 2 | B3: Data Change – Use Position Reports To | C3: 3933 | D3: NON-OCR | E3: Y | F3: Y | G3: Simple | I3: Varun
A4: 3 | B4: Job Architecture | C4: 10692 | D4: NON-OCR | E4: Y | F4: Y | G4: Medium | I4: Varun
A5: 4 | B5: Job Description Update | C5: 7168 | D5: NON-OCR | E5: N | F5: Y | G5: Complex | H5: =VLOOKUP(_xlfn.CONCAT(D5,G5),'Estimation Guidelines'!C:L,10,FALSE) -> 8.6 | I5: Kishor | J5: Mar-April
A6: 5 | B6: Data Change – Override Person Job Band | C6: 4 | D6: NON-OCR | F6: N
A7: 6 | B7: Data Change – Use Position Job Band | C7: 7 | D7: NON-OCR | F7: N
A8: 7 | B8: Data Change – Data Change | C8: 6804 | D8: NON-OCR | E8: N | F8: Y | G8: Medium | H8: =VLOOKUP(_xlfn.CONCAT(D8,G8),'Estimation Guidelines'!C:L,10,FALSE) -> 5.8 | I8: Kishor | J8: May
A9: 8 | B9: External Hire Poornata ID creation | C9: 5170 | D9: NON-OCR | E9: N | F9: Y | G9: Complex | H9: =VLOOKUP(_xlfn.CONCAT(D9,G9),'Estimation Guidelines'!C:L,10,FALSE) -> 8.6 | I9: Kishor | J9: June- July
A10: 9 | B10: Poornata ID creation (Add a Person - Smart HR) | C10: 1057 | D10: NON-OCR | F10: N | G10: Medium
A11: 10 | B11: Poornata ID Creation (Add a Person) - Excel Template | C11: 5159 | D11: NON-OCR | E11: N | F11: Y | G11: Complex | H11: =VLOOKUP(_xlfn.CONCAT(D11,G11),'Estimation Guidelines'!C:L,10,FALSE) -> 8.6 | I11: Kishor | J11: Aug-Sep
A12: 11 | B12: Poornata ID Creation (Add POI/CWR) | C12: 573 | D12: NON-OCR | F12: N | G12: Complex
A13: 12 | B13: Job Data Update (Confirmation/Confirmation with pay rate change/Mobility) | C13: 10119 | D13: OCR | E13: N | F13: Y | G13: Complex | H13: =VLOOKUP(_xlfn.CONCAT(D13,G13),'Estimation Guidelines'!C:L,10,FALSE) -> 11.6 | I13: Rutuja , Vibhav | J13: Nov-Dec-Jan-Feb
A14: 13 | B14: Personal Data Update (Excluding Bulk volume-43,274) | C14: 14504 | D14: OCR | E14: N | F14: Y | G14: Complex | H14: =VLOOKUP(_xlfn.CONCAT(D14,G14),'Estimation Guidelines'!C:L,10,FALSE) -> 11.6 | I14: Rutuja , Vibhav | J14: Nov-Dec-Jan-Feb
A15: 14 | B15: Compensation Update (Excluding bulk volume-71,968) | C15: 7232 | D15: OCR | E15: N | F15: Y | G15: Complex | H15: =VLOOKUP(_xlfn.CONCAT(D15,G15),'Estimation Guidelines'!C:L,10,FALSE) -> 11.6 | I15: Rutuja , Vibhav | J15: Nov-Dec-Jan-Feb
A16: 15 | B16: Creation of Potential Assessment Document | C16: 5337 | D16: NON-OCR | E16: N | F16: Y | G16: Complex | H16: =VLOOKUP(_xlfn.CONCAT(D16,G16),'Estimation Guidelines'!C:L,10,FALSE) -> 8.6 | I16: Kishor | J16: Oct-Nov 2024
A17: 16 | B17: Poornata ID Creation (Add a Person) (Proposed Process Change) | C17: 8925 | D17: OCR | E17: N | F17: Y | G17: Complex | H17: =VLOOKUP(_xlfn.CONCAT(D17,G17),'Estimation Guidelines'!C:L,10,FALSE) -> 11.6 | I17: Rutuja , Vibhav | J17: Aug-Sep-Oct
A18: 17 | B18: Bank Data Update | C18: 3695 | D18: OCR | E18: N | F18: Y | G18: Medium | H18: =VLOOKUP(_xlfn.CONCAT(D18,G18),'Estimation Guidelines'!C:L,10,FALSE) -> 8.8 | I18: Rutuja , Vibhav | J18: April - May-June-July
A19: 18 | B19: Poornata ID creation (Through External Hire) – QC action and update if missing data-Proposed process change | C19: 5854 | D19: OCR | E19: N | F19: Y | G19: Complex | H19: =VLOOKUP(_xlfn.CONCAT(D19,G19),'Estimation Guidelines'!C:L,10,FALSE) -> 11.6 | I19: Rutuja , Vibhav | J19: Aug-Sep-Oct
A20: 19 | B20: Education Data | C20: 2981 | D20: OCR | E20: N | F20: Y | G20: Complex | H20: =VLOOKUP(_xlfn.CONCAT(D20,G20),'Estimation Guidelines'!C:L,10,FALSE) -> 11.6 | I20: Rutuja , Vibhav | J20: April - May-June-July
A21: 20 | B21: National ID, PAN, Aadhar, Passport, Visa, Address | C21: 9845 | D21: OCR | E21: N | F21: Y | G21: Complex | H21: =VLOOKUP(_xlfn.CONCAT(D21,G21),'Estimation Guidelines'!C:L,10,FALSE) -> 11.6 | I21: Rutuja , Vibhav | J21: April - May-June-July
A22: 21 | B22: Learning Session creation | C22: 1277 | D22: NON-OCR | F22: N
A23: 22 | B23: Leave Balance upload | C23: 4243 | D23: NON-OCR | E23: N | F23: Y | G23: Complex | H23: =VLOOKUP(_xlfn.CONCAT(D23,G23),'Estimation Guidelines'!C:L,10,FALSE) -> 8.6 | I23: Kishor | J23: Dec-Jan
A24: 23 | B24: BGV initiation and Report upload Initiate – 20 mins Report upload 10 mins | C24: 5228 | D24: NON-OCR | E24: N | F24: Y | G24: Complex | H24: =VLOOKUP(_xlfn.CONCAT(D24,G24),'Estimation Guidelines'!C:L,10,FALSE) -> 8.6 | I24: Kishor | J24: Feb-Mar 2025
A25: 24 | B25: FnF Settlement | C25: 12829 | D25: NON-OCR | E25: N | F25: Y | G25: Complex | H25: =VLOOKUP(_xlfn.CONCAT(D25,G25),'Estimation Guidelines'!C:L,10,FALSE) -> 8.6 | I25: Ganesh / Tushar | J25: April - May
A26: 25 | B26: Maker-Checker - ACR Letter | D26: NON-OCR | E26: N | F26: Y | G26: Complex | H26: =VLOOKUP(_xlfn.CONCAT(D26,G26),'Estimation Guidelines'!C:L,10,FALSE) -> 8.6 | I26: Ganesh / Tushar | J26: June- July -Aug
A27: 26 | B27: Ticket Creater | C27: 48701 | D27: NON-OCR | E27: Y | F27: Y | G27: Complex | I27: Varun
A28: 27 | B28: Talent Profile Creation BOT | C28: 5310 | D28: NON-OCR | E28: Y | F28: Y | G28: Complex | I28: Varun
A29: 28 | B29: Poornata Status update - SR Update in Transaction | C29: 53182 | D29: NON-OCR | E29: Y | F29: Y | G29: Simple | I29: Viji
A30: 29 | B30: Audit Sampling | D30: NON-OCR | E30: Y | F30: Y | G30: Simple | I30: Viji
A31: 30 | B31: Create a Dashboard | D31: NON-OCR | E31: Y | F31: Y | G31: Simple | I31: Viji
A32: 31 | B32: Cement ticket creator | D32: NON-OCR | E32: Y | F32: Y | G32: Complex | I32: Viji
A33: 32 | B33: Potential Assesment | C33: 6316 | D33: NON-OCR | E33: Y | F33: Y | G33: Medium | I33: Viji
A34: 33 | B34: PH Link Initiation (ABCAP) | C34: 111114 | D34: OCR | E34: N | F34: Y | G34: Complex | H34: =VLOOKUP(_xlfn.CONCAT(D34,G34),'Estimation Guidelines'!C:L,10,FALSE) -> 11.6 | I34: Rutuja , Vibhav | J34: Aug-Sep-Oct
A35: 34 | B35: Cancelling of performance document | C35: 1639 | D35: NON-OCR | E35: N | F35: Y | G35: Medium | H35: =VLOOKUP(_xlfn.CONCAT(D35,G35),'Estimation Guidelines'!C:L,10,FALSE) -> 5.8 | I35: Kishor | J35: April-May 2025
A36: 35 | B36: Creation and Assigning of Curriculum/ Deeplinks/ Online Courses/ Uploading Videos | C36: 2025 | D36: NON-OCR | E36: N | F36: Y | G36: Medium | H36: =VLOOKUP(_xlfn.CONCAT(D36,G36),'Estimation Guidelines'!C:L,10,FALSE) -> 5.8 | I36: Kishor | J36: June-July 2025
A37: 36 | B37: Creation of performance document | C37: 2013 | D37: NON-OCR | E37: N | F37: Y | G37: Complex | H37: =VLOOKUP(_xlfn.CONCAT(D37,G37),'Estimation Guidelines'!C:L,10,FALSE) -> 8.6 | I37: Kishor | J37: Aug-Sep 2025
A38: 37 | B38: Exit_Approval reassignment for Clearance | C38: 1931 | D38: NON-OCR | E38: N | F38: Y | G38: Complex | H38: =VLOOKUP(_xlfn.CONCAT(D38,G38),'Estimation Guidelines'!C:L,10,FALSE) -> 8.6 | I38: Kishor | J38: Oct-Nov 2025
A39: 38 | B39: Holiday Schedule upload | C39: 10287 | D39: NON-OCR | E39: N | F39: Y | G39: Simple | H39: =VLOOKUP(_xlfn.CONCAT(D39,G39),'Estimation Guidelines'!C:L,10,FALSE) -> 4.8 | I39: Kishor | J39: 45992
A40: 39 | B40: Incident Class. / Data / sync issue | C40: 1926 | D40: NON-OCR | E40: N | F40: Y | G40: Medium | H40: =VLOOKUP(_xlfn.CONCAT(D40,G40),'Estimation Guidelines'!C:L,10,FALSE) -> 5.8 | I40: Kishor | J40: Jan - Feb 2026
A41: 40 | B41: JD linkage | C41: 4037 | D41: NON-OCR | E41: N | F41: Y | G41: Medium | H41: =VLOOKUP(_xlfn.CONCAT(D41,G41),'Estimation Guidelines'!C:L,10,FALSE) -> 5.8 | I41: Kishor | J41: March-April 2026
A42: 41 | B42: Job Data Update | C42: 45835 | D42: NON-OCR | E42: N | F42: Y | G42: Medium | H42: =VLOOKUP(_xlfn.CONCAT(D42,G42),'Estimation Guidelines'!C:L,10,FALSE) -> 5.8
A43: 42 | B43: Job Data Update (Resignation, Separation and Transfer) | C43: 4381 | D43: NON-OCR | E43: N | F43: Y | G43: Medium | H43: =VLOOKUP(_xlfn.CONCAT(D43,G43),'Estimation Guidelines'!C:L,10,FALSE) -> 5.8
A44: 43 | B44: Mobility_HR Initiated Transfer | C44: 7125 | D44: NON-OCR | E44: N | F44: Y | G44: Medium | H44: =VLOOKUP(_xlfn.CONCAT(D44,G44),'Estimation Guidelines'!C:L,10,FALSE) -> 5.8
A45: 44 | B45: New/ Old Event | C45: 2192 | D45: NON-OCR | E45: N | F45: Y | G45: Complex | H45: =VLOOKUP(_xlfn.CONCAT(D45,G45),'Estimation Guidelines'!C:L,10,FALSE) -> 8.6
A46: 45 | B46: Onboarding Initiation | C46: 2676 | D46: NON-OCR | E46: N | F46: Y | G46: Complex | H46: =VLOOKUP(_xlfn.CONCAT(D46,G46),'Estimation Guidelines'!C:L,10,FALSE) -> 8.6
A47: 46 | B47: Position Creation/ Updation/ Deactivation and JD Linkage (Job Arch ???) | C47: 9247 | D47: NON-OCR | E47: N | F47: Y | G47: Medium | H47: =VLOOKUP(_xlfn.CONCAT(D47,G47),'Estimation Guidelines'!C:L,10,FALSE) -> 5.8

Sheet RPA RoadMap (3)
B1: RPA Use Cases | L1: 2024 | U1: 2025 | AG1: 2026
A2: Sr# | B2: UseCase Name | C2: Average Transactions (Annual) | D2: OCR / NON-OCR | E2: Already in production | F2: Automation Required | G2: RPA Complexity | H2: Estimated Efforts(Weeks) | I2: Developer | J2: Timeline | K2: Smonth | L2: Apr | M2: May | N2: Jun | O2: Jul | P2: Aug | Q2: Sep | R2: Oct | S2: Nov | T2: Dec | U2: Jan | V2: Feb | W2: Mar | X2: Apr | Y2: May | Z2: Jun | AA2: Jul | AB2: Aug | AC2: Sep | AD2: Oct | AE2: Nov | AF2: Dec | AG2: Jan | AH2: Feb | AI2: Mar | AJ2: Apr | AK2: May
A3: 4 | B3: Job Description Update | C3: 7168 | D3: NON-OCR | E3: N | F3: Y | G3: Complex | H3: =VLOOKUP(_xlfn.CONCAT(D3,G3),'Estimation Guidelines'!C:L,10,FALSE) -> 8.6 | I3: Kishor | J3: Mar-April | K3: 202403 | L3: 1
A4: 20 | B4: National ID, PAN, Aadhar, Passport, Visa, Address | C4: 9845 | D4: OCR | E4: N | F4: Y | G4: Complex | H4: =VLOOKUP(_xlfn.CONCAT(D4,G4),'Estimation Guidelines'!C:L,10,FALSE) -> 11.6 | I4: Rutuja , Vibhav | J4: April - May-June-July | K4: 202404 | L4: 1 | M4: 1 | N4: 1 | O4: 1
A5: 17 | B5: Bank Data Update | C5: 3695 | D5: OCR | E5: N | F5: Y | G5: Medium | H5: =VLOOKUP(_xlfn.CONCAT(D5,G5),'Estimation Guidelines'!C:L,10,FALSE) -> 8.8 | I5: Rutuja , Vibhav | J5: April - May-June-July | K5: 202404 | L5: 1 | M5: 1 | N5: 1 | O5: 1
A6: 19 | B6: Education Data | C6: 2981 | D6: OCR | E6: N | F6: Y | G6: Complex | H6: =VLOOKUP(_xlfn.CONCAT(D6,G6),'Estimation Guidelines'!C:L,10,FALSE) -> 11.6 | I6: Rutuja , Vibhav | J6: April - May-June-July | K6: 202404 | L6: 1 | M6: 1 | N6: 1 | O6: 1
A7: 24 | B7: FnF Settlement | C7: 12829 | D7: NON-OCR | E7: N | F7: Y | G7: Complex | H7: =VLOOKUP(_xlfn.CONCAT(D7,G7),'Estimation Guidelines'!C:L,10,FALSE) -> 8.6 | I7: Ganesh / Tushar | J7: April - May | K7: 202404 | L7: 1 | M7: 1
A8: 38 | B8: Holiday Schedule upload | C8: 10287 | D8: NON-OCR | E8: N | F8: Y | G8: Simple | H8: =VLOOKUP(_xlfn.CONCAT(D8,G8),'Estimation Guidelines'!C:L,10,FALSE) -> 4.8 | I8: Kishor | J8: May | K8: 202405 | M8: 1
A9: 41 | B9: Job Data Update | C9: 45835 | D9: NON-OCR | E9: N | F9: Y | G9: Medium | H9: =VLOOKUP(_xlfn.CONCAT(D9,G9),'Estimation Guidelines'!C:L,10,FALSE) -> 5.8 | I9: Kishor | J9: June- July | K9: 202406 | N9: 1 | O9: 1
A10: 25 | B10: Maker-Checker - ACR Letter | D10: NON-OCR | E10: N | F10: Y | G10: Complex | H10: =VLOOKUP(_xlfn.CONCAT(D10,G10),'Estimation Guidelines'!C:L,10,FALSE) -> 8.6 | I10: Ganesh / Tushar | J10: June- July -Aug | K10: 202406 | N10: 1 | O10: 1 | P10: 1
A11: 33 | B11: PH Link Initiation (ABCAP) | C11: 111114 | D11: OCR | E11: N | F11: Y | G11: Complex | H11: =VLOOKUP(_xlfn.CONCAT(D11,G11),'Estimation Guidelines'!C:L,10,FALSE) -> 11.6 | I11: Rutuja , Vibhav | J11: Aug-Sep-Oct | K11: 202408 | P11: 1 | Q11: 1 | R11: 1
A12: 16 | B12: Poornata ID Creation (Add a Person) (Proposed Process Change) | C12: 8925 | D12: OCR | E12: N | F12: Y | G12: Complex | H12: =VLOOKUP(_xlfn.CONCAT(D12,G12),'Estimation Guidelines'!C:L,10,FALSE) -> 11.6 | I12: Rutuja , Vibhav | J12: Aug-Sep-Oct | K12: 202408 | P12: 1 | Q12: 1 | R12: 1
A13: 18 | B13: Poornata ID creation (Through External Hire) – QC action and update if missing data-Proposed process change | C13: 5854 | D13: OCR | E13: N | F13: Y | G13: Complex | H13: =VLOOKUP(_xlfn.CONCAT(D13,G13),'Estimation Guidelines'!C:L,10,FALSE) -> 11.6 | I13: Rutuja , Vibhav | J13: Aug-Sep-Oct | K13: 202408 | P13: 1 | Q13: 1 | R13: 1
A14: 46 | B14: Position Creation/ Updation/ Deactivation and JD Linkage (Job Arch ???) | C14: 9247 | D14: NON-OCR | E14: N | F14: Y | G14: Medium | H14: =VLOOKUP(_xlfn.CONCAT(D14,G14),'Estimation Guidelines'!C:L,10,FALSE) -> 5.8 | I14: Kishor | J14: Aug-Sep | K14: 202408 | P14: 1 | Q14: 1
A15: 15 | B15: Creation of Potential Assessment Document | C15: 5337 | D15: NON-OCR | E15: N | F15: Y | G15: Complex | H15: =VLOOKUP(_xlfn.CONCAT(D15,G15),'Estimation Guidelines'!C:L,10,FALSE) -> 8.6 | I15: Kishor | J15: Oct-Nov 2024 | K15: 202410 | R15: 1 | S15: 1
A16: 13 | B16: Personal Data Update (Excluding Bulk volume-43,274) | C16: 14504 | D16: OCR | E16: N | F16: Y | G16: Complex | H16: =VLOOKUP(_xlfn.CONCAT(D16,G16),'Estimation Guidelines'!C:L,10,FALSE) -> 11.6 | I16: Rutuja , Vibhav | J16: Nov-Dec-Jan-Feb | K16: 202411 | S16: 1 | T16: 1 | U16: 1
A17: 12 | B17: Job Data Update (Confirmation/Confirmation with pay rate change/Mobility) | C17: 10119 | D17: OCR | E17: N | F17: Y | G17: Complex | H17: =VLOOKUP(_xlfn.CONCAT(D17,G17),'Estimation Guidelines'!C:L,10,FALSE) -> 11.6 | I17: Rutuja , Vibhav | J17: Nov-Dec-Jan-Feb | K17: 202411 | S17: 1 | T17: 1 | U17: 1
A18: 14 | B18: Compensation Update (Excluding bulk volume-71,968) | C18: 7232 | D18: OCR | E18: N | F18: Y | G18: Complex | H18: =VLOOKUP(_xlfn.CONCAT(D18,G18),'Estimation Guidelines'!C:L,10,FALSE) -> 11.6 | I18: Rutuja , Vibhav | J18: Nov-Dec-Jan-Feb | K18: 202411 | S18: 1 | T18: 1 | U18: 1
A19: 22 | B19: Leave Balance upload | C19: 4243 | D19: NON-OCR | E19: N | F19: Y | G19: Complex | H19: =VLOOKUP(_xlfn.CONCAT(D19,G19),'Estimation Guidelines'!C:L,10,FALSE) -> 8.6 | I19: Kishor | J19: Dec-Jan | K19: 202412 | T19: 1 | U19: 1
A20: 23 | B20: BGV initiation and Report upload Initiate – 20 mins Report upload 10 mins | C20: 5228 | D20: NON-OCR | E20: N | F20: Y | G20: Complex | H20: =VLOOKUP(_xlfn.CONCAT(D20,G20),'Estimation Guidelines'!C:L,10,FALSE) -> 8.6 | I20: Rutuja | J20: Feb-Mar 2025 | K20: 202502 | V20: 1 | W20: 1
A21: 34 | B21: Cancelling of performance document | C21: 1639 | D21: NON-OCR | E21: N | F21: Y | G21: Medium | H21: =VLOOKUP(_xlfn.CONCAT(D21,G21),'Estimation Guidelines'!C:L,10,FALSE) -> 5.8 | I21: Kishor | J21: Feb-Mar 2025 | K21: 202502 | V21: 1 | W21: 1
A22: 35 | B22: Creation and Assigning of Curriculum/ Deeplinks/ Online Courses/ Uploading Videos | C22: 2025 | D22: NON-OCR | E22: N | F22: Y | G22: Medium | H22: =VLOOKUP(_xlfn.CONCAT(D22,G22),'Estimation Guidelines'!C:L,10,FALSE) -> 5.8 | I22: Rutuja | J22: Apr-May-25 | K22: 202504 | X22: 1 | Y22: 1
A23: 36 | B23: Creation of performance document | C23: 2013 | D23: NON-OCR | E23: N | F23: Y | G23: Complex | H23: =VLOOKUP(_xlfn.CONCAT(D23,G23),'Estimation Guidelines'!C:L,10,FALSE) -> 8.6 | I23: Kishor | J23: Apr-May-Jun-25 | K23: 202504 | X23: 1 | Y23: 1 | Z23: 1
A24: 37 | B24: Exit_Approval reassignment for Clearance | C24: 1931 | D24: NON-OCR | E24: N | F24: Y | G24: Complex | H24: =VLOOKUP(_xlfn.CONCAT(D24,G24),'Estimation Guidelines'!C:L,10,FALSE) -> 8.6 | I24: Rutuja | J24: Jun-Jul-Aug-25 | K24: 202506 | Z24: 1 | AA24: 1 | AB24: 1
A25: 7 | B25: Data Change – Data Change | C25: 6804 | D25: NON-OCR | E25: N | F25: Y | G25: Medium | H25: =VLOOKUP(_xlfn.CONCAT(D25,G25),'Estimation Guidelines'!C:L,10,FALSE) -> 5.8 | I25: Kishor | J25: 45839 | K25: 202507 | AA25: 1
A26: 40 | B26: JD linkage | C26: 4037 | D26: NON-OCR | E26: N | F26: Y | G26: Medium | H26: =VLOOKUP(_xlfn.CONCAT(D26,G26),'Estimation Guidelines'!C:L,10,FALSE) -> 5.8 | I26: Kishor | J26: Aug-Sep-25 | K26: 202508 | AB26: 1 | AC26: 1
A27: 39 | B27: Incident Class. / Data / sync issue | C27: 1926 | D27: NON-OCR | E27: N | F27: Y | G27: Medium | H27: =VLOOKUP(_xlfn.CONCAT(D27,G27),'Estimation Guidelines'!C:L,10,FALSE) -> 5.8 | I27: Rutuja | J27: Sep-Oct-25 | K27: 202509 | AC27: 1 | AD27: 1
A28: 42 | B28: Job Data Update (Resignation, Separation and Transfer) | C28: 4381 | D28: NON-OCR | E28: N | F28: Y | G28: Medium | H28: =VLOOKUP(_xlfn.CONCAT(D28,G28),'Estimation Guidelines'!C:L,10,FALSE) -> 5.8 | I28: Kishor | J28: Oct-Nov-25 | K28: 202510 | AD28: 1 | AE28: 1
A29: 43 | B29: Mobility_HR Initiated Transfer | C29: 7125 | D29: NON-OCR | E29: N | F29: Y | G29: Medium | H29: =VLOOKUP(_xlfn.CONCAT(D29,G29),'Estimation Guidelines'!C:L,10,FALSE) -> 5.8 | I29: Rutuja | J29: Jan-Feb-26 | K29: 202511 | AE29: 1 | AF29: 1
A30: 8 | B30: External Hire Poornata ID creation | C30: 5170 | D30: NON-OCR | E30: N | F30: Y | G30: Complex | H30: =VLOOKUP(_xlfn.CONCAT(D30,G30),'Estimation Guidelines'!C:L,10,FALSE) -> 8.6 | I30: Kishor | J30: Nov-Dec-25 | K30: 202512 | AF30: 1 | AG30: 1
A31: 10 | B31: Poornata ID Creation (Add a Person) - Excel Template | C31: 5159 | D31: NON-OCR | E31: N | F31: Y | G31: Complex | H31: =VLOOKUP(_xlfn.CONCAT(D31,G31),'Estimation Guidelines'!C:L,10,FALSE) -> 8.6 | I31: Kishor | J31: Mar-Apr-26 | K31: 202601 | AG31: 1 | AH31: 1 | AI31: 1
A32: 44 | B32: New/ Old Event | C32: 2192 | D32: NON-OCR | E32: N | F32: Y | G32: Complex | H32: =VLOOKUP(_xlfn.CONCAT(D32,G32),'Estimation Guidelines'!C:L,10,FALSE) -> 8.6 | I32: Kishor | J32: Dec-Jan-Feb-26 | K32: 202602 | AH32: 1 | AI32: 1
A33: 45 | B33: Onboarding Initiation | C33: 2676 | D33: NON-OCR | E33: N | F33: Y | G33: Complex | H33: =VLOOKUP(_xlfn.CONCAT(D33,G33),'Estimation Guidelines'!C:L,10,FALSE) -> 8.6 | I33: Rutuja | J33: Mar-Apr-May-26 | K33: 202603 | AI33: 1 | AJ33: 1 | AK33: 1
A34: 1 | B34: Data Change – Override Manager | C34: 6089 | D34: NON-OCR | E34: Y | F34: Y | G34: Medium | I34: Varun
A35: 2 | B35: Data Change – Use Position Reports To | C35: 3933 | D35: NON-OCR | E35: Y | F35: Y | G35: Simple | I35: Varun
A36: 3 | B36: Job Architecture | C36: 10692 | D36: NON-OCR | E36: Y | F36: Y | G36: Medium | I36: Varun
A37: 5 | B37: Data Change – Override Person Job Band | C37: 4 | D37: NON-OCR | F37: N
A38: 6 | B38: Data Change – Use Position Job Band | C38: 7 | D38: NON-OCR | F38: N
A39: 9 | B39: Poornata ID creation (Add a Person - Smart HR) | C39: 1057 | D39: NON-OCR | F39: N | G39: Medium
A40: 11 | B40: Poornata ID Creation (Add POI/CWR) | C40: 573 | D40: NON-OCR | F40: N | G40: Complex
A41: 21 | B41: Learning Session creation | C41: 1277 | D41: NON-OCR | F41: N
A42: 26 | B42: Ticket Creater | C42: 48701 | D42: NON-OCR | E42: Y | F42: Y | G42: Complex | I42: Varun
A43: 27 | B43: Talent Profile Creation BOT | C43: 5310 | D43: NON-OCR | E43: Y | F43: Y | G43: Complex | I43: Varun
A44: 28 | B44: Poornata Status update - SR Update in Transaction | C44: 53182 | D44: NON-OCR | E44: Y | F44: Y | G44: Simple | I44: Viji
A45: 29 | B45: Audit Sampling | D45: NON-OCR | E45: Y | F45: Y | G45: Simple | I45: Viji
A46: 30 | B46: Create a Dashboard | D46: NON-OCR | E46: Y | F46: Y | G46: Simple | I46: Viji
A47: 31 | B47: Cement ticket creator | D47: NON-OCR | E47: Y | F47: Y | G47: Complex | I47: Viji
A48: 32 | B48: Potential Assesment | C48: 6316 | D48: NON-OCR | E48: Y | F48: Y | G48: Medium | I48: Viji

Sheet OverallProcesses
A2: Final category | B2: Final catalog | C2: Total
A3: WFA | B3: ABCap Prospective Hire Link Creation | C3: 43
B4: Bank Data Update | C4: 2876
B5: Compensation Update | C5: 78207
B6: Confirmation | C6: 959
B7: Confirmation with Payrate Change | C7: 1204
B8: Confirmation with Payrate Change and Promotion | C8: 29
B9: Data Change - Data Change | C9: 6785
B10: Data Change - Override Manager | C10: 5918
B11: Data Change - Override Person Job Band | C11: 16
B12: Data Change - Use Position Job Band | C12: 10
B13: Data Change - Use Position Reports To | C13: 3657
B14: Exit_Approval reassignment for Clearance | C14: 1920
B15: Exit_Approval reassignment for Resignation | C15: 168
... B55: Personal Data | C55: 1
A56: WFA Total | C56: 212016
A57: JAE | B57: ABCap Prospective Hire Link Creation | C57: 36
B58: Compensation Update | C58: 4
B59: Confirmation | C59: 921
B60: Data Change - Data Change | C60: 19
B61: Data Change - Override Manager | C61: 99
B62: Data Change - Use Position Reports To | C62: 14
B63: Incident Class. / Admin / Tech Issues | C63: 1
B64: JD linkage | C64: 4009
B65: Job Code Creation | C65: 2
B66: Job Data Update | C66: 1372
B67: Job Data Update (Resignation, Separation and Transfer) | C67: 33
B68: Leave Balance upload | C68: 65
B69: Mobility_HR Initiated Transfer | C69: 5
... B78: JAE and Position Management | C78: 16
A79: JAE Total | C79: 32069
A80: TM | B80: Business PMS Calendar Update | C80: 0
B81: Cancellation of Potential Assessment document | C81: 788
B82: Compensation Update | C82: 0
B83: Creation of performance document | C83: 20
B84: Domo Reports Access Request (GVC- Elearning) | C84: 31
B85: Exit_Resignation/Separation/ Termination | C85: 2
B86: Incident Class. / Access Issues | C86: 0
B87: Initiate Background Verification Check | C87: 0
B88: Initiate EP File Check | C88: 0
B89: Job Data Update | C89: 0
B90: Mobility_HR Initiated Transfer | C90: 2
B91: Personal Data Update | C91: 32
B92: Process Queries | C92: 0
... B107: Any other request | C107: 166
A108: TM Total | C108: 20247
A109: TS | B109: ABCap Prospective Hire Link Creation | C109: 2603
B110: ABMCPL - 1st Day joining forms | C110: 8
B111: Blacklisting | C111: 7
B112: Email Notification to Internal B and C category Applicants | C112: 1
B113: Initiate Background Verification Check | C113: 4427
B114: Initiate EJF Verification Process | C114: 9840
B115: Initiate EP File Check | C115: 198
B116: Initiate Medical Check | C116: 45
B117: Job Requisition creation and On-boarding | C117: 90
B118: null | C118: 0
B119: Onboarding Initiation | C119: 2676
B120: Onboarding Initiation request ( confidential hiring) | C120: 1
B121: Poornata ID creation (Through External Hire) - Business | C121: 5
... B128: Job Requisition Creation (Taleo updation and offer extension) | C128: 14
A129: TS Total | C129: 20113
A130: PMS | B130: Approval of documents on system | C130: 331
B131: Assign Goals to Employees | C131: 12
B132: Business PMS Calendar Update | C132: 34
B133: Cancellation of Probation Document | C133: 56
B134: Cancelling of performance document | C134: 1639
B135: Closure of performance document | C135: 209
B136: Confirmation | C136: 5
B137: Creation of performance document | C137: 1993
B138: Creation of Probation Document | C138: 6
B139: Data Change - Override Person Job Band | C139: 1
B140: Data Change - Use Position Reports To | C140: 4
B141: Goal library and sample goal updation | C141: 0
B142: Job Data Update | C142: 5
... B158: Create Venue | C158: 1
A159: PMS Total | C159: 10291
A160: JOB Arch | B160: Data Change - Override Manager | C160: 1
B161: null | C161: 0
B162: Position creation/update | C162: 8512
B163: Standard Job creation/update | C163: 460
A164: JOB Arch Total | C164: 8973
A165: LM | B165: ABMCPL - 1st Day joining forms | C165: 3
B166: Add new user-Bulk | C166: 688
B167: Add Participants | C167: 238
B168: Add Trainer | C168: 10
B169: Adding/Deleting users in Channels/Groups | C169: 16
B170: Admin Access Required | C170: 623
B171: Attendance and Roster Updation | C171: 337
B172: Compensation Update | C172: 1
B173: Create evaluation form | C173: 33
B174: Create Event(s) | C174: 926
B175: Create Session(s) | C175: 475
B176: Creating Online Courses | C176: 1
B177: Creation and Assigning of Curriculum/ Deeplinks/ Online Courses/ Uploading Videos | C177: 11
... B219: (blank) | C219: 7
A220: LM Total | C220: 8465
A221: GVC | B221: Add new user-Bulk | C221: 542
B222: Adding/Deleting users in Channels/Groups | C222: 30
B223: Admin Access Required | C223: 12
B224: Creating Online Courses | C224: 442
...

Sheet Inventory
A1: Sr# | B1: Transaction Name | C1: Priority on Symphony (Filter Used) | D1: Average Transactions (Annual) | E1: Average Transactions (Monthly) | F1: AHT Manual (In Min's) | G1: Total AHT (HR) | H1: Frequency | I1: SLA | J1: Response SLA Resolution SLA (Annual) | K1: Processing Hours | L1: Weekend BOT Run | M1: Peak Period | N1: RPA Priority | O1: Applications Name | P1: Tickets Containing OCR Documents (%) | Q1: OCR Required | R1: Complexity | S1: Impact | T1: RPA AHT (Per Transaction) | U1: Total Hrs (Daily) | V1: Status
A2: 1 | B2: Data Change – Override Manager | C2: WFA_DTCHNG_OVRMGR-MEDIUM | D2: 6089 | E2: =D2/12 -> 507.41667 | F2: 6 | G2: =(E2*F2)/60 -> 50.741667 | H2: Daily | I2: 24 Hrs | J2: 98.81% 99.90% | K2: Business Hours | L2: Yes | M2: March | N2: 1 | O2: Symphony, PeopleSoft Read from Excel | P2: 0.3 | Q2: Non OCR | R2: Medium | S2: High | V2: Deployed in Production
A3: 2 | B3: Data Change – Use Position Reports To | C3: WFA_DTCHNG_USEPOMGR_MEDIUM | D3: 3933 | E3: =D3/12 -> 327.75 | F3: 5 | G3: =(E3*F3)/60 -> 27.3125 | H3: Daily | I3: 24 Hrs | J3: 99.81% 99.90% | K3: Business Hours | L3: Yes | M3: Jun-Aug | N3: 2 | O3: Symphony, PeopleSoft Read from Excel | P3: 0.3 | Q3: Non OCR | R3: Simple | S3: High | V3: Deployed in Production
A4: 3 | B4: Job Architecture | C4: Job Arch_Position_Creation/Updation_High (0-20) | D4: 10692 | E4: =D4/12 -> 891 | F4: 5 | G4: =(E4*F4)/60 -> 74.25 | H4: Daily | I4: 12 Hrs | J4: NA | K4: Business Hours | L4: Yes | M4: Mar-Jun | N4: 3 | O4: Symphony, PeopleSoft Read from Excel | P4: 0 | Q4: Non OCR | R4: Medium | S4: High | V4: Deployed in Production
A5: 4 | B5: Job Description Update | C5: JAE and PM_JDLink_Low(1-330+) | D5: 7168 | E5: =D5/12 -> 597.33333 | F5: 10 | G5: =(E5*F5)/60 -> 99.555556 | H5: Daily | I5: 12 Hrs | J5: NA | K5: Business Hours | L5: Yes | M5: May-Jul | N5: 4 | O5: Symphony, PeopleSoft Read from Excel | P5: 0 | Q5: Non OCR | R5: Complex | S5: High | V5: KT
A6: 5 | B6: Data Change – Override Person Job Band | C6: WFA_DTCHNG_OVRJB_MEDIUM | D6: 4 | E6: =D6/12 -> 0.33333333 | G6: =(E6*F6)/60 -> 0 | I6: 24 Hrs | N6: 5 | O6: Symphony, PeopleSoft Read from Excel | P6: 0 | Q6: Non OCR
A7: 6 | B7: Data Change – Use Position Job Band | C7: WFA_DTCHNG_USPOJB_MEDIUM | D7: 7 | E7: =D7/12 -> 0.58333333 | G7: =(E7*F7)/60 -> 0 | I7: 24 Hrs | N7: 6 | O7: Symphony, PeopleSoft Read from Excel | P7: 0 | Q7: Non OCR
A8: 7 | B8: Data Change – Data Change | C8: WFA_DTCHNG_DTCHNG_MEDIUM | D8: 1372 | E8: =D8/12 -> 114.33333 | G8: =(E8*F8)/60 -> 0 | I8: 24 Hrs | N8: 7 | O8: Symphony, PeopleSoft Read from Excel | P8: 0 | Q8: Non OCR
A9: 8 | B9: External Hire Poornata ID creation | C9: WFA_ExtHireB_High (80 or Less) | D9: 5170 | E9: =D9/12 -> 430.83333 | G9: =(E9*F9)/60 -> 0 | H9: Daily | I9: 12 Hrs | N9: 8 | O9: Symphony, PeopleSoft Read from Excel | P9: 0 | Q9: Non OCR | R9: Complex | S9: High
B10: Poornata ID creation (Add a Person - Smart HR) | C10: WFA_SmrtAddprsn_High | D10: 1057 | E10: =D10/12 -> 88.083333 | F10: 5 | G10: =ROUNDUP((E10*F10)/60,2) -> 7.35 | H10: On Demand | I10: 12 Hrs - If volume is less than 30 84 Hrs - if Volum is greater than 30 | O10: Symphony, PeopleSoft Read from Excel | Q10: Non OCR | R10: Medium | S10: Low
B11: Poornata ID Creation (Add a Person) - Excel Template | C11: WFA_Addperson_High (85 or Less) | D11: 5159 | E11: =D11/12 -> 429.91667 | F11: 20 | G11: =ROUNDUP((E11*F11)/60,2) -> 143.31 | H11: On Demand | I11: 12 Hrs - If volume is less than 30 84 Hrs - if Volum is greater than 30 | O11: Symphony, PeopleSoft Read from Excel | Q11: Non OCR | R11: Complex | S11: High
B12: Poornata ID Creation (Add POI/CWR) | C12: WFA_AddaPersnPOI/CWR_High (80 or Less) | D12: 573 | E12: =D12/12 -> 47.75 | F12: 10 | G12: =ROUNDUP((E12*F12)/60,2) -> 7.96 | H12: On Demand | I12: 12 Hrs - If volume is less than 30 84 Hrs - if Volum is greater than 30 | O12: Symphony, PeopleSoft Read from Excel | Q12: Non OCR | R12: Complex | S12: Low
A13: 9 | B13: Job Data Update (Confirmation/Confirmation with pay rate change/Mobility) | D13: 10119 | E13: =D13/12 -> 843.25 | F13: 5 | G13: =ROUNDUP((E13*F13)/60,2) -> 70.28 | H13: Daily | I13: 12 Hrs | K13: Business Hours | O13: Symphony, PeopleSoft Read from Excel | P13: 0.6 | Q13: OCR | R13: Complex | S13: High
A14: 10 | B14: Personal Data Update (Excluding Bulk volume-43,274) | C14: WFA_Prsnl_Low (1 to 240) | D14: 14504 | E14: =D14/12 -> 1208.6667 | F14: 10 | G14: =ROUNDUP((E14*F14)/60,2) -> 201.45 | H14: Daily | I14: 36 Hrs - If volume is less than 30 84 Hrs - if Volum is greater than 30 | K14: Business Hours | O14: Symphony, PeopleSoft Read from Excel | P14: 0.2 | Q14: OCR | R14: Complex | S14: High
A15: 11 | B15: Compensation Update (Excluding bulk volume-71,968) | C15: WFA_JobUpd(Comp)_High ( 70 or Less) | D15: 7232 | E15: =D15/12 -> 602.66667 | F15: 15 | G15: =ROUNDUP((E15*F15)/60,2) -> 150.67 | H15: Daily | I15: 12 Hrs - If volume is less than 30 84 Hrs - if Volum is greater than 30 | K15: Business Hours | O15: Symphony, PeopleSoft Read from document/Excel | P15: 0.2 | Q15: OCR | R15: Complex | S15: High
A16: 12 | B16: Creation of Potential Assessment Document | C16: TM_CrtPAD_High (1 to 30) | D16: 5337 | E16: =D16/12 -> 444.75 | F16: 5 | G16: =ROUNDUP((E16*F16)/60,2) -> 37.07 | H16: Daily | K16: Business Hours | O16: Symphony, PeopleSoft Read from document/Excel | P16: 0 | Q16: Non OCR | R16: check with Anuja | S16: High
A17: 13 | B17: Poornata ID Creation (Add a Person) (Proposed Process Change) | D17: 8925 | E17: =D17/12 -> 743.75 | F17: 25 | G17: =ROUNDUP((E17*F17)/60,2) -> 309.9 | I17: 12 Hrs | O17: Symphony, PeopleSoft Read from document/Excel | P17: 0.9 | Q17: OCR | R17: Complex
A18: 14 | B18: Bank Data Update | C18: WFA_BankDataUpdate_1-30_High | D18: 3695 | E18: =D18/12 -> 307.91667 | F18: 8 | G18: =ROUNDUP((E18*F18)/60,2) -> 41.06 | H18: Weekly | K18: Business Hours | M18: Every Month 10th to 25th | O18: Symphony, PeopleSoft Read from document/Excel | P18: 0.9 | Q18: OCR | R18: Medium | S18: Medium
A19: 15 | B19: Poornata ID creation (Through External Hire) – QC action and update if missing data-Proposed process change | D19: 5854 | E19: =D19/12 -> 487.83333 | F19: 25 | G19: =ROUNDUP((E19*F19)/60,2) -> 203.27 | I19: 12 Hrs | O19: Onboarding tool, PeopleSoft Read from document/Excel | P19: 0.9 | Q19: OCR
A20: 16 | B20: Education Data | C20: ESS_Edu_Low | D20: 2981 | E20: =D20/12 -> 248.41667 | F20: 7 | G20: =ROUNDUP((E20*F20)/60,2) -> 28.99 | H20: Daily | I20: 36 Hrs | K20: Business Hours | O20: Symphony, PeopleSoft Read from document/Excel | P20: 0.9 | Q20: OCR | R20: Complex | S20: High
A21: 17 | B21: National ID, PAN, Aadhar, Passport, Visa, Address | C21: ESS_AddChg_Low ESS_Ppst_Low ESS_Visa_Low ESS_NationID_High | D21: 495 | E21: =D21/12 -> 41.25 | F21: 10 | G21: =ROUNDUP((E21*F21)/60,2) -> 6.88 | H21: Weekly | I21: 36 Hrs | K21: Business Hours | O21: Symphony, PeopleSoft Read from document/Excel | P21: 0.9 | Q21: OCR | R21: Medium | S21: High
A22: 18 | B22: Learning Session creation | C22: LM_Crt_Sess_Medium (1 to 50) | D22: 1277 | E22: =D22/12 -> 106.41667 | F22: 20 | G22: =ROUNDUP((E22*F22)/60,2) -> 35.48 | H22: Weekly | I22: 24 Hrs | K22: Business Hours | O22: Symphony, CSOD Read from Excel | P22: 0 | Q22: Non OCR | S22: Medium
A23: 19 | B23: Leave Balance upload | C23: WFA_Leave Balance upload_Medium | D23: 4243 | E23: =D23/12 -> 353.58333 | F23: 12 | G23: =ROUNDUP((E23*F23)/60,2) -> 70.72 | H23: Monthly | I23: 24 Hrs | K23: Business Hours | M23: Every End Activity - Dec to Jan | O23: Symphony, PeopleSoft Read from Excel | P23: 0 | Q23: Non OCR | R23: Complex | S23: Medium
A24: 20 | B24: BGV initiation and Report upload Initiate – 20 mins Report upload 10 mins | C24: TS_BGV_Medium (1-30) | D24: 5228 | E24: =D24/12 -> 435.66667 | F24: 30 | G24: =ROUNDUP((E24*F24)/60,2) -> 217.84 | H24: Daily | I24: 24 Hrs | K24: Business Hours | O24: On boarding, One drive, Outlook and DMS | P24: 0 | Q24: Non OCR | R24: Complex | S24: High
G25: =ROUNDUP((E25*F25)/60,2) -> 0
A26: 21 | B26: FnF Settlement | D26: 12829 | E26: =D26/12 -> 1069.0833 | G26: =ROUNDUP((E26*F26)/60,2) -> 0 | O26: Excel, Payroll system | Q26: non OCR | R26: Complex | S26: High
A27: 22 | B27: Maker-Checker - ACR Letter | G27: =ROUNDUP((E27*F27)/60,2) -> 0 | O27: People Soft, PDF, Excel | Q27: non OCR | R27: Complex | S27: High
A28: 23 | B28: Ticket Creater | D28: 48701 | E28: =D28/12 -> 4058.4167 | G28: =ROUNDUP((E28*F28)/60,2) -> 0 | H28: Daily | K28: Business Hours | L28: Yes | M28: year | N28: 1 | O28: Symphony, PeopleSoft Read from Excel | Q28: non OCR | V28: Deployed in Production | X28: 44643 | Y28: =X28/11 -> 4058.4545 | Z28: =Y28*12 -> 48701.455
A29: 24 | B29: Talent Profile Creation BOT | D29: 5310 | E29: 442.5 | G29: =ROUNDUP((E29*F29)/60,2) -> 0 | H29: Based on requirement | K29: Business Hours | L29: Yes | M29: year | N29: 2 | O29: PeopleSoft Read from Excel,PDF | Q29: non OCR | V29: Deployed in Production
A30: 25 | B30: Poornata Status update - SR Update in Transaction | D30: 53182 | E30: 4431.8333 | G30: =ROUNDUP((E30*F30)/60,2) -> 0 | H30: Daily | K30: Business Hours | L30: Yes | M30: year | N30: 1 | O30: PeopleSoft Read from Excel | Q30: non OCR | V30: Deployed in Production
A31: 26 | B31: Audit Sampling | G31: =ROUNDUP((E31*F31)/60,2) -> 0 | H31: Based on requirement | K31: Business Hours | L31: Yes | M31: year | N31: 2 | O31: Read from Excel | Q31: non OCR | V31: Deployed in Production
A32: 27 | B32: Create a Dashboard | G32: =ROUNDUP((E32*F32)/60,2) -> 0 | H32: Daily | K32: Business Hours | L32: Yes | M32: year | N32: 1 | O32: Read from Excel,Outlook | Q32: non OCR
A33: 28 | B33: Cement ticket creator | G33: =ROUNDUP((E33*F33)/60,2) -> 0 | H33: Daily | K33: Business Hours | L33: Yes | M33: year | N33: 1 | O33: Symphony, PeopleSoft Read from Excel | Q33: non OCR
A34: 27 | B34: Potential Assesment | C34: Was built on Priority | G34: =ROUNDUP((E34*F34)/60,2) -> 0 | H34: Based on requirement | K34: Business Hours | L34: Yes | M34: Oct-Dec | N34: 1 | O34: Symphony, PeopleSoft Read from Excel | Q34: non OCR | V34: Deployed in Production
A35: 28 | B35: PH Link Initiation (ABCAP) | C35: TS_Onbrd_High | D35: 6316 | E35: =D35/12 -> 526.33333 | F35: 10 | H35: Daily | I35: 12 Hrs | K35: Business Hours | L35: Yes | M35: year | O35: Symphony, ALT Recruit | Q35: OCR | R35: Complex | S35: High
B36: Total | D36: =SUM(D2:D24) -> 111114 | F36: =SUM(F2:F24) -> 233 | T36: =SUM(T2:T24) -> 0 | U36: =SUM(U2:U24) -> 0

Sheet Sheet1
A1: Automation Required | B1: Y
A3: Count of UseCase Name | B3: Column Labels
A4: RPA UseCases | B4: Complex | C4: Medium | D4: Simple | E4: Grand Total
A5: NON-OCR | B5: 15 | C5: 12 | D5: 5 | E5: 32
A6: OCR | B6: 8 | C6: 1 | E6: 9
A7: Grand Total | B7: 23 | C7: 13 | D7: 5 | E7: 41

Sheet Sheet2
A3: Row Labels | B3: Sum of Average Transactions (Annual)
A4: NON-OCR | B4: 284393
A5: OCR | B5: 174269
A6: (blank)
A7: Grand Total | B7: 458662

Sheet Complexity Guidelines
A2: Parameter | B2: Simple | C2: Medium | D2: Complex
A3: Definitions | B3: Tasks does not have any manual non digital inputs like | C3: - Tasks have a maximum of simple binary decision-making steps like Yes/No etc. | D3: - Tasks have handoffs between activities and the linkages have to be accurately managed.
B4: - Scanned images | C4: - Data Transformation | D4: - Nested Tasks / Activities
B5: - Unstructured data | C5: - Application based Authentication Handing | D5: - Multiple application interfaces
B6: - Handwritten documents etc.
A7: Number of applications used in the task? | B7: 3 Max | C7: 4 Max | D7: 5 Max
A8: (MS Excel, Outlook, SAP or a web browser, DB, Custom Application etc)
A9: - In case of SAP / Web application, each tcode / screen or web page will be treated as a separate application
A10: How many fields does the task have overall? (Sum the number of fields on all screens involved) | B10: 01-35 | C10: 35-75 | D10: 75-125
A11: What kind of decisions are taken to complete the task | B11: The tasks is linear - there are no decisions to be taken | C11: The tasks involves simple decisions (yes/no type) | D11: The tasks involves complex & multiple decisions
A12: Number of rules/conditions | B12: 5 | C12: 6 | D12: 12
A13: Multi Factor Authentication / Captcha / QR Code | B13: No | C13: Yes | D13: Yes
A14: Any task which cannot accomplish without Human supervision / checks (Example: Approvals, Digital Signature or any Complex decision) | B14: No | C14: No | D14: Yes
A15: Are any of the applications accessed via Citrix/VDI? | B15: No | C15: No | D15: Yes
A16: Is your input data only digital? | B16: Yes | C16: Yes | D16: Yes
A17: Input Channels Considered (Outlook, Files, ERP, Web downloads) | B17: 2 | C17: 4 | D17: 6
A18: Any task that require pattern recognition / Sentiment & Emotion Analysis (Example: Any decision making activity based on email received or any feedback survey) | B18: No | C18: No | D18: Yes
A19: Is your input data is structured/Unstructured? | B19: Structured Excel, Word, Text Files | C19: Form Based PDF, Fillable Word Forms | D19: Unstructured Documents, Scanned Images, Handwritten Documents
A20: Number of Files/file Types processed (Excel, Google Sheets, Word, .csv, .txt) | B20: 3 | C20: 5 | D20: 7
A21: Exception handling - Application and Logic | B21: 6 Max | C21: 10 Max | D21: 15 Max

Sheet ROI
A2: Use Case Meta Data | I2: Existing Manual Daily Cost | O2: Savings | Q2: BOT Daily Cost | Z2: ROI
A3: #Priority | B3: UseCase | C3: Already in Production | D3: AverageTransactions(Annual) | E3: OCR/NON-OCR | F3: Frequency | G3: Complexity | H3: Manual MHT / AHT in Min /Transaction | I3: Manual FTE Required/Day | J3: FTE Cost (Per Day) | K3: Seat Cost (Per Day) | L3: Employee Cost (Others - Paid by )* Per Day | M3: Other OPEX Cost*Per Day | N3: Total Cost (Per Day) | O3: FTE Saved/Day | P3: BOT MHT / AHT (Min) | Q3: BOT FTE Required / Day | R3: FTE Cost After BOT Implementation(Per Day) | S3: Infra Cost (Per Day) | T3: License Cost (Per Day) | W3: Development & Support | Y3: Total Cost (Excluding Development & Creater Cost) | Z3: ROI (Per Day) | AA3: ROI In Percent
T4: Runner | U4: Creater | V4: OCR | W4: Development | X4: Support
A6: Overall Program ROI

Sheet License
A2: Total License | E2: Bots Planned | F2: Annual Transactions | G2: Including 20% Buffer Transactions | H2: Monthly Transactions | I2: Daily Transactions | J2: Daily Total time (Mins)
A3: Runner License | B3: 0 | E3: 23 | F3: =SUM(ROI!D5:D5) -> 0 | G3: =(F3*20%)+F3 -> 0 | H3: =G3/12 -> 0 | I3: =H3/30 -> 0 | J3: =I3*AVERAGE(ROI!P5:P5) -> #DIV/0!
A4: Creator | B4: 0 | E4: Mins in 24 hours | J4: 1440
E5: Runner Licenses | J5: =J3/J4 -> #DIV/0!
A6: Allocated License | E6: Evaluate every 3month based on Bots in production
A7: Runner License | B7: 0 | C7: Existing Prod. Bots
C8: Ticket Creation
A10: Available | E10: Bots Planned | F10: Annual Transactions | G10: Including 20% Buffer Transactions | H10: Monthly Transactions | I10: Daily Transactions | J10: Daily Total time (Mins)
A11: Runner License | B11: 1 | E11: 23 | F11: =SUM(ROI!D5:D5) -> 0 | G11: =(F11*20%)+F11 -> 0 | H11: =G11/12 -> 0 | I11: =H11/30 -> 0 | J11: =I11*AVERAGE(ROI!P5:P5) -> #DIV/0!
B12: 1 | E12: Mins in 12 hours | J12: 720
A13: Creator | B13: 0 | C13: Developer 1 | E13: Runner Licenses | J13: =J11/J12 -> #DIV/0!
B14: 0 | C14: Developer 2 | E14: Evaluate every 3month based on Bots in production
B15: 0 | C15: Developer 3
B16: 0 | C16: Developer 4

Sheet RPA RoadMap
D1: =SUBTOTAL(9,D4:D500) -> 478662 | H1: =SUBTOTAL(9,H4:H500) -> 54.695638 | I1: =SUBTOTAL(9,I4:I500) -> 30.732741 | J1: =SUBTOTAL(9,J4:J500) -> 28132600 | K1: =SUBTOTAL(9,K4:K500) -> 18439645 | L1: =K1/J1 -> 0.65545469 | M1: >1500
B2: RPA Use Cases | S2: 2024 | AB2: 2025 | AN2: 2026
A3: Sr# | B3: UseCase Name | D3: Average Transactions (Annual) | E3: OCR / NON-OCR | F3: Frequency | G3: AHT (Manual) Mins | H3: FTE Manual | I3: FTE Saved | J3: FTE Manual Cost (INR) | K3: FTE Saved Cost (INR) | L3: Already in production | M3: Automation Required | N3: RPA Complexity | O3: Estimated Efforts(Weeks) | P3: Developer | Q3: Timeline | R3: Smonth | S3: Apr | T3: May | U3: Jun | V3: Jul | W3: Aug | X3: Sep | Y3: Oct | Z3: Nov | AA3: Dec | AB3: Jan | AC3: Feb | AD3: Mar | AE3: Apr | AF3: May | AG3: Jun | AH3: Jul | AI3: Aug | AJ3: Sep | AK3: Oct | AL3: Nov | AM3: Dec | AN3: Jan | AO3: Feb | AP3: Mar | AQ3: Apr | AR3: May
A4: 4 | B4: Job Description Update | D4: 7168 | E4: NON-OCR | F4: =VLOOKUP('RPA RoadMap'!$B4,Inventory!$B$1:$N$38,7,FALSE) -> Daily | G4: =VLOOKUP('RPA RoadMap'!$B4,Inventory!$B$1:$N$38,5,FALSE) -> 10 | H4: =((D4/200)*G4)/60/6.5 -> 0.91897436 | I4: =H4*0.6 -> 0.55138462 | J4: =H4*600000 -> 551384.62 | K4: =I4*600000 -> 330830.77 | L4: N | M4: Y | N4: Complex | O4: =VLOOKUP(_xlfn.CONCAT(E4,N4),'Estimation Guidelines'!C:L,10,FALSE) -> 8.6 | P4: Kishor | Q4: Mar-April | R4: 202403 | S4: 1
A5: 20 | B5: National ID, PAN, Aadhar, Passport, Visa, Address | D5: 9845 | E5: OCR | F5: =VLOOKUP('RPA RoadMap'!$B5,Inventory!$B$1:$N$38,7,FALSE) -> Weekly | G5: =VLOOKUP('RPA RoadMap'!$B5,Inventory!$B$1:$N$38,5,FALSE) -> 10 | H5: =((D5/200)*G5)/60/6.5 -> 1.2621795 | I5: =H5*0.6 -> 0.75730769 | J5: =H5*600000 -> 757307.69 | K5: =I5*600000 -> 454384.62 | L5: N | M5: Y | N5: Complex | O5: =VLOOKUP(_xlfn.CONCAT(E5,N5),'Estimation Guidelines'!C:L,10,FALSE) -> 11.6 | P5: Rutuja , RPADEV01 | Q5: April - May-June-July | R5: 202404 | S5: 1 | T5: 1 | U5: 1 | V5: 1
A6: 17 | B6: Bank Data Update | D6: 3695 | E6: OCR | F6: =VLOOKUP('RPA RoadMap'!$B6,Inventory!$B$1:$N$38,7,FALSE) -> Weekly | G6: =VLOOKUP('RPA RoadMap'!$B6,Inventory!$B$1:$N$38,5,FALSE) -> 8 | H6: =((D6/200)*G6)/60/6.5 -> 0.37897436 | I6: =H6*0.8 -> 0.30317949 | J6: =H6*600000 -> 227384.62 | K6: =I6*600000 -> 181907.69 | L6: N | M6: Y | N6: Medium | O6: =VLOOKUP(_xlfn.CONCAT(E6,N6),'Estimation Guidelines'!C:L,10,FALSE) -> 8.8 | P6: Rutuja , RPADEV01 | Q6: April - May-June-July | R6: 202404 | S6: 1 | T6: 1 | U6: 1 | V6: 1
A7: 19 | B7: Education Data | D7: 2981 | E7: OCR | F7: =VLOOKUP('RPA RoadMap'!$B7,Inventory!$B$1:$N$38,7,FALSE) -> Daily | G7: =VLOOKUP('RPA RoadMap'!$B7,Inventory!$B$1:$N$38,5,FALSE) -> 7 | H7: =((D7/200)*G7)/60/6.5 -> 0.26752564 | I7: =H7*0.6 -> 0.16051538 | J7: =H7*600000 -> 160515.38 | K7: =I7*600000 -> 96309.231 | L7: N | M7: Y | N7: Complex | O7: =VLOOKUP(_xlfn.CONCAT(E7,N7),'Estimation Guidelines'!C:L,10,FALSE) -> 11.6 | P7: Rutuja , RPADEV01 | Q7: April - May-June-July | R7: 202404 | S7: 1 | T7: 1 | U7: 1 | V7: 1
A8: 24 | B8: FnF Settlement | D8: 12829 | E8: NON-OCR | F8: Monthly | G8: 10 | H8: =((D8/200)*G8)/60/6.5 -> 1.6447436 | I8: =H8*0.6 -> 0.98684615 | J8: =H8*600000 -> 986846.15 | K8: =I8*600000 -> 592107.69 | L8: N | M8: Y | N8: Complex | O8: =VLOOKUP(_xlfn.CONCAT(E8,N8),'Estimation Guidelines'!C:L,10,FALSE) -> 8.6 | P8: Ganesh / Tushar | Q8: April - May | R8: 202404 | S8: 1 | T8: 1
A9: 38 | B9: Holiday Schedule upload | D9: 10287 | E9: NON-OCR | F9: Monthly | G9: 10 | H9: =((D9/200)*G9)/60/6.5 -> 1.3188462 | I9: =H9*0.9 -> 1.1869615 | J9: =H9*600000 -> 791307.69 | K9: =I9*600000 -> 712176.92 | L9: N | M9: Y | N9: Simple | O9: =VLOOKUP(_xlfn.CONCAT(E9,N9),'Estimation Guidelines'!C:L,10,FALSE) -> 4.8 | P9: Kishor | Q9: May | R9: 202405 | T9: 1
A10: 41 | B10: Job Data Update | D10: 45835 | E10: NON-OCR | F10: Daily | G10: 10 | H10: =((D10/200)*G10)/60/6.5 -> 5.8762821 | I10: =H10*0.8 -> 4.7010256 | J10: =H10*600000 -> 3525769.2 | K10: =I10*600000 -> 2820615.4 | L10: N | M10: Y | N10: Medium | O10: =VLOOKUP(_xlfn.CONCAT(E10,N10),'Estimation Guidelines'!C:L,10,FALSE) -> 5.8 | P10: Kishor | Q10: June- July | R10: 202406 | U10: 1 | V10: 1
A11: 25 | B11: Maker-Checker - ACR Letter | D11: 5000 | E11: NON-OCR | F11: Annual | G11: 10 | H11: =((D11/200)*G11)/60/6.5 -> 0.64102564 | I11: =H11*0.6 -> 0.38461538 | J11: =H11*600000 -> 384615.38 | K11: =I11*600000 -> 230769.23 | L11: N | M11: Y | N11: Complex | O11: =VLOOKUP(_xlfn.CONCAT(E11,N11),'Estimation Guidelines'!C:L,10,FALSE) -> 8.6 | P11: Ganesh / Tushar | Q11: June- July -Aug | R11: 202406 | U11: 1 | V11: 1 | W11: 1
A12: 33 | B12: PH Link Initiation (ABCAP) | D12: 111114 | E12: OCR | F12: =VLOOKUP('RPA RoadMap'!$B12,Inventory!$B$1:$N$38,7,FALSE) -> Daily | G12: =VLOOKUP('RPA RoadMap'!$B12,Inventory!$B$1:$N$38,5,FALSE) -> 10 | H12: =((D12/200)*G12)/60/6.5 -> 14.245385 | I12: =H12*0.6 -> 8.5472308 | J12: =H12*600000 -> 8547230.8 | K12: =I12*600000 -> 5128338.5 | L12: N | M12: Y | N12: Complex | O12: =VLOOKUP(_xlfn.CONCAT(E12,N12),'Estimation Guidelines'!C:L,10,FALSE) -> 11.6 | P12: Rutuja , RPADEV01 | Q12: Aug-Sep-Oct | R12: 202408 | W12: 1 | X12: 1 | Y12: 1
A13: 16 | B13: Poornata ID Creation (Add a Person) (Proposed Process Change) | D13: 8925 | E13: OCR | F13: Daily | G13: =VLOOKUP('RPA RoadMap'!$B13,Inventory!$B$1:$N$38,5,FALSE) -> 25 | H13: =((D13/200)*G13)/60/6.5 -> 2.8605769 | I13: =H13*0.6 -> 1.7163462 | J13: =H13*600000 -> 1716346.2 | K13: =I13*600000 -> 1029807.7 | L13: N | M13: Y | N13: Complex | O13: =VLOOKUP(_xlfn.CONCAT(E13,N13),'Estimation Guidelines'!C:L,10,FALSE) -> 11.6 | P13: Rutuja , RPADEV01 | Q13: Aug-Sep-Oct | R13: 202408 | W13: 1 | X13: 1 | Y13: 1
A14: 18 | B14: Poornata ID creation (Through External Hire) – QC action and update if missing data-Proposed process change | D14: 5854 | E14: OCR | F14: Daily | G14: =VLOOKUP('RPA RoadMap'!$B14,Inventory!$B$1:$N$38,5,FALSE) -> 25 | H14: =((D14/200)*G14)/60/6.5 -> 1.8762821 | I14: =H14*0.6 -> 1.1257692 | J14: =H14*600000 -> 1125769.2 | K14: =I14*600000 -> 675461.54 | L14: N | M14: Y | N14: Complex | O14: =VLOOKUP(_xlfn.CONCAT(E14,N14),'Estimation Guidelines'!C:L,10,FALSE) -> 11.6 | P14: Rutuja , RPADEV01 | Q14: Aug-Sep-Oct | R14: 202408 | W14: 1 | X14: 1 | Y14: 1
A15: 46 | B15: Position Creation/ Updation/ Deactivation and JD Linkage (Job Arch ???) | D15: 9247 | E15: NON-OCR | F15: Daily | G15: 10 | H15: =((D15/200)*G15)/60/6.5 -> 1.1855128 | I15: =H15*0.8 -> 0.94841026 | J15: =H15*600000 -> 711307.69 | K15: =I15*600000 -> 569046.15 | L15: N | M15: Y | N15: Medium | O15: =VLOOKUP(_xlfn.CONCAT(E15,N15),'Estimation Guidelines'!C:L,10,FALSE) -> 5.8 | P15: Kishor | Q15: Aug-Sep | R15: 202408 | W15: 1 | X15: 1
A16: 15 | B16: Creation of Potential Assessment Document | D16: 5337 | E16: NON-OCR | F16: =VLOOKUP('RPA RoadMap'!$B16,Inventory!$B$1:$N$38,7,FALSE) -> Daily | G16: =VLOOKUP('RPA RoadMap'!$B16,Inventory!$B$1:$N$38,5,FALSE) -> 5 | H16: =((D16/200)*G16)/60/6.5 -> 0.34211538 | I16: =H16*0.6 -> 0.20526923 | J16: =H16*600000 -> 205269.23 | K16: =I16*600000 -> 123161.54 | L16: N | M16: Y | N16: Complex | O16: =VLOOKUP(_xlfn.CONCAT(E16,N16),'Estimation Guidelines'!C:L,10,FALSE) -> 8.6 | P16: Kishor | Q16: Oct-Nov 2024 | R16: 202410 | Y16: 1 | Z16: 1
A17: 13 | B17: Personal Data Update (Excluding Bulk volume-43,274) | D17: 14504 | E17: OCR | F17: =VLOOKUP('RPA RoadMap'!$B17,Inventory!$B$1:$N$38,7,FALSE) -> Daily | G17: =VLOOKUP('RPA RoadMap'!$B17,Inventory!$B$1:$N$38,5,FALSE) -> 10 | H17: =((D17/200)*G17)/60/6.5 -> 1.8594872 | I17: =H17*0.6 -> 1.1156923 | J17: =H17*600000 -> 1115692.3 | K17: =I17*600000 -> 669415.38 | L17: N | M17: Y | N17: Complex | O17: =VLOOKUP(_xlfn.CONCAT(E17,N17),'Estimation Guidelines'!C:L,10,FALSE) -> 11.6 | P17: Rutuja , RPADEV01 | Q17: Nov-Dec-Jan-Feb | R17: 202411 | Z17: 1 | AA17: 1 | AB17: 1
A18: 12 | B18: Job Data Update (Confirmation/Confirmation with pay rate change/Mobility) | D18: 10119 | E18: OCR | F18: =VLOOKUP('RPA RoadMap'!$B18,Inventory!$B$1:$N$38,7,FALSE) -> Daily | G18: =VLOOKUP('RPA RoadMap'!$B18,Inventory!$B$1:$N$38,5,FALSE) -> 5 | H18: =((D18/200)*G18)/60/6.5 -> 0.64865385 | I18: =H18*0.6 -> 0.38919231 | J18: =H18*600000 -> 389192.31 | K18: =I18*600000 -> 233515.38 | L18: N | M18: Y | N18: Complex | O18: =VLOOKUP(_xlfn.CONCAT(E18,N18),'Estimation Guidelines'!C:L,10,FALSE) -> 11.6 | P18: Rutuja , RPADEV01 | Q18: Nov-Dec-Jan-Feb | R18: 202411 | Z18: 1 | AA18: 1 | AB18: 1
A19: 14 | B19: Compensation Update (Excluding bulk volume-71,968) | D19: 7232 | E19: OCR | F19: =VLOOKUP('RPA RoadMap'!$B19,Inventory!$B$1:$N$38,7,FALSE) -> Daily | G19: =VLOOKUP('RPA RoadMap'!$B19,Inventory!$B$1:$N$38,5,FALSE) -> 15 | H19: =((D19/200)*G19)/60/6.5 -> 1.3907692 | I19: =H19*0.6 -> 0.83446154 | J19: =H19*600000 -> 834461.54 | K19: =I19*600000 -> 500676.92 | L19: N | M19: Y | N19: Complex | O19: =VLOOKUP(_xlfn.CONCAT(E19,N19),'Estimation Guidelines'!C:L,10,FALSE) -> 11.6 | P19: Rutuja , RPADEV01 | Q19: Nov-Dec-Jan-Feb | R19: 202411 | Z19: 1 | AA19: 1 | AB19: 1
A20: 22 | B20: Leave Balance upload | D20: 4243 | E20: NON-OCR | F20: =VLOOKUP('RPA RoadMap'!$B20,Inventory!$B$1:$N$38,7,FALSE) -> Monthly | G20: =VLOOKUP('RPA RoadMap'!$B20,Inventory!$B$1:$N$38,5,FALSE) -> 12 | H20: =((D20/200)*G20)/60/6.5 -> 0.65276923 | I20: =H20*0.6 -> 0.39166154 | J20: =H20*600000 -> 391661.54 | K20: =I20*600000 -> 234996.92 | L20: N | M20: Y | N20: Complex | O20: =VLOOKUP(_xlfn.CONCAT(E20,N20),'Estimation Guidelines'!C:L,10,FALSE) -> 8.6 | P20: Kishor | Q20: Dec-Jan | R20: 202412 | AA20: 1 | AB20: 1
A21: 23 | B21: BGV initiation and Report upload Initiate – 20 mins Report upload 10 mins | D21: 5228 | E21: NON-OCR | F21: =VLOOKUP('RPA RoadMap'!$B21,Inventory!$B$1:$N$38,7,FALSE) -> Daily | G21: =VLOOKUP('RPA RoadMap'!$B21,Inventory!$B$1:$N$38,5,FALSE) -> 30 | H21: =((D21/200)*G21)/60/6.5 -> 2.0107692 | I21: =H21*0.6 -> 1.2064615 | J21: =H21*600000 -> 1206461.5 | K21: =I21*600000 -> 723876.92 | L21: N | M21: Y | N21: Complex | O21: =VLOOKUP(_xlfn.CONCAT(E21,N21),'Estimation Guidelines'!C:L,10,FALSE) -> 8.6 | P21: Rutuja | Q21: Feb-Mar 2025 | R21: 202502 | AC21: 1 | AD21: 1
A22: 34 | B22: Cancelling of performance document | D22: 1639 | E22: NON-OCR | F22: Annual | G22: 10 | H22: =((D22/200)*G22)/60/6.5 -> 0.21012821 | I22: =H22*0.8 -> 0.16810256 | J22: =H22*600000 -> 126076.92 | K22: =I22*600000 -> 100861.54 | L22: N | M22: Y | N22: Medium | O22: =VLOOKUP(_xlfn.CONCAT(E22,N22),'Estimation Guidelines'!C:L,10,FALSE) -> 5.8 | P22: Kishor | Q22: Feb-Mar 2025 | R22: 202502 | AC22: 1 | AD22: 1
A23: 35 | B23: Creation and Assigning of Curriculum/ Deeplinks/ Online Courses/ Uploading Videos | D23: 2025 | E23: NON-OCR | F23: Monthly | G23: 10 | H23: =((D23/200)*G23)/60/6.5 -> 0.25961538 | I23: =H23*0.8 -> 0.20769231 | J23: =H23*600000 -> 155769.23 | K23: =I23*600000 -> 124615.38 | L23: N | M23: Y | N23: Medium | O23: =VLOOKUP(_xlfn.CONCAT(E23,N23),'Estimation Guidelines'!C:L,10,FALSE) -> 5.8 | P23: Rutuja | Q23: Apr-May-25 | R23: 202504 | AE23: 1 | AF23: 1
A24: 36 | B24: Creation of performance document | D24: 2013 | E24: NON-OCR | F24: Annual | G24: 10 | H24: =((D24/200)*G24)/60/6.5 -> 0.25807692 | I24: =H24*0.6 -> 0.15484615 | J24: =H24*600000 -> 154846.15 | K24: =I24*600000 -> 92907.692 | L24: N | M24: Y | N24: Complex | O24: =VLOOKUP(_xlfn.CONCAT(E24,N24),'Estimation Guidelines'!C:L,10,FALSE) -> 8.6 | P24: Kishor | Q24: Apr-May-Jun-25 | R24: 202504 | AE24: 1 | AF24: 1 | AG24: 1
A25: 37 | B25: Exit_Approval reassignment for Clearance | D25: 1931 | E25: NON-OCR | F25: Monthly | G25: 10 | H25: =((D25/200)*G25)/60/6.5 -> 0.2475641 | I25: =H25*0.6 -> 0.14853846 | J25: =H25*600000 -> 148538.46 | K25: =I25*600000 -> 89123.077 | L25: N | M25: Y | N25: Complex | O25: =VLOOKUP(_xlfn.CONCAT(E25,N25),'Estimation Guidelines'!C:L,10,FALSE) -> 8.6 | P25: Rutuja | Q25: Jun-Jul-Aug-25 | R25: 202506 | AG25: 1 | AH25: 1 | AI25: 1
A26: 7 | B26: Data Change – Data Change | D26: 6804 | E26: NON-OCR | F26: Daily | G26: 10 | H26: =((D26/200)*G26)/60/6.5 -> 0.87230769 | I26: =H26*0.8 -> 0.69784615 | J26: =H26*600000 -> 523384.62 | K26: =I26*600000 -> 418707.69 | L26: N | M26: Y | N26: Medium | O26: =VLOOKUP(_xlfn.CONCAT(E26,N26),'Estimation Guidelines'!C:L,10,FALSE) -> 5.8 | P26: Kishor | Q26: 45839 | R26: 202507 | AH26: 1
A27: 40 | B27: JD linkage | D27: 4037 | E27: NON-OCR | F27: Daily | G27: 10 | H27: =((D27/200)*G27)/60/6.5 -> 0.5175641 | I27: =H27*0.8 -> 0.41405128 | J27: =H27*600000 -> 310538.46 | K27: =I27*600000 -> 248430.77 | L27: N | M27: Y | N27: Medium | O27: =VLOOKUP(_xlfn.CONCAT(E27,N27),'Estimation Guidelines'!C:L,10,FALSE) -> 5.8 | P27: Kishor | Q27: Aug-Sep-25 | R27: 202508 | AI27: 1 | AJ27: 1
A28: 39 | B28: Incident Class. / Data / sync issue | D28: 1926 | E28: NON-OCR | F28: Daily | G28: 10 | H28: =((D28/200)*G28)/60/6.5 -> 0.24692308 | I28: =H28*0.8 -> 0.19753846 | J28: =H28*600000 -> 148153.85 | K28: =I28*600000 -> 118523.08 | L28: N | M28: Y | N28: Medium | O28: =VLOOKUP(_xlfn.CONCAT(E28,N28),'Estimation Guidelines'!C:L,10,FALSE) -> 5.8 | P28: Rutuja | Q28: Sep-Oct-25 | R28: 202509 | AJ28: 1 | AK28: 1
A29: 42 | B29: Job Data Update (Resignation, Separation and Transfer) | D29: 4381 | E29: NON-OCR | F29: On Demand | G29: 10 | H29: =((D29/200)*G29)/60/6.5 -> 0.56166667 | I29: =H29*0.8 -> 0.44933333 | J29: =H29*600000 -> 337000 | K29: =I29*600000 -> 269600 | L29: N | M29: Y | N29: Medium | O29: =VLOOKUP(_xlfn.CONCAT(E29,N29),'Estimation Guidelines'!C:L,10,FALSE) -> 5.8 | P29: Kishor | Q29: Oct-Nov-25 | R29: 202510 | AK29: 1 | AL29: 1
A30: 43 | B30: Mobility_HR Initiated Transfer | D30: 7125 | E30: NON-OCR | F30: Monthly | G30: 10 | H30: =((D30/200)*G30)/60/6.5 -> 0.91346154 | I30: =H30*0.8 -> 0.73076923 | J30: =H30*600000 -> 548076.92 | K30: =I30*600000 -> 438461.54 | L30: N | M30: Y | N30: Medium | O30: =VLOOKUP(_xlfn.CONCAT(E30,N30),'Estimation Guidelines'!C:L,10,FALSE) -> 5.8 | P30: Rutuja | Q30: Jan-Feb-26 | R30: 202511 | AL30: 1 | AM30: 1
A31: 8 | B31: External Hire Poornata ID creation | D31: 5170 | E31: NON-OCR | F31: =VLOOKUP('RPA RoadMap'!$B31,Inventory!$B$1:$N$38,7,FALSE) -> Daily | G31: 10 | H31: =((D31/200)*G31)/60/6.5 -> 0.66282051 | I31: =H31*0.6 -> 0.39769231 | J31: =H31*600000 -> 397692.31 | K31: =I31*600000 -> 238615.38 | L31: N | M31: Y | N31: Complex | O31: =VLOOKUP(_xlfn.CONCAT(E31,N31),'Estimation Guidelines'!C:L,10,FALSE) -> 8.6 | P31: Kishor | Q31: Nov-Dec-25 | R31: 202512 | AM31: 1 | AN31: 1
A32: 10 | B32: Poornata ID Creation (Add a Person) - Excel Template | D32: 5159 | E32: NON-OCR | F32: =VLOOKUP('RPA RoadMap'!$B32,Inventory!$B$1:$N$38,7,FALSE) -> On Demand | G32: =VLOOKUP('RPA RoadMap'!$B32,Inventory!$B$1:$N$38,5,FALSE) -> 20 | H32: =((D32/200)*G32)/60/6.5 -> 1.3228205 | I32: =H32*0.6 -> 0.79369231 | J32: =H32*600000 -> 793692.31 | K32: =I32*600000 -> 476215.38 | L32: N | M32: Y | N32: Complex | O32: =VLOOKUP(_xlfn.CONCAT(E32,N32),'Estimation Guidelines'!C:L,10,FALSE) -> 8.6 | P32: Kishor | Q32: Mar-Apr-26 | R32: 202601 | AN32: 1 | AO32: 1 | AP32: 1
A33: 44 | B33: New/ Old Event | D33: 2192 | E33: NON-OCR | F33: Daily | G33: 10 | H33: =((D33/200)*G33)/60/6.5 -> 0.28102564 | I33: =H33*0.6 -> 0.16861538 | J33: =H33*600000 -> 168615.38 | K33: =I33*600000 -> 101169.23 | L33: N | M33: Y | N33: Complex | O33: =VLOOKUP(_xlfn.CONCAT(E33,N33),'Estimation Guidelines'!C:L,10,FALSE) -> 8.6 | P33: Kishor | Q33: Dec-Jan-Feb-26 | R33: 202602 | AO33: 1 | AP33: 1
A34: 45 | B34: Onboarding Initiation | D34: 2676 | E34: NON-OCR | F34: Weekly | G34: 10 | H34: =((D34/200)*G34)/60/6.5 -> 0.34307692 | I34: =H34*0.6 -> 0.20584615 | J34: =H34*600000 -> 205846.15 | K34: =I34*600000 -> 123507.69 | L34: N | M34: Y | N34: Complex | O34: =VLOOKUP(_xlfn.CONCAT(E34,N34),'Estimation Guidelines'!C:L,10,FALSE) -> 8.6 | P34: Rutuja | Q34: Mar-Apr-May-26 | R34: 202603 | AP34: 1 | AQ34: 1 | AR34: 1
A35: 1 | B35: Data Change – Override Manager | D35: 6089 | E35: NON-OCR | F35: =VLOOKUP('RPA RoadMap'!$B35,Inventory!$B$1:$N$38,7,FALSE) -> Daily | G35: =VLOOKUP('RPA RoadMap'!$B35,Inventory!$B$1:$N$38,5,FALSE) -> 6 | H35: =(((D35/200)*G35)/60/6.5)*16.67 -> 7.8079715 | L35: Y | M35: Y | N35: Medium | P35: Varun
A36: 2 | B36: Data Change – Use Position Reports To | D36: 3933 | E36: NON-OCR | F36: =VLOOKUP('RPA RoadMap'!$B36,Inventory!$B$1:$N$38,7,FALSE) -> Daily | G36: =VLOOKUP('RPA RoadMap'!$B36,Inventory!$B$1:$N$38,5,FALSE) -> 5 | L36: Y | M36: Y | N36: Simple | P36: Varun
A37: 3 | B37: Job Architecture | D37: 10692 | E37: NON-OCR | F37: =VLOOKUP('RPA RoadMap'!$B37,Inventory!$B$1:$N$38,7,FALSE) -> Daily | G37: =VLOOKUP('RPA RoadMap'!$B37,Inventory!$B$1:$N$38,5,FALSE) -> 5 | L37: Y | M37: Y | N37: Medium | P37: Varun
A38: 5 | B38: Data Change – Override Person Job Band | D38: 4 | E38: NON-OCR | G38: =VLOOKUP('RPA RoadMap'!$B38,Inventory!$B$1:$N$38,5,FALSE) -> 0 | M38: N
A39: 6 | B39: Data Change – Use Position Job Band | D39: 7 | E39: NON-OCR | G39: =VLOOKUP('RPA RoadMap'!$B39,Inventory!$B$1:$N$38,5,FALSE) -> 0 | M39: N
A40: 9 | B40: Poornata ID creation (Add a Person - Smart HR) | D40: 1057 | E40: NON-OCR | G40: =VLOOKUP('RPA RoadMap'!$B40,Inventory!$B$1:$N$38,5,FALSE) -> 5 | M40: N
A41: 11 | B41: Poornata ID Creation (Add POI/CWR) | D41: 573 | E41: NON-OCR | G41: =VLOOKUP('RPA RoadMap'!$B41,Inventory!$B$1:$N$38,5,FALSE) -> 10 | M41: N
A42: 21 | B42: Learning Session creation | D42: 1277 | E42: NON-OCR | G42: =VLOOKUP('RPA RoadMap'!$B42,Inventory!$B$1:$N$38,5,FALSE) -> 20 | M42: N
A43: 26 | B43: Ticket Creater | D43: 48701 | E43: NON-OCR | F43: =VLOOKUP('RPA RoadMap'!$B43,Inventory!$B$1:$N$38,7,FALSE) -> Daily | G43: 10 | L43: Y | M43: Y | N43: Complex | P43: Varun
A44: 27 | B44: Talent Profile Creation BOT | C44: Peoplesoft feasiblity to download the selected profiles in bulk. Unattended BOT feasiblity | D44: 5310 | E44: NON-OCR | F44: =VLOOKUP('RPA RoadMap'!$B44,Inventory!$B$1:$N$38,7,FALSE) -> Based on requirement | G44: 10 | L44: Y | M44: Y | N44: Complex | P44: Varun
A45: 28 | B45: Poornata Status update - SR Update in Transaction | C45: Child BOT of Ticket Creater | D45: 53182 | E45: NON-OCR | F45: =VLOOKUP('RPA RoadMap'!$B45,Inventory!$B$1:$N$38,7,FALSE) -> Daily | G45: 10 | L45: Y | M45: Y | N45: Simple | P45: Viji
A46: 29 | B46: Audit Sampling | C46: Once in 15 days | D46: 5000 | E46: NON-OCR | F46: =VLOOKUP('RPA RoadMap'!$B46,Inventory!$B$1:$N$38,7,FALSE) -> Based on requirement | G46: 10 | L46: Y | M46: Y | N46: Simple | P46: Viji
A47: 30 | B47: Create a Dashboard | C47: Centralized framework 1) Using powerapps,Onedrive 2) Bot Insights 3) using Oracle database & OCI Reports | D47: 5000 | E47: NON-OCR | F47: =VLOOKUP('RPA RoadMap'!$B47,Inventory!$B$1:$N$38,7,FALSE) -> Daily | G47: 10 | L47: Y | M47: Y | N47: Simple | P47: Viji
A48: 31 | B48: Cement ticket creator | C48: Child BOT of Ticket Creater | D48: 5000 | E48: NON-OCR | F48: =VLOOKUP('RPA RoadMap'!$B48,Inventory!$B$1:$N$38,7,FALSE) -> Daily | G48: 10 | L48: Y | M48: Y | N48: Complex | P48: Viji
A49: 32 | B49: Potential Assesment | C49: Peoplesoft feasiblity to check bulk creation. Unattended BOT feasiblity | D49: 6316 | E49: NON-OCR | F49: =VLOOKUP('RPA RoadMap'!$B49,Inventory!$B$1:$N$38,7,FALSE) -> Based on requirement | G49: 10 | H49: =((D49/200)*G49)/60/6.5 -> 0.80974359 | I49: =H49*0.6 -> 0.48584615 | J49: =H49*600000 -> 485846.15 | K49: =I49*600000 -> 291507.69 | L49: Y | M49: Y | N49: Medium | P49: Viji
B50: OBIEE Sync Failuer BOT

Sheet RPA_SOP_Analysis_ABG Team SI-2
J1: 0.2 | K1: 0.15 | L1: 0.05 | M1: 0.2 | N1: 0.05 | O1: 0.35 | P1: =SUM(J1:O1) -> 1
A2: UseCase Name | B2: Comment | C2: Priority | D2: Average Transactions (Annual) | E2: OCR / NON-OCR | F2: Frequency | G2: AHT (Manual) Mins | H2: Document Referred | I2: SOP Available | J2: Manual Involvement | K2: Complexity | L2: Need Standardisation | M2: Volume | N2: Work with multiple data files | O2: VOC | P2: Scoring Index | Q2: Owner
A3: National ID, PAN, Aadhar, Passport, Visa, Address | C3: 6 | D3: 9845 | E3: OCR | F3: Weekly | G3: 10 | H3: ESS SOP_National ID_SR to IM(2) | I3: Y | J3: 5 | K3: 1 | L3: 5 | M3: 5 | N3: 5 | O3: 5 | P3: =SUM((J$1*$J3),(K$1*$K3),(L$1*$L3)*(M$1*$M3),(N$1*$N3),(O$1*$O3))*100 -> 340 | Q3: Kunal
A4: FnF Settlement | C4: Parallel Execution | D4: 12829 | E4: NON-OCR | F4: Monthly | G4: 10 | I4: N | J4: 5 | K4: 1 | L4: 5 | M4: 5 | N4: 5 | O4: 5 | P4: =SUM((J$1*$J4),(K$1*$K4),(L$1*$L4)*(M$1*$M4),(N$1*$N4),(O$1*$O4))*100 -> 340 | Q4: Kunal
A5: Initiate EJF Verification Process | C5: 1 | D5: =9840+D37 -> 14999 | J5: 5 | K5: 1 | L5: 5 | M5: 4 | N5: 5 | O5: 5 | P5: =SUM((J$1*$J5),(K$1*$K5),(L$1*$L5)*(M$1*$M5),(N$1*$N5),(O$1*$O5))*100 -> 335
A6: AWOO(A world of opprtunity) - OCR | C6: 4 | D6: =150*3*6 -> 2700 | E6: OCR | F6: Yearly | G6: 10 | J6: 5 | K6: 1 | L6: 5 | M6: 2 | N6: 5 | O6: 5 | P6: =SUM((J$1*$J6),(K$1*$K6),(L$1*$L6)*(M$1*$M6),(N$1*$N6),(O$1*$O6))*100 -> 325 | Q6: Asawari
A7: Education Data | C7: 6 | D7: 2981 | E7: OCR | F7: Daily | G7: 7 | H7: ESS SOP_Educational Data_SR to IM | I7: Y | J7: 5 | K7: 1 | L7: 5 | M7: 2 | N7: 5 | O7: 5 | P7: =SUM((J$1*$J7),(K$1*$K7),(L$1*$L7)*(M$1*$M7),(N$1*$N7),(O$1*$O7))*100 -> 325 | Q7: Kunal | R7: SOP not shared but currently working on the project hence aware of the complexity. Sunil will share the SOP soon (as per Swara)
A8: Pratibha - OCR | C8: 3 | D8: =30*3*6 -> 540 | E8: OCR | F8: Yearly | G8: 10 | J8: 5 | K8: 1 | L8: 5 | M8: 1 | N8: 5 | O8: 5 | P8: =SUM((J$1*$J8),(K$1*$K8),(L$1*$L8)*(M$1*$M8),(N$1*$N8),(O$1*$O8))*100 -> 320
A9: PH Link Initiation (ABCAP) | B9: Not Required | D9: 111114 | E9: OCR | F9: Daily | G9: 10 | H9: ABCAP SOP - Initiating Prospective Hire Link(2) | I9: Y | J9: 2 | K9: 4 | L9: 3 | M9: 5 | N9: 3 | O9: 5 | P9: =SUM((J$1*$J9),(K$1*$K9),(L$1*$L9)*(M$1*$M9),(N$1*$N9),(O$1*$O9))*100 -> 305
A10: Exit_Approval reassignment for Clearance | B10: Not Required | D10: 1931 | E10: NON-OCR | F10: Monthly | G10: 10 | H10: Exit Module SOP_V.5 | I10: Y | J10: 3 | K10: 5 | L10: 1 | M10: 2 | N10: 1 | O10: 4 | P10: =SUM((J$1*$J10),(K$1*$K10),(L$1*$L10)*(M$1*$M10),(N$1*$N10),(O$1*$O10))*100 -> 282 | Q10: Kunal
A11: Onboarding Initiation | B11: Part of EJF | C11: xxxx | D11: 2676 | E11: NON-OCR | F11: Weekly | G11: 10 | H11: Alt Onboarding L5 V.2 | I11: Y | J11: 3 | K11: 4 | L11: 2 | M11: 3 | N11: 2 | O11: 4 | P11: =SUM((J$1*$J11),(K$1*$K11),(L$1*$L11)*(M$1*$M11),(N$1*$N11),(O$1*$O11))*100 -> 276 | Q11: Kunal
A12: Poornata ID Creation (Add a Person) (Proposed Process Change) | C12: 2 | D12: 8925 | E12: OCR | F12: Daily | G12: 25 | I12: N | J12: 2 | K12: 4 | L12: 5 | M12: 4 | N12: 1 | O12: 4 | P12: =SUM((J$1*$J12),(K$1*$K12),(L$1*$L12)*(M$1*$M12),(N$1*$N12),(O$1*$O12))*100 -> 265 | Q12: Kunal
A13: Poornata ID creation (Through External Hire) – QC action and update if missing data-Proposed process change | C13: 2 | D13: 5854 | E13: OCR | F13: Daily | G13: 25 | I13: N | J13: 2 | K13: 4 | L13: 5 | M13: 3 | N13: 1 | O13: 4 | P13: =SUM((J$1*$J13),(K$1*$K13),(L$1*$L13)*(M$1*$M13),(N$1*$N13),(O$1*$O13))*100 -> 260 | Q13: Asawari
A14: Job Data Update (Excel Input / Bulk Data Update) | C14: 9 | D14: 45835 | E14: NON-OCR | F14: Daily | G14: 10 | I14: N | J14: 4 | K14: 1 | L14: 5 | M14: 5 | N14: 1 | O14: 3 | P14: =SUM((J$1*$J14),(K$1*$K14),(L$1*$L14)*(M$1*$M14),(N$1*$N14),(O$1*$O14))*100 -> 230 | Q14: Abhishek
A15: Data Change – Data Change | B15: Need at later stage | C15: xxxx | D15: 6804 | E15: NON-OCR | F15: Daily | G15: 10 | I15: N | J15: 3 | K15: 3 | L15: 5 | M15: 3 | N15: 1 | O15: 3 | P15: =SUM((J$1*$J15),(K$1*$K15),(L$1*$L15)*(M$1*$M15),(N$1*$N15),(O$1*$O15))*100 -> 230 | Q15: Abhishek
A16: JD linkage | B16: Not Required | D16: 4037 | E16: NON-OCR | F16: Daily | G16: 10 | H16: JD Update SOP | I16: Y | J16: 1 | K16: 3 | L16: 5 | M16: 3 | N16: 1 | O16: 4 | P16: =SUM((J$1*$J16),(K$1*$K16),(L$1*$L16)*(M$1*$M16),(N$1*$N16),(O$1*$O16))*100 -> 225
A17: Job Data Update (Resignation, Separation and Transfer) | B17: Duplicate | D17: 4381 | E17: NON-OCR | F17: On Demand | G17: 10 | H17: JD Update SOP | I17: Y | J17: 1 | K17: 3 | L17: 5 | M17: 3 | N17: 1 | O17: 4 | P17: =SUM((J$1*$J17),(K$1*$K17),(L$1*$L17)*(M$1*$M17),(N$1*$N17),(O$1*$O17))*100 -> 225 | Q17: Poonam
A18: Mobility_HR Initiated Transfer | B18: Duplicate | D18: 7125 | E18: OCR | F18: Monthly | G18: 10 | H18: Mobility SOP | I18: Y | J18: 1 | K18: 5 | L18: 1 | M18: 4 | N18: 3 | O18: 3 | P18: =SUM((J$1*$J18),(K$1*$K18),(L$1*$L18)*(M$1*$M18),(N$1*$N18),(O$1*$O18))*100 -> 219 | Q18: Kunal
A19: Transfer of performance document | B19: Check script option | C19: 8 | D19: 3558 | J19: 2 | K19: 5 | L19: 5 | M19: 3 | N19: 1 | O19: 2 | P19: =SUM((J$1*$J19),(K$1*$K19),(L$1*$L19)*(M$1*$M19),(N$1*$N19),(O$1*$O19))*100 -> 205 | Q19: Asawari
A20: Creation of performance document | B20: Exception Management | D20: 2013 | E20: NON-OCR | F20: Annual | G20: 10 | H20: SOP_Creation of Performance Document | I20: Y | J20: 4 | K20: 5 | L20: 5 | M20: 2 | N20: 5 | P20: =SUM((J$1*$J20),(K$1*$K20),(L$1*$L20)*(M$1*$M20),(N$1*$N20),(O$1*$O20))*100 -> 190 | Q20: Asawari
A21: Job Description Update | C21: 0 | D21: 7168 | E21: NON-OCR | F21: Daily | G21: 10 | H21: JD Update SOP | I21: Y | J21: 2 | K21: 4 | L21: 4 | M21: 3 | N21: 1 | O21: 1 | P21: =SUM((J$1*$J21),(K$1*$K21),(L$1*$L21)*(M$1*$M21),(N$1*$N21),(O$1*$O21))*100 -> 152 | Q21: Asawari
A22: Holiday Schedule upload | C22: 7 | D22: 10287 | E22: NON-OCR | F22: Monthly | G22: 10 | H22: Holiday Calender Upload SOP | I22: Y | J22: 1 | K22: 5 | L22: 5 | M22: 1 | N22: 1 | O22: 1 | P22: =SUM((J$1*$J22),(K$1*$K22),(L$1*$L22)*(M$1*$M22),(N$1*$N22),(O$1*$O22))*100 -> 140 | Q22: Kunal
A23: Cancelling of performance document | B23: Already backend script available | D23: 1639 | E23: NON-OCR | F23: Annual | G23: 10 | H23: SOP_Cancellation of Performance Document | I23: Y | J23: 3 | K23: 3 | L23: 5 | M23: 2 | N23: 5 | P23: =SUM((J$1*$J23),(K$1*$K23),(L$1*$L23)*(M$1*$M23),(N$1*$N23),(O$1*$O23))*100 -> 140 | Q23: Kunal
A24: Leave Balance upload | B24: Not Required | D24: 4243 | E24: NON-OCR | F24: Monthly | G24: 12 | H24: Leave Balance Upload SOP_V3 | I24: Y | J24: 1 | K24: 5 | L24: 5 | M24: 4 | N24: 5 | P24: =SUM((J$1*$J24),(K$1*$K24),(L$1*$L24)*(M$1*$M24),(N$1*$N24),(O$1*$O24))*100 -> 140 | Q24: Kunal
A25: Bank Data Update | C25: 5 | D25: 3695 | E25: OCR | F25: Weekly | G25: 8 | H25: WFA Global SOP | I25: Y | J25: 1 | K25: 4 | L25: 5 | M25: 2 | N25: 1 | O25: 1 | P25: =SUM((J$1*$J25),(K$1*$K25),(L$1*$L25)*(M$1*$M25),(N$1*$N25),(O$1*$O25))*100 -> 130 | Q25: Abhishek
A26: Creation and Assigning of Curriculum/ Deeplinks/ Online Courses/ Uploading Videos | B26: Learning | C26: TBD | D26: 2025 | E26: NON-OCR | F26: Monthly | G26: 10 | H26: SOP_CSOD_Creation & Assign Curriculum SOP_CSOD_Upload and Assign Online course_V1 SOP_CSOD_Upload and Assign Video_V1 | I26: Y | J26: 1 | K26: 5 | L26: 5 | M26: 2 | N26: 5 | P26: =SUM((J$1*$J26),(K$1*$K26),(L$1*$L26)*(M$1*$M26),(N$1*$N26),(O$1*$O26))*100 -> 130 | Q26: Abhishek
A27: New/ Old Event | B27: Learning | C27: TBD | D27: 2192 | E27: NON-OCR | F27: Daily | G27: 10 | H27: Creating Event, Session & Adding Trainer - Group Creation SOP | I27: Y | J27: 2 | K27: 3 | L27: 1 | M27: 2 | N27: 1 | O27: 1 | P27: =SUM((J$1*$J27),(K$1*$K27),(L$1*$L27)*(M$1*$M27),(N$1*$N27),(O$1*$O27))*100 -> 127 | Q27: Abhishek
A28: Creation of Potential Assessment Document | B28: Already there - Not required | D28: 5337 | E28: NON-OCR | F28: Daily | G28: 5 | H28: SOP_Potential Management_Creation of Potential Assessment Document | I28: Y | J28: 2 | K28: 2 | L28: 1 | M28: 1 | N28: 1 | O28: 1 | P28: =SUM((J$1*$J28),(K$1*$K28),(L$1*$L28)*(M$1*$M28),(N$1*$N28),(O$1*$O28))*100 -> 111 | Q28: Abhishek
A29: Position Creation/ Updation/ Deactivation and JD Linkage (Job Arch) | B29: Already in Production | C29: 0 | D29: 9247 | E29: NON-OCR | F29: Daily | G29: 10 | I29: N | P29: =SUM((J$1*$J29),(K$1*$K29),(L$1*$L29)*(M$1*$M29),(N$1*$N29),(O$1*$O29))*100 -> 0 | Q29: Poonam
A30: Incident Class. / Data / sync issue | B30: Learning | C30: TBD | D30: 1926 | E30: NON-OCR | F30: Daily | G30: 10 | I30: N | P30: =SUM((J$1*$J30),(K$1*$K30),(L$1*$L30)*(M$1*$M30),(N$1*$N30),(O$1*$O30))*100 -> 0 | Q30: Poonam
A31: Maker-Checker - ACR Letter | B31: To be confirmed | D31: 5000 | E31: NON-OCR | F31: Annual | G31: 10 | I31: N | P31: =SUM((J$1*$J31),(K$1*$K31),(L$1*$L31)*(M$1*$M31),(N$1*$N31),(O$1*$O31))*100 -> 0 | Q31: Poonam
A32: Personal Data Update (Excluding Bulk volume-43,274) | B32: Assess Selenium Current build | D32: 14504 | E32: NON-OCR | F32: Daily | G32: 10 | I32: N | P32: =SUM((J$1*$J32),(K$1*$K32),(L$1*$L32)*(M$1*$M32),(N$1*$N32),(O$1*$O32))*100 -> 0 | Q32: Poonam
A33: Job Data Update (Confirmation/Confirmation with pay rate change/Mobility) | B33: TBD- Peoplesoft Letter generation Built | D33: 10119 | E33: OCR | F33: Daily | G33: 5 | I33: N | P33: =SUM((J$1*$J33),(K$1*$K33),(L$1*$L33)*(M$1*$M33),(N$1*$N33),(O$1*$O33))*100 -> 0 | Q33: Poonam
A34: Compensation Update (Excluding bulk volume-71,968) | B34: Not Required | D34: 7232 | E34: OCR | F34: Daily | G34: 15 | I34: N | M34: 5 | P34: =SUM((J$1*$J34),(K$1*$K34),(L$1*$L34)*(M$1*$M34),(N$1*$N34),(O$1*$O34))*100 -> 0 | Q34: Poonam
A35: BGV initiation and Report upload Initiate – 20 mins Report upload 10 mins | B35: Not Required | D35: 5228 | E35: NON-OCR | F35: Daily | G35: 30 | I35: N | M35: 5 | P35: =SUM((J$1*$J35),(K$1*$K35),(L$1*$L35)*(M$1*$M35),(N$1*$N35),(O$1*$O35))*100 -> 0 | Q35: Poonam
A36: External Hire Poornata ID creation | B36: Duplicate | D36: 5170 | E36: NON-OCR | F36: Daily | G36: 10 | I36: N | P36: =SUM((J$1*$J36),(K$1*$K36),(L$1*$L36)*(M$1*$M36),(N$1*$N36),(O$1*$O36))*100 -> 0 | Q36: Poonam
A37: Poornata ID Creation (Add a Person) - Excel Template | B37: Duplicate | D37: 5159 | E37: NON-OCR | F37: On Demand | G37: 20 | I37: N | P37: =SUM((J$1*$J37),(K$1*$K37),(L$1*$L37)*(M$1*$M37),(N$1*$N37),(O$1*$O37))*100 -> 0 | Q37: Asawari
A38: Report generation for talent discussions | B38: Already BOT present | D38: 6131
A39: Position creation/update | B39: Duplicate | D39: 8512

Sheet RPA_SOP_Analysis_ABG Team
J1: 0.2 | K1: 0.15 | L1: 0.05 | M1: 0.2 | N1: 0.05 | O1: 0.35 | P1: =SUM(J1:O1) -> 1
A2: UseCase Name | B2: Comment | C2: Priority | D2: Average Transactions (Annual) | E2: OCR / NON-OCR | F2: Frequency | G2: AHT (Manual) Mins | H2: Document Referred | I2: SOP Available | J2: Manual Involvement | K2: Complexity | L2: Need Standardisation | M2: Volume | N2: Work with multiple data files | O2: VOC | P2: Scoring Index | Q2: Owner
A3: Job Description Update | C3: 0 | D3: 7168 | E3: NON-OCR | F3: Daily | G3: 10 | H3: JD Update SOP | I3: Y | J3: 2 | K3: 2 | L3: 2 | M3: 3 | N3: 1 | O3: 1 | P3: =SUM((J$1*$J3),(K$1*$K3),(L$1*$L3)*(M$1*$M3),(N$1*$N3),(O$1*$O3))*100 -> 116 | Q3: Kunal
A4: Position Creation/ Updation/ Deactivation and JD Linkage (Job Arch) | B4: Already in Production | C4: 0 | D4: 9247 | E4: NON-OCR | F4: Daily | G4: 10 | I4: N | P4: =SUM((J$1*$J4),(K$1*$K4),(L$1*$L4)*(M$1*$M4),(N$1*$N4),(O$1*$O4))*100 -> 0 | Q4: Kunal
A5: Initiate EJF Verification Process | C5: 1 | D5: =9840+D37 -> 12516 | J5: 5 | K5: 5 | L5: 1 | M5: 4 | N5: 5 | O5: 5 | P5: =SUM((J$1*$J5),(K$1*$K5),(L$1*$L5)*(M$1*$M5),(N$1*$N5),(O$1*$O5))*100 -> 379
A6: Poornata ID Creation (Add a Person) (Proposed Process Change) | C6: 2 | D6: 8925 | E6: OCR | F6: Daily | G6: 25 | I6: N | J6: 2 | K6: 2 | L6: 1 | M6: 4 | N6: 1 | O6: 4 | P6: =SUM((J$1*$J6),(K$1*$K6),(L$1*$L6)*(M$1*$M6),(N$1*$N6),(O$1*$O6))*100 -> 219 | Q6: Asawari
A7: Poornata ID creation (Through External Hire) – QC action and update if missing data-Proposed process change | C7: 2 | D7: 5854 | E7: OCR | F7: Daily | G7: 25 | I7: N | J7: 2 | K7: 2 | L7: 1 | M7: 3 | N7: 1 | O7: 4 | P7: =SUM((J$1*$J7),(K$1*$K7),(L$1*$L7)*(M$1*$M7),(N$1*$N7),(O$1*$O7))*100 -> 218 | Q7: Kunal | R7: SOP not shared but currently working on the project hence aware of the complexity. Sunil will share the SOP soon (as per Swara)
A8: Pratibha | C8: 3 | D8: =30*3*6 -> 540 | E8: OCR | F8: Yearly | G8: 10 | J8: 5 | K8: 5 | L8: 1 | M8: 1 | N8: 5 | O8: 5 | P8: =SUM((J$1*$J8),(K$1*$K8),(L$1*$L8)*(M$1*$M8),(N$1*$N8),(O$1*$O8))*100 -> 376
A9: AWOO(A world of opprtunity) | C9: 4 | D9: =150*3*6 -> 2700 | E9: OCR | F9: Yearly | G9: 10 | J9: 5 | K9: 5 | L9: 1 | M9: 2 | N9: 5 | O9: 5 | P9: =SUM((J$1*$J9),(K$1*$K9),(L$1*$L9)*(M$1*$M9),(N$1*$N9),(O$1*$O9))*100 -> 377
A10: Bank Data Update | C10: 5 | D10: 3695 | E10: OCR | F10: Weekly | G10: 8 | H10: WFA Global SOP | I10: Y | J10: 1 | K10: 2 | L10: 1 | M10: 2 | N10: 1 | O10: 1 | P10: =SUM((J$1*$J10),(K$1*$K10),(L$1*$L10)*(M$1*$M10),(N$1*$N10),(O$1*$O10))*100 -> 92 | Q10: Kunal
A11: National ID, PAN, Aadhar, Passport, Visa, Address | C11: 6 | D11: 9845 | E11: OCR | F11: Weekly | G11: 10 | H11: ESS SOP_National ID_SR to IM(2) | I11: Y | J11: 5 | K11: 5 | L11: 1 | M11: 5 | N11: 5 | O11: 5 | P11: =SUM((J$1*$J11),(K$1*$K11),(L$1*$L11)*(M$1*$M11),(N$1*$N11),(O$1*$O11))*100 -> 380 | Q11: Kunal
A12: Education Data | C12: 6 | D12: 2981 | E12: OCR | F12: Daily | G12: 7 | H12: ESS SOP_Educational Data_SR to IM | I12: Y | J12: 5 | K12: 5 | L12: 1 | M12: 2 | N12: 5 | O12: 5 | P12: =SUM((J$1*$J12),(K$1*$K12),(L$1*$L12)*(M$1*$M12),(N$1*$N12),(O$1*$O12))*100 -> 377 | Q12: Kunal
A13: Holiday Schedule upload | C13: 7 | D13: 10287 | E13: NON-OCR | F13: Monthly | G13: 10 | H13: Holiday Calender Upload SOP | I13: Y | J13: 1 | K13: 1 | L13: 1 | M13: 1 | N13: 1 | O13: 1 | P13: =SUM((J$1*$J13),(K$1*$K13),(L$1*$L13)*(M$1*$M13),(N$1*$N13),(O$1*$O13))*100 -> 76 | Q13: Asawari
A14: Creation of performance document | B14: Exception Management | D14: 2013 | E14: NON-OCR | F14: Annual | G14: 10 | H14: SOP_Creation of Performance Document | I14: Y | J14: 4 | K14: 5 | L14: 5 | M14: 2 | N14: 5 | P14: =SUM((J$1*$J14),(K$1*$K14),(L$1*$L14)*(M$1*$M14),(N$1*$N14),(O$1*$O14))*100 -> 190 | Q14: Abhishek
A15: Cancelling of performance document | B15: Already backend script available | D15: 1639 | E15: NON-OCR | F15: Annual | G15: 10 | H15: SOP_Cancellation of Performance Document | I15: Y | J15: 3 | K15: 3 | L15: 5 | M15: 2 | N15: 5 | P15: =SUM((J$1*$J15),(K$1*$K15),(L$1*$L15)*(M$1*$M15),(N$1*$N15),(O$1*$O15))*100 -> 140 | Q15: Abhishek
A16: Transfer of performance document | B16: Check script option | C16: 8 | D16: 3558 | J16: 2 | K16: 1 | L16: 1 | M16: 3 | N16: 1 | O16: 2 | P16: =SUM((J$1*$J16),(K$1*$K16),(L$1*$L16)*(M$1*$M16),(N$1*$N16),(O$1*$O16))*100 -> 133
A17: Data Change – Data Change | B17: Need at later stage | C17: xxxx | D17: 6804 | E17: NON-OCR | F17: Daily | G17: 10 | I17: N | J17: 3 | K17: 3 | L17: 1 | M17: 3 | N17: 1 | O17: 3 | P17: =SUM((J$1*$J17),(K$1*$K17),(L$1*$L17)*(M$1*$M17),(N$1*$N17),(O$1*$O17))*100 -> 218 | Q17: Poonam
A18: FnF Settlement | C18: Parallel Execution | D18: 12829 | E18: NON-OCR | F18: Monthly | G18: 10 | I18: N | J18: 5 | K18: 5 | L18: 1 | M18: 5 | N18: 5 | O18: 5 | P18: =SUM((J$1*$J18),(K$1*$K18),(L$1*$L18)*(M$1*$M18),(N$1*$N18),(O$1*$O18))*100 -> 380 | Q18: Kunal
A19: Job Data Update (Excel Input / Bulk Data Update) | C19: 9 | D19: 45835 | E19: NON-OCR | F19: Daily | G19: 10 | I19: N | J19: 4 | K19: 5 | L19: 1 | M19: 5 | N19: 1 | O19: 3 | P19: =SUM((J$1*$J19),(K$1*$K19),(L$1*$L19)*(M$1*$M19),(N$1*$N19),(O$1*$O19))*100 -> 270 | Q19: Asawari
A20: Maker-Checker - ACR Letter | B20: To be confirmed | D20: 5000 | E20: NON-OCR | F20: Annual | G20: 10 | I20: N | P20: =SUM((J$1*$J20),(K$1*$K20),(L$1*$L20)*(M$1*$M20),(N$1*$N20),(O$1*$O20))*100 -> 0 | Q20: Asawari
A21: PH Link Initiation (ABCAP) | B21: Not Required | D21: 111114 | E21: OCR | F21: Daily | G21: 10 | H21: ABCAP SOP - Initiating Prospective Hire Link(2) | I21: Y | J21: 2 | K21: 4 | L21: 3 | M21: 5 | N21: 3 | O21: 5 | P21: =SUM((J$1*$J21),(K$1*$K21),(L$1*$L21)*(M$1*$M21),(N$1*$N21),(O$1*$O21))*100 -> 305 | Q21: Asawari
A22: Creation of Potential Assessment Document | B22: Already there - Not required | D22: 5337 | E22: NON-OCR | F22: Daily | G22: 5 | H22: SOP_Potential Management_Creation of Potential Assessment Document | I22: Y | J22: 2 | K22: 2 | L22: 1 | M22: 1 | N22: 1 | O22: 1 | P22: =SUM((J$1*$J22),(K$1*$K22),(L$1*$L22)*(M$1*$M22),(N$1*$N22),(O$1*$O22))*100 -> 111 | Q22: Kunal
A23: Personal Data Update (Excluding Bulk volume-43,274) | B23: Assess Selenium Current build | D23: 14504 | E23: NON-OCR | F23: Daily | G23: 10 | I23: N | P23: =SUM((J$1*$J23),(K$1*$K23),(L$1*$L23)*(M$1*$M23),(N$1*$N23),(O$1*$O23))*100 -> 0 | Q23: Kunal
A24: Job Data Update (Confirmation/Confirmation with pay rate change/Mobility) | B24: TBD- Peoplesoft Letter generation Built | D24: 10119 | E24: OCR | F24: Daily | G24: 5 | I24: N | P24: =SUM((J$1*$J24),(K$1*$K24),(L$1*$L24)*(M$1*$M24),(N$1*$N24),(O$1*$O24))*100 -> 0 | Q24: Kunal
A25: Compensation Update (Excluding bulk volume-71,968) | B25: Not Required | D25: 7232 | E25: OCR | F25: Daily | G25: 15 | I25: N | M25: 5 | P25: =SUM((J$1*$J25),(K$1*$K25),(L$1*$L25)*(M$1*$M25),(N$1*$N25),(O$1*$O25))*100 -> 0 | Q25: Abhishek
A26: Leave Balance upload | B26: Not Required | D26: 4243 | E26: NON-OCR | F26: Monthly | G26: 12 | H26: Leave Balance Upload SOP_V3 | I26: Y | J26: 1 | K26: 5 | L26: 5 | M26: 4 | N26: 5 | P26: =SUM((J$1*$J26),(K$1*$K26),(L$1*$L26)*(M$1*$M26),(N$1*$N26),(O$1*$O26))*100 -> 140 | Q26: Abhishek
A27: BGV initiation and Report upload Initiate – 20 mins Report upload 10 mins | B27: Not Required | D27: 5228 | E27: NON-OCR | F27: Daily | G27: 30 | I27: N | M27: 5 | P27: =SUM((J$1*$J27),(K$1*$K27),(L$1*$L27)*(M$1*$M27),(N$1*$N27),(O$1*$O27))*100 -> 0 | Q27: Abhishek
A28: Creation and Assigning of Curriculum/ Deeplinks/ Online Courses/ Uploading Videos | B28: Learning | C28: TBD | D28: 2025 | E28: NON-OCR | F28: Monthly | G28: 10 | H28: SOP_CSOD_Creation & Assign Curriculum SOP_CSOD_Upload and Assign Online course_V1 SOP_CSOD_Upload and Assign Video_V1 | I28: Y | J28: 1 | K28: 5 | L28: 5 | M28: 2 | N28: 5 | P28: =SUM((J$1*$J28),(K$1*$K28),(L$1*$L28)*(M$1*$M28),(N$1*$N28),(O$1*$O28))*100 -> 130 | Q28: Abhishek
A29: Exit_Approval reassignment for Clearance | B29: Not Required | D29: 1931 | E29: NON-OCR | F29: Monthly | G29: 10 | H29: Exit Module SOP_V.5 | I29: Y | J29: 3 | K29: 5 | L29: 1 | M29: 2 | N29: 1 | O29: 4 | P29: =SUM((J$1*$J29),(K$1*$K29),(L$1*$L29)*(M$1*$M29),(N$1*$N29),(O$1*$O29))*100 -> 282 | Q29: Poonam
A30: JD linkage | B30: Not Required | D30: 4037 | E30: NON-OCR | F30: Daily | G30: 10 | H30: JD Update SOP | I30: Y | J30: 1 | K30: 3 | L30: 5 | M30: 3 | N30: 1 | O30: 4 | P30: =SUM((J$1*$J30),(K$1*$K30),(L$1*$L30)*(M$1*$M30),(N$1*$N30),(O$1*$O30))*100 -> 225 | Q30: Poonam
A31: Incident Class. / Data / sync issue | B31: Learning | C31: TBD | D31: 1926 | E31: NON-OCR | F31: Daily | G31: 10 | I31: N | P31: =SUM((J$1*$J31),(K$1*$K31),(L$1*$L31)*(M$1*$M31),(N$1*$N31),(O$1*$O31))*100 -> 0 | Q31: Poonam
A32: Job Data Update (Resignation, Separation and Transfer) | B32: Duplicate | D32: 4381 | E32: NON-OCR | F32: On Demand | G32: 10 | H32: JD Update SOP | I32: Y | J32: 1 | K32: 3 | L32: 5 | M32: 3 | N32: 1 | O32: 4 | P32: =SUM((J$1*$J32),(K$1*$K32),(L$1*$L32)*(M$1*$M32),(N$1*$N32),(O$1*$O32))*100 -> 225 | Q32: Poonam
A33: Mobility_HR Initiated Transfer | B33: Duplicate | D33: 7125 | E33: OCR | F33: Monthly | G33: 10 | H33: Mobility SOP | I33: Y | J33: 1 | K33: 5 | L33: 1 | M33: 4 | N33: 3 | O33: 3 | P33: =SUM((J$1*$J33),(K$1*$K33),(L$1*$L33)*(M$1*$M33),(N$1*$N33),(O$1*$O33))*100 -> 219 | Q33: Poonam
A34: External Hire Poornata ID creation | B34: Duplicate | D34: 5170 | E34: NON-OCR | F34: Daily | G34: 10 | I34: N | P34: =SUM((J$1*$J34),(K$1*$K34),(L$1*$L34)*(M$1*$M34),(N$1*$N34),(O$1*$O34))*100 -> 0 | Q34: Poonam
A35: Poornata ID Creation (Add a Person) - Excel Template | B35: Duplicate | D35: 5159 | E35: NON-OCR | F35: On Demand | G35: 20 | I35: N | P35: =SUM((J$1*$J35),(K$1*$K35),(L$1*$L35)*(M$1*$M35),(N$1*$N35),(O$1*$O35))*100 -> 0 | Q35: Poonam
A36: New/ Old Event | B36: Learning | C36: TBD | D36: 2192 | E36: NON-OCR | F36: Daily | G36: 10 | H36: Creating Event, Session & Adding Trainer - Group Creation SOP | I36: Y | J36: 2 | K36: 3 | L36: 1 | M36: 2 | N36: 1 | O36: 1 | P36: =SUM((J$1*$J36),(K$1*$K36),(L$1*$L36)*(M$1*$M36),(N$1*$N36),(O$1*$O36))*100 -> 127 | Q36: Poonam
A37: Onboarding Initiation | B37: Part of EJF | C37: xxxx | D37: 2676 | E37: NON-OCR | F37: Weekly | G37: 10 | H37: Alt Onboarding L5 V.2 | I37: Y | J37: 3 | K37: 4 | L37: 2 | M37: 3 | N37: 2 | O37: 4 | P37: =SUM((J$1*$J37),(K$1*$K37),(L$1*$L37)*(M$1*$M37),(N$1*$N37),(O$1*$O37))*100 -> 276 | Q37: Asawari
A38: Report generation for talent discussions | B38: Already BOT present | D38: 6131
A39: Position creation/update | B39: Duplicate | D39: 8512

Sheet RPA_SOP_Analysis_ABG Team SI
J1: 0.2 | K1: 0.15 | L1: 0.05 | M1: 0.2 | N1: 0.05 | O1: 0.35 | P1: =SUM(J1:O1) -> 1
A2: UseCase Name | B2: Comment | C2: Priority | D2: Average Transactions (Annual) | E2: OCR / NON-OCR | F2: Frequency | G2: AHT (Manual) Mins | H2: Document Referred | I2: SOP Available | J2: Manual Involvement | K2: Complexity | L2: Need Standardisation | M2: Volume | N2: Work with multiple data files | O2: VOC | P2: Scoring Index | Q2: Owner
A3: National ID, PAN, Aadhar, Passport, Visa, Address | C3: 6 | D3: 9845 | E3: OCR | F3: Weekly | G3: 10 | H3: ESS SOP_National ID_SR to IM(2) | I3: Y | J3: 5 | K3: 1 | L3: 5 | M3: 5 | N3: 5 | O3: 5 | P3: =SUM((J$1*$J3),(K$1*$K3),(L$1*$L3)*(M$1*$M3),(N$1*$N3),(O$1*$O3))*100 -> 340 | Q3: Kunal
A4: FnF Settlement | C4: Parallel Execution | D4: 12829 | E4: NON-OCR | F4: Monthly | G4: 10 | I4: N | J4: 5 | K4: 1 | L4: 5 | M4: 5 | N4: 5 | O4: 5 | P4: =SUM((J$1*$J4),(K$1*$K4),(L$1*$L4)*(M$1*$M4),(N$1*$N4),(O$1*$O4))*100 -> 340 | Q4: Kunal
A5: Initiate EJF Verification Process | C5: 1 | D5: =9840+D37 -> 14999 | J5: 5 | K5: 1 | L5: 5 | M5: 4 | N5: 5 | O5: 5 | P5: =SUM((J$1*$J5),(K$1*$K5),(L$1*$L5)*(M$1*$M5),(N$1*$N5),(O$1*$O5))*100 -> 335
A6: AWOO(A world of opprtunity) | C6: 4 | D6: =150*3*6 -> 2700 | E6: OCR | F6: Yearly | G6: 10 | J6: 5 | K6: 1 | L6: 5 | M6: 2 | N6: 5 | O6: 5 | P6: =SUM((J$1*$J6),(K$1*$K6),(L$1*$L6)*(M$1*$M6),(N$1*$N6),(O$1*$O6))*100 -> 325 | Q6: Asawari
A7: Education Data | C7: 6 | D7: 2981 | E7: OCR | F7: Daily | G7: 7 | H7: ESS SOP_Educational Data_SR to IM | I7: Y | J7: 5 | K7: 1 | L7: 5 | M7: 2 | N7: 5 | O7: 5 | P7: =SUM((J$1*$J7),(K$1*$K7),(L$1*$L7)*(M$1*$M7),(N$1*$N7),(O$1*$O7))*100 -> 325 | Q7: Kunal | R7: SOP not shared but currently working on the project hence aware of the complexity. Sunil will share the SOP soon (as per Swara)
A8: Pratibha | C8: 3 | D8: =30*3*6 -> 540 | E8: OCR | F8: Yearly | G8: 10 | J8: 5 | K8: 1 | L8: 5 | M8: 1 | N8: 5 | O8: 5 | P8: =SUM((J$1*$J8),(K$1*$K8),(L$1*$L8)*(M$1*$M8),(N$1*$N8),(O$1*$O8))*100 -> 320
A9: PH Link Initiation (ABCAP) | B9: Not Required | D9: 111114 | E9: OCR | F9: Daily | G9: 10 | H9: ABCAP SOP - Initiating Prospective Hire Link(2) | I9: Y | J9: 2 | K9: 4 | L9: 3 | M9: 5 | N9: 3 | O9: 5 | P9: =SUM((J$1*$J9),(K$1*$K9),(L$1*$L9)*(M$1*$M9),(N$1*$N9),(O$1*$O9))*100 -> 305
A10: Exit_Approval reassignment for Clearance | B10: Not Required | D10: 1931 | E10: NON-OCR | F10: Monthly | G10: 10 | H10: Exit Module SOP_V.5 | I10: Y | J10: 3 | K10: 5 | L10: 1 | M10: 2 | N10: 1 | O10: 4 | P10: =SUM((J$1*$J10),(K$1*$K10),(L$1*$L10)*(M$1*$M10),(N$1*$N10),(O$1*$O10))*100 -> 282 | Q10: Kunal
A11: Onboarding Initiation | B11: Part of EJF | C11: xxxx | D11: 2676 | E11: NON-OCR | F11: Weekly | G11: 10 | H11: Alt Onboarding L5 V.2 | I11: Y | J11: 3 | K11: 4 | L11: 2 | M11: 3 | N11: 2 | O11: 4 | P11: =SUM((J$1*$J11),(K$1*$K11),(L$1*$L11)*(M$1*$M11),(N$1*$N11),(O$1*$O11))*100 -> 276 | Q11: Kunal
A12: Poornata ID Creation (Add a Person) (Proposed Process Change) | C12: 2 | D12: 8925 | E12: OCR | F12: Daily | G12: 25 | I12: N | J12: 2 | K12: 4 | L12: 5 | M12: 4 | N12: 1 | O12: 4 | P12: =SUM((J$1*$J12),(K$1*$K12),(L$1*$L12)*(M$1*$M12),(N$1*$N12),(O$1*$O12))*100 -> 265 | Q12: Kunal
A13: Poornata ID creation (Through External Hire) – QC action and update if missing data-Proposed process change | C13: 2 | D13: 5854 | E13: OCR | F13: Daily | G13: 25 | I13: N | J13: 2 | K13: 4 | L13: 5 | M13: 3 | N13: 1 | O13: 4 | P13: =SUM((J$1*$J13),(K$1*$K13),(L$1*$L13)*(M$1*$M13),(N$1*$N13),(O$1*$O13))*100 -> 260 | Q13: Asawari
A14: Job Data Update (Excel Input / Bulk Data Update) | C14: 9 | D14: 45835 | E14: NON-OCR | F14: Daily | G14: 10 | I14: N | J14: 4 | K14: 1 | L14: 5 | M14: 5 | N14: 1 | O14: 3 | P14: =SUM((J$1*$J14),(K$1*$K14),(L$1*$L14)*(M$1*$M14),(N$1*$N14),(O$1*$O14))*100 -> 230 | Q14: Abhishek
A15: Data Change – Data Change | B15: Need at later stage | C15: xxxx | D15: 6804 | E15: NON-OCR | F15: Daily | G15: 10 | I15: N | J15: 3 | K15: 3 | L15: 5 | M15: 3 | N15: 1 | O15: 3 | P15: =SUM((J$1*$J15),(K$1*$K15),(L$1*$L15)*(M$1*$M15),(N$1*$N15),(O$1*$O15))*100 -> 230 | Q15: Abhishek
A16: JD linkage | B16: Not Required | D16: 4037 | E16: NON-OCR | F16: Daily | G16: 10 | H16: JD Update SOP | I16: Y | J16: 1 | K16: 3 | L16: 5 | M16: 3 | N16: 1 | O16: 4 | P16: =SUM((J$1*$J16),(K$1*$K16),(L$1*$L16)*(M$1*$M16),(N$1*$N16),(O$1*$O16))*100 -> 225
A17: Job Data Update (Resignation, Separation and Transfer) | B17: Duplicate | D17: 4381 | E17: NON-OCR | F17: On Demand | G17: 10 | H17: JD Update SOP | I17: Y | J17: 1 | K17: 3 | L17: 5 | M17: 3 | N17: 1 | O17: 4 | P17: =SUM((J$1*$J17),(K$1*$K17),(L$1*$L17)*(M$1*$M17),(N$1*$N17),(O$1*$O17))*100 -> 225 | Q17: Poonam
A18: Mobility_HR Initiated Transfer | B18: Duplicate | D18: 7125 | E18: OCR | F18: Monthly | G18: 10 | H18: Mobility SOP | I18: Y | J18: 1 | K18: 5 | L18: 1 | M18: 4 | N18: 3 | O18: 3 | P18: =SUM((J$1*$J18),(K$1*$K18),(L$1*$L18)*(M$1*$M18),(N$1*$N18),(O$1*$O18))*100 -> 219 | Q18: Kunal
A19: Transfer of performance document | B19: Check script option | C19: 8 | D19: 3558 | J19: 2 | K19: 5 | L19: 5 | M19: 3 | N19: 1 | O19: 2 | P19: =SUM((J$1*$J19),(K$1*$K19),(L$1*$L19)*(M$1*$M19),(N$1*$N19),(O$1*$O19))*100 -> 205 | Q19: Asawari
A20: Creation of performance document | B20: Exception Management | D20: 2013 | E20: NON-OCR | F20: Annual | G20: 10 | H20: SOP_Creation of Performance Document | I20: Y | J20: 4 | K20: 5 | L20: 5 | M20: 2 | N20: 5 | P20: =SUM((J$1*$J20),(K$1*$K20),(L$1*$L20)*(M$1*$M20),(N$1*$N20),(O$1*$O20))*100 -> 190 | Q20: Asawari
A21: Job Description Update | C21: 0 | D21: 7168 | E21: NON-OCR | F21: Daily | G21: 10 | H21: JD Update SOP | I21: Y | J21: 2 | K21: 4 | L21: 4 | M21: 3 | N21: 1 | O21: 1 | P21: =SUM((J$1*$J21),(K$1*$K21),(L$1*$L21)*(M$1*$M21),(N$1*$N21),(O$1*$O21))*100 -> 152 | Q21: Asawari
A22: Holiday Schedule upload | C22: 7 | D22: 10287 | E22: NON-OCR | F22: Monthly | G22: 10 | H22: Holiday Calender Upload SOP | I22: Y | J22: 1 | K22: 5 | L22: 5 | M22: 1 | N22: 1 | O22: 1 | P22: =SUM((J$1*$J22),(K$1*$K22),(L$1*$L22)*(M$1*$M22),(N$1*$N22),(O$1*$O22))*100 -> 140 | Q22: Kunal
A23: Cancelling of performance document | B23: Already backend script available | D23: 1639 | E23: NON-OCR | F23: Annual | G23: 10 | H23: SOP_Cancellation of Performance Document | I23: Y | J23: 3 | K23: 3 | L23: 5 | M23: 2 | N23: 5 | P23: =SUM((J$1*$J23),(K$1*$K23),(L$1*$L23)*(M$1*$M23),(N$1*$N23),(O$1*$O23))*100 -> 140 | Q23: Kunal
A24: Leave Balance upload | B24: Not Required | D24: 4243 | E24: NON-OCR | F24: Monthly | G24: 12 | H24: Leave Balance Upload SOP_V3 | I24: Y | J24: 1 | K24: 5 | L24: 5 | M24: 4 | N24: 5 | P24: =SUM((J$1*$J24),(K$1*$K24),(L$1*$L24)*(M$1*$M24),(N$1*$N24),(O$1*$O24))*100 -> 140 | Q24: Kunal
A25: Bank Data Update | C25: 5 | D25: 3695 | E25: OCR | F25: Weekly | G25: 8 | H25: WFA Global SOP | I25: Y | J25: 1 | K25: 4 | L25: 5 | M25: 2 | N25: 1 | O25: 1 | P25: =SUM((J$1*$J25),(K$1*$K25),(L$1*$L25)*(M$1*$M25),(N$1*$N25),(O$1*$O25))*100 -> 130 | Q25: Abhishek
A26: Creation and Assigning of Curriculum/ Deeplinks/ Online Courses/ Uploading Videos | B26: Learning | C26: TBD | D26: 2025 | E26: NON-OCR | F26: Monthly | G26: 10 | H26: SOP_CSOD_Creation & Assign Curriculum SOP_CSOD_Upload and Assign Online course_V1 SOP_CSOD_Upload and Assign Video_V1 | I26: Y | J26: 1 | K26: 5 | L26: 5 | M26: 2 | N26: 5 | P26: =SUM((J$1*$J26),(K$1*$K26),(L$1*$L26)*(M$1*$M26),(N$1*$N26),(O$1*$O26))*100 -> 130 | Q26: Abhishek
A27: New/ Old Event | B27: Learning | C27: TBD | D27: 2192 | E27: NON-OCR | F27: Daily | G27: 10 | H27: Creating Event, Session & Adding Trainer - Group Creation SOP | I27: Y | J27: 2 | K27: 3 | L27: 1 | M27: 2 | N27: 1 | O27: 1 | P27: =SUM((J$1*$J27),(K$1*$K27),(L$1*$L27)*(M$1*$M27),(N$1*$N27),(O$1*$O27))*100 -> 127 | Q27: Abhishek
A28: Creation of Potential Assessment Document | B28: Already there - Not required | D28: 5337 | E28: NON-OCR | F28: Daily | G28: 5 | H28: SOP_Potential Management_Creation of Potential Assessment Document | I28: Y | J28: 2 | K28: 2 | L28: 1 | M28: 1 | N28: 1 | O28: 1 | P28: =SUM((J$1*$J28),(K$1*$K28),(L$1*$L28)*(M$1*$M28),(N$1*$N28),(O$1*$O28))*100 -> 111 | Q28: Abhishek
A29: Position Creation/ Updation/ Deactivation and JD Linkage (Job Arch) | B29: Already in Production | C29: 0 | D29: 9247 | E29: NON-OCR | F29: Daily | G29: 10 | I29: N | P29: =SUM((J$1*$J29),(K$1*$K29),(L$1*$L29)*(M$1*$M29),(N$1*$N29),(O$1*$O29))*100 -> 0 | Q29: Poonam
A30: Incident Class. / Data / sync issue | B30: Learning | C30: TBD | D30: 1926 | E30: NON-OCR | F30: Daily | G30: 10 | I30: N | P30: =SUM((J$1*$J30),(K$1*$K30),(L$1*$L30)*(M$1*$M30),(N$1*$N30),(O$1*$O30))*100 -> 0 | Q30: Poonam
A31: Maker-Checker - ACR Letter | B31: To be confirmed | D31: 5000 | E31: NON-OCR | F31: Annual | G31: 10 | I31: N | P31: =SUM((J$1*$J31),(K$1*$K31),(L$1*$L31)*(M$1*$M31),(N$1*$N31),(O$1*$O31))*100 -> 0 | Q31: Poonam
A32: Personal Data Update (Excluding Bulk volume-43,274) | B32: Assess Selenium Current build | D32: 14504 | E32: NON-OCR | F32: Daily | G32: 10 | I32: N | P32: =SUM((J$1*$J32),(K$1*$K32),(L$1*$L32)*(M$1*$M32),(N$1*$N32),(O$1*$O32))*100 -> 0 | Q32: Poonam
A33: Job Data Update (Confirmation/Confirmation with pay rate change/Mobility) | B33: TBD- Peoplesoft Letter generation Built | D33: 10119 | E33: OCR | F33: Daily | G33: 5 | I33: N | P33: =SUM((J$1*$J33),(K$1*$K33),(L$1*$L33)*(M$1*$M33),(N$1*$N33),(O$1*$O33))*100 -> 0 | Q33: Poonam
A34: Compensation Update (Excluding bulk volume-71,968) | B34: Not Required | D34: 7232 | E34: OCR | F34: Daily | G34: 15 | I34: N | M34: 5 | P34: =SUM((J$1*$J34),(K$1*$K34),(L$1*$L34)*(M$1*$M34),(N$1*$N34),(O$1*$O34))*100 -> 0 | Q34: Poonam
A35: BGV initiation and Report upload Initiate – 20 mins Report upload 10 mins | B35: Not Required | D35: 5228 | E35: NON-OCR | F35: Daily | G35: 30 | I35: N | M35: 5 | P35: =SUM((J$1*$J35),(K$1*$K35),(L$1*$L35)*(M$1*$M35),(N$1*$N35),(O$1*$O35))*100 -> 0 | Q35: Poonam
A36: External Hire Poornata ID creation | B36: Duplicate | D36: 5170 | E36: NON-OCR | F36: Daily | G36: 10 | I36: N | P36: =SUM((J$1*$J36),(K$1*$K36),(L$1*$L36)*(M$1*$M36),(N$1*$N36),(O$1*$O36))*100 -> 0 | Q36: Poonam
A37: Poornata ID Creation (Add a Person) - Excel Template | B37: Duplicate | D37: 5159 | E37: NON-OCR | F37: On Demand | G37: 20 | I37: N | P37: =SUM((J$1*$J37),(K$1*$K37),(L$1*$L37)*(M$1*$M37),(N$1*$N37),(O$1*$O37))*100 -> 0 | Q37: Asawari
A38: Report generation for talent discussions | B38: Already BOT present | D38: 6131
A39: Position creation/update | B39: Duplicate | D39: 8512

Sheet RPA_SOP_Analysis
H1: 0.2 | I1: 0.15 | J1: 0.05 | K1: 0.2 | L1: 0.05 | M1: 0.3 | N1: 0.05 | O1: =SUM(H1:N1) -> 1
A2: UseCase Name | B2: Average Transactions (Annual) | C2: OCR / NON-OCR | D2: Frequency | E2: AHT (Manual) Mins | F2: Document Referred | G2: SOP Available | H2: Manual Involvement | I2: Complexity | J2: Need Standardisation | K2: Volume | L2: Work with multiple data files | M2: VOC | N2: Service Quality | O2: Scoring Index | P2: Owner
A3: Job Description Update | B3: 7168 | C3: NON-OCR | D3: Daily | E3: 10 | F3: JD Update SOP | G3: Y | H3: 1 | I3: 2 | J3: 2 | K3: 1 | L3: 1 | M3: 1 | N3: 1 | O3: =SUM((H$1*$H3),(I$1*$I3),(J$1*$J3)*(K$1*$K3),(L$1*$L3),(M$1*$M3),(N$1*$N3))*100 -> 92 | P3: Kunal
A4: National ID, PAN, Aadhar, Passport, Visa, Address | B4: 9845 | C4: OCR | D4: Weekly | E4: 10 | F4: ESS SOP_National ID_SR to IM(2) | G4: Y | H4: 2 | I4: 2 | J4: 1 | K4: 1 | L4: 2 | M4: 1 | N4: 1 | O4: =SUM((H$1*$H4),(I$1*$I4),(J$1*$J4)*(K$1*$K4),(L$1*$L4),(M$1*$M4),(N$1*$N4))*100 -> 116 | P4: Kunal
A5: Bank Data Update | B5: 3695 | C5: OCR | D5: Weekly | E5: 8 | F5: WFA Global SOP | G5: Y | H5: 1 | I5: 2 | J5: 1 | K5: 1 | L5: 2 | M5: 1 | N5: 1 | O5: =SUM((H$1*$H5),(I$1*$I5),(J$1*$J5)*(K$1*$K5),(L$1*$L5),(M$1*$M5),(N$1*$N5))*100 -> 96 | P5: Kunal
A6: Education Data | B6: 2981 | C6: OCR | D6: Daily | E6: 7 | F6: ESS SOP_Educational Data_SR to IM | G6: Y | H6: 2 | I6: 2 | J6: 1 | K6: 1 | L6: 2 | M6: 1 | N6: 1 | O6: =SUM((H$1*$H6),(I$1*$I6),(J$1*$J6)*(K$1*$K6),(L$1*$L6),(M$1*$M6),(N$1*$N6))*100 -> 116 | P6: Kunal
A7: FnF Settlement | B7: 12829 | C7: NON-OCR | D7: Monthly | E7: 10 | G7: N | H7: 2 | I7: 3 | J7: 1 | K7: 2 | L7: 3 | M7: 2 | N7: 1 | O7: =SUM((H$1*$H7),(I$1*$I7),(J$1*$J7)*(K$1*$K7),(L$1*$L7),(M$1*$M7),(N$1*$N7))*100 -> 167 | P7: Kunal | Q7: SOP not shared but currently working on the project hence aware of the complexity. Sunil will share the SOP soon (as per Swara)
A8: Holiday Schedule upload | B8: 10287 | C8: NON-OCR | D8: Monthly | E8: 10 | F8: Holiday Calender Upload SOP | G8: Y | H8: 1 | I8: 1 | J8: 1 | K8: 1 | L8: 1 | M8: 1 | N8: 1 | O8: =SUM((H$1*$H8),(I$1*$I8),(J$1*$J8)*(K$1*$K8),(L$1*$L8),(M$1*$M8),(N$1*$N8))*100 -> 76 | P8: Asawari
A9: Job Data Update | B9: 45835 | C9: NON-OCR | D9: Daily | E9: 10 | G9: N | O9: =SUM((H$1*$H9),(I$1*$I9),(J$1*$J9)*(K$1*$K9),(L$1*$L9),(M$1*$M9),(N$1*$N9))*100 -> 0 | P9: Asawari
A10: Maker-Checker - ACR Letter | B10: 5000 | C10: NON-OCR | D10: Annual | E10: 10 | G10: N | O10: =SUM((H$1*$H10),(I$1*$I10),(J$1*$J10)*(K$1*$K10),(L$1*$L10),(M$1*$M10),(N$1*$N10))*100 -> 0 | P10: Asawari
A11: PH Link Initiation (ABCAP) | B11: 111114 | C11: OCR | D11: Daily | E11: 10 | F11: ABCAP SOP - Initiating Prospective Hire Link(2) | G11: Y | H11: 2 | I11: 4 | J11: 3 | K11: 5 | L11: 3 | M11: 5 | N11: 4 | O11: =SUM((H$1*$H11),(I$1*$I11),(J$1*$J11)*(K$1*$K11),(L$1*$L11),(M$1*$M11),(N$1*$N11))*100 -> 300 | P11: Asawari
A12: Poornata ID Creation (Add a Person) (Proposed Process Change) | B12: 8925 | C12: OCR | D12: Daily | E12: 25 | G12: N | O12: =SUM((H$1*$H12),(I$1*$I12),(J$1*$J12)*(K$1*$K12),(L$1*$L12),(M$1*$M12),(N$1*$N12))*100 -> 0 | P12: Asawari
A13: Poornata ID creation (Through External Hire) – QC action and update if missing data-Proposed process change | B13: 5854 | C13: OCR | D13: Daily | E13: 25 | G13: N | O13: =SUM((H$1*$H13),(I$1*$I13),(J$1*$J13)*(K$1*$K13),(L$1*$L13),(M$1*$M13),(N$1*$N13))*100 -> 0 | P13: Kunal
A14: Position Creation/ Updation/ Deactivation and JD Linkage (Job Arch ???) | B14: 9247 | C14: NON-OCR | D14: Daily | E14: 10 | G14: N | O14: =SUM((H$1*$H14),(I$1*$I14),(J$1*$J14)*(K$1*$K14),(L$1*$L14),(M$1*$M14),(N$1*$N14))*100 -> 0 | P14: Kunal
A15: Creation of Potential Assessment Document | B15: 5337 | C15: NON-OCR | D15: Daily | E15: 5 | F15: SOP_Potential Management_Creation of Potential Assessment Document | G15: Y | H15: 2 | I15: 2 | J15: 1 | K15: 1 | L15: 1 | M15: 1 | N15: 1 | O15: =SUM((H$1*$H15),(I$1*$I15),(J$1*$J15)*(K$1*$K15),(L$1*$L15),(M$1*$M15),(N$1*$N15))*100 -> 111 | P15: Kunal
A16: Personal Data Update (Excluding Bulk volume-43,274) | B16: 14504 | C16: OCR | D16: Daily | E16: 10 | G16: N | O16: =SUM((H$1*$H16),(I$1*$I16),(J$1*$J16)*(K$1*$K16),(L$1*$L16),(M$1*$M16),(N$1*$N16))*100 -> 0 | P16: Kunal
A17: Job Data Update (Confirmation/Confirmation with pay rate change/Mobility) | B17: 10119 | C17: OCR | D17: Daily | E17: 5 | G17: N | O17: =SUM((H$1*$H17),(I$1*$I17),(J$1*$J17)*(K$1*$K17),(L$1*$L17),(M$1*$M17),(N$1*$N17))*100 -> 0 | P17: Kunal
A18: Compensation Update (Excluding bulk volume-71,968) | B18: 7232 | C18: OCR | D18: Daily | E18: 15 | G18: N | K18: 5 | O18: =SUM((H$1*$H18),(I$1*$I18),(J$1*$J18)*(K$1*$K18),(L$1*$L18),(M$1*$M18),(N$1*$N18))*100 -> 0 | P18: Abhishek
A19: Leave Balance upload | B19: 4243 | C19: NON-OCR | D19: Monthly | E19: 12 | F19: Leave Balance Upload SOP_V3 | G19: Y | H19: 1 | I19: 5 | J19: 5 | K19: 4 | L19: 5 | O19: =SUM((H$1*$H19),(I$1*$I19),(J$1*$J19)*(K$1*$K19),(L$1*$L19),(M$1*$M19),(N$1*$N19))*100 -> 140 | P19: Abhishek
A20: BGV initiation and Report upload Initiate – 20 mins Report upload 10 mins | B20: 5228 | C20: NON-OCR | D20: Daily | E20: 30 | G20: N | K20: 5 | O20: =SUM((H$1*$H20),(I$1*$I20),(J$1*$J20)*(K$1*$K20),(L$1*$L20),(M$1*$M20),(N$1*$N20))*100 -> 0 | P20: Abhishek
A21: Cancelling of performance document | B21: 1639 | C21: NON-OCR | D21: Annual | E21: 10 | F21: SOP_Cancellation of Performance Document | G21: Y | H21: 3 | I21: 3 | J21: 5 | K21: 2 | L21: 5 | O21: =SUM((H$1*$H21),(I$1*$I21),(J$1*$J21)*(K$1*$K21),(L$1*$L21),(M$1*$M21),(N$1*$N21))*100 -> 140 | P21: Abhishek
A22: Creation and Assigning of Curriculum/ Deeplinks/ Online Courses/ Uploading Videos | B22: 2025 | C22: NON-OCR | D22: Monthly | E22: 10 | F22: SOP_CSOD_Creation & Assign Curriculum SOP_CSOD_Upload and Assign Online course_V1 SOP_CSOD_Upload and Assign Video_V1 | G22: Y | H22: 1 | I22: 5 | J22: 5 | K22: 2 | L22: 5 | O22: =SUM((H$1*$H22),(I$1*$I22),(J$1*$J22)*(K$1*$K22),(L$1*$L22),(M$1*$M22),(N$1*$N22))*100 -> 130 | P22: Abhishek
A23: Creation of performance document | B23: 2013 | C23: NON-OCR | D23: Annual | E23: 10 | F23: SOP_Creation of Performance Document | G23: Y | H23: 4 | I23: 5 | J23: 5 | K23: 2 | L23: 5 | O23: =SUM((H$1*$H23),(I$1*$I23),(J$1*$J23)*(K$1*$K23),(L$1*$L23),(M$1*$M23),(N$1*$N23))*100 -> 190 | P23: Abhishek
A24: Exit_Approval reassignment for Clearance | B24: 1931 | C24: NON-OCR | D24: Monthly | E24: 10 | F24: Exit Module SOP_V.5 | G24: Y | H24: 3 | I24: 5 | J24: 1 | K24: 2 | L24: 1 | M24: 4 | N24: 5 | O24: =SUM((H$1*$H24),(I$1*$I24),(J$1*$J24)*(K$1*$K24),(L$1*$L24),(M$1*$M24),(N$1*$N24))*100 -> 287 | P24: Poonam
A25: Data Change – Data Change | B25: 6804 | C25: NON-OCR | D25: Daily | E25: 10 | G25: N | O25: =SUM((H$1*$H25),(I$1*$I25),(J$1*$J25)*(K$1*$K25),(L$1*$L25),(M$1*$M25),(N$1*$N25))*100 -> 0 | P25: Poonam
A26: JD linkage | B26: 4037 | C26: NON-OCR | D26: Daily | E26: 10 | F26: JD Update SOP | G26: Y | H26: 1 | I26: 3 | J26: 5 | K26: 3 | L26: 1 | M26: 4 | N26: 3 | O26: =SUM((H$1*$H26),(I$1*$I26),(J$1*$J26)*(K$1*$K26),(L$1*$L26),(M$1*$M26),(N$1*$N26))*100 -> 220 | P26: Poonam
A27: Incident Class. / Data / sync issue | B27: 1926 | C27: NON-OCR | D27: Daily | E27: 10 | G27: N | O27: =SUM((H$1*$H27),(I$1*$I27),(J$1*$J27)*(K$1*$K27),(L$1*$L27),(M$1*$M27),(N$1*$N27))*100 -> 0 | P27: Poonam
A28: Job Data Update (Resignation, Separation and Transfer) | B28: 4381 | C28: NON-OCR | D28: On Demand | E28: 10 | F28: JD Update SOP | G28: Y | H28: 1 | I28: 3 | J28: 5 | K28: 3 | L28: 1 | M28: 4 | N28: 3 | O28: =SUM((H$1*$H28),(I$1*$I28),(J$1*$J28)*(K$1*$K28),(L$1*$L28),(M$1*$M28),(N$1*$N28))*100 -> 220 | P28: Poonam
A29: Mobility_HR Initiated Transfer | B29: 7125 | C29: OCR | D29: Monthly | E29: 10 | F29: Mobility SOP | G29: Y | H29: 1 | I29: 5 | J29: 1 | K29: 4 | L29: 3 | M29: 3 | N29: 5 | O29: =SUM((H$1*$H29),(I$1*$I29),(J$1*$J29)*(K$1*$K29),(L$1*$L29),(M$1*$M29),(N$1*$N29))*100 -> 229 | P29: Poonam
A30: External Hire Poornata ID creation | B30: 5170 | C30: NON-OCR | D30: Daily | E30: 10 | G30: N | O30: =SUM((H$1*$H30),(I$1*$I30),(J$1*$J30)*(K$1*$K30),(L$1*$L30),(M$1*$M30),(N$1*$N30))*100 -> 0 | P30: Poonam
A31: Poornata ID Creation (Add a Person) - Excel Template | B31: 5159 | C31: NON-OCR | D31: On Demand | E31: 20 | G31: N | O31: =SUM((H$1*$H31),(I$1*$I31),(J$1*$J31)*(K$1*$K31),(L$1*$L31),(M$1*$M31),(N$1*$N31))*100 -> 0 | P31: Poonam
A32: New/ Old Event | B32: 2192 | C32: NON-OCR | D32: Daily | E32: 10 | F32: Creating Event, Session & Adding Trainer - Group Creation SOP | G32: Y | H32: 2 | I32: 3 | J32: 1 | K32: 2 | L32: 1 | M32: 1 | N32: 1 | O32: =SUM((H$1*$H32),(I$1*$I32),(J$1*$J32)*(K$1*$K32),(L$1*$L32),(M$1*$M32),(N$1*$N32))*100 -> 127 | P32: Poonam
A33: Onboarding Initiation | B33: 2676 | C33: NON-OCR | D33: Weekly | E33: 10 | F33: Alt Onboarding L5 V.2 | G33: Y | H33: 3 | I33: 4 | J33: 2 | K33: 3 | L33: 2 | M33: 4 | N33: 4 | O33: =SUM((H$1*$H33),(I$1*$I33),(J$1*$J33)*(K$1*$K33),(L$1*$L33),(M$1*$M33),(N$1*$N33))*100 -> 276 | P33: Asawari

Sheet Gantt
A1: RPA Use Cases | D1: 2024 | M1: 2025 | Y1: 2026
A2: Use Case Name | B2: Average Transactions (Annual) | C2: OCR / NON-OCR | D2: Apr | E2: May | F2: Jun | G2: Jul | H2: Aug | I2: Sep | J2: Oct | K2: Nov | L2: Dec | M2: Jan | N2: Feb | O2: Mar | P2: Apr | Q2: May | R2: Jun | S2: Jul | T2: Aug | U2: Sep | V2: Oct | W2: Nov | X2: Dec | Y2: Jan | Z2: Feb | AA2: Mar | AB2: Apr | AC2: May
A3: Job Description Update | B3: 7168 | C3: NON-OCR | D3: 1
A4: National ID, PAN, Aadhar, Passport, Visa, Address | B4: 9845 | C4: OCR | D4: 1 | E4: 1 | F4: 1 | G4: 1
A5: Bank Data Update | B5: 3695 | C5: OCR | D5: 1 | E5: 1 | F5: 1 | G5: 1
A6: Education Data | B6: 2981 | C6: OCR | D6: 1 | E6: 1 | F6: 1 | G6: 1
A7: FnF Settlement | B7: 12829 | C7: NON-OCR | D7: 1 | E7: 1
A8: Holiday Schedule upload | B8: 10287 | C8: NON-OCR | E8: 1
A9: Job Data Update | B9: 45835 | C9: NON-OCR | F9: 1 | G9: 1
A10: Maker-Checker - ACR Letter | C10: NON-OCR | F10: 1 | G10: 1 | H10: 1
A11: PH Link Initiation (ABCAP) | B11: 111114 | C11: OCR | H11: 1 | I11: 1 | J11: 1
A12: Poornata ID Creation (Add a Person) (Proposed Process Change) | B12: 8925 | C12: OCR | H12: 1 | I12: 1 | J12: 1
A13: Poornata ID creation (Through External Hire) | B13: 5854 | C13: OCR | H13: 1 | I13: 1 | J13: 1
A14: Position Creation/ Updation/ Deactivation and JD Linkage (Job Arch ???) | B14: 9247 | C14: NON-OCR | H14: 1 | I14: 1
A15: Creation of Potential Assessment Document | B15: 5337 | C15: NON-OCR | J15: 1 | K15: 1
A16: Personal Data Update (Excluding Bulk volume-43,274) | B16: 14504 | C16: OCR | K16: 1 | L16: 1 | M16: 1
A17: Job Data Update (Confirmation/Confirmation with pay rate change/Mobility) | B17: 10119 | C17: OCR | K17: 1 | L17: 1 | M17: 1
A18: Compensation Update (Excluding bulk volume-71,968) | B18: 7232 | C18: OCR | K18: 1 | L18: 1 | M18: 1
A19: Leave Balance upload | B19: 4243 | C19: NON-OCR | L19: 1 | M19: 1
A20: BGV initiation and Report upload Initiate – 20 mins Report upload 10 mins | B20: 5228 | C20: NON-OCR | N20: 1 | O20: 1
A21: Cancelling of performance document | B21: 1639 | C21: NON-OCR | N21: 1 | O21: 1
A22: Creation and Assigning of Curriculum/ Deeplinks/ Online Courses/ Uploading Videos | B22: 2025 | C22: NON-OCR | P22: 1 | Q22: 1
A23: Creation of performance document | B23: 2013 | C23: NON-OCR | P23: 1 | Q23: 1 | R23: 1
A24: Exit_Approval reassignment for Clearance | B24: 1931 | C24: NON-OCR | R24: 1 | S24: 1 | T24: 1
A25: Data Change – Data Change | B25: 6804 | C25: NON-OCR | S25: 1
A26: JD linkage | B26: 4037 | C26: NON-OCR | T26: 1 | U26: 1
A27: Incident Class. / Data / sync issue | B27: 1926 | C27: NON-OCR | U27: 1 | V27: 1
A28: Job Data Update (Resignation, Separation and Transfer) | B28: 4381 | C28: NON-OCR | V28: 1 | W28: 1
A29: Mobility_HR Initiated Transfer | B29: 7125 | C29: NON-OCR | W29: 1 | X29: 1
A30: External Hire Poornata ID creation | B30: 5170 | C30: NON-OCR | X30: 1 | Y30: 1
A31: Poornata ID Creation (Add a Person) - Excel Template | B31: 5159 | C31: NON-OCR | Y31: 1 | Z31: 1 | AA31: 1
A32: New/ Old Event | B32: 2192 | C32: NON-OCR | Z32: 1 | AA32: 1
A33: Onboarding Initiation | B33: 2676 | C33: NON-OCR | AA33: 1 | AB33: 1 | AC33: 1

Sheet RPA ProcessCount_Frequency
A3: Count of UseCase Name | B3: Column Labels
A4: Row Labels | B4: Annual | C4: Based on requirement | D4: Daily | E4: Monthly | F4: On Demand | G4: Weekly | H4: Grand Total
A5: NON-OCR | B5: 3 | C5: 3 | D5: 17 | E5: 6 | F5: 2 | G5: 1 | H5: 32
A6: OCR | D6: 7 | G6: 2 | H6: 9
A7: Grand Total | B7: 3 | C7: 3 | D7: 24 | E7: 6 | F7: 2 | G7: 3 | H7: 41

Sheet ROI Toolkit Parameters
A1: ROI
A2: FTE Cost
A3: Quality Cost
A4: Subscription Cost
A5: Infra Cost
A6: Other CAPEX
A7: Other OPEX

Sheet ROI-V1
A1: Use Case Meta Data | I1: Existing Manual Monthly Cost | O1: FTE Saved/Day | P1: BOT AHT (Min) | Q1: BOT FTE | R1: FTE Cost | S1: BOT Monthly Cost | AB1: ROI
A2: #Priority | B2: UseCase | C2: Already in Production | D2: AverageTransactions(Annual) | E2: OCR/NON-OCR | F2: Frequency | G2: Complexity | H2: Manual AHT in Min /Transaction | I2: Manual FTE Required/Day | J2: FTE Cost (Per Day) | K2: Seat Cost (Per Day) | L2: Employee Cost (Others - Paid by ABG)* Per Day | M2: Other OPEX Cost*Per Day | N2: Total Cost (Per Day) | S2: BOT FTE Required / Day | T2: FTE Cost (Per Day) | U2: Infra Cost (Per Day) | V2: License Cost (Per Day) | Y2: Development & Support | AA2: Total Cost | AB2: ROI in Rupees (Per Day) | AC2: ROI In Percent
V3: Runner | W3: Creater | X3: Document Automation | Y3: Development | Z3: Support
A4: NA | B4: Data Change – Override Manager | C4: Y | D4: =VLOOKUP(B4,'RPA RoadMap'!B:R,3,) -> 6089 | E4: =VLOOKUP(B4,'RPA RoadMap'!B:AA,4,FALSE) -> NON-OCR | F4: =VLOOKUP(B4,'RPA RoadMap'!B:R,5,FALSE) -> Daily | G4: =VLOOKUP(B4,'RPA RoadMap'!B:R,13,FALSE) -> Medium | H4: =((150*2)-71)/60 -> 3.8166667 | I4: =((D4*H4)/60)/(200)/6.5 -> 0.29794466 | J4: =I4*(48000/30) -> 476.71145 | K4: =I4*(10785/30) -> 107.1111 | L4: =I4*(5283/30) -> 52.468054 | M4: =I4*(6432/30) -> 63.879335 | N4: =I4*(70500/30) -> 700.16995 | O4: =I4*0.85 -> 0.25325296 | P4: =(205-71)/60 -> 2.2333333 | Q4: =((D4*P4/100)/60)/(200/12)/6.5 -> 0.020921179 | R4: =Q4*70500 -> 1474.9432 | S4: =I4-O4 -> 0.044691699 | T4: =S4*(70500/30) -> 105.02549 | U4: =(5000/30) -> 166.66667 | V4: =(((D4/365)*(P4))/60)*(49000/(30*24)) -> 42.258978 | W4: =(21000/30)/3 -> 233.33333 | X4: 0 | Y4: =(((600000/4)/22)*29)/66 -> 2995.8678 | Z4: =((100000*2)/23)/30 -> 289.85507 | AA4: =SUM(T4:Z4)-W4-Y4 -> 603.80621 | AB4: =(N4-AA4) -> 96.363737 | AC4: =(N4-AA4)/N4 -> 0.13762907
A5: NA | B5: Data Change – Use Position Reports To | C5: Y | D5: =VLOOKUP(B5,'RPA RoadMap'!B:R,3,) -> 3933 | E5: =VLOOKUP(B5,'RPA RoadMap'!B:AA,4,FALSE) -> NON-OCR | F5: =VLOOKUP(B5,'RPA RoadMap'!B:R,5,FALSE) -> Daily | G5: =VLOOKUP(B5,'RPA RoadMap'!B:R,13,FALSE) -> Simple | H5: =((143*2)-69)/60 -> 3.6166667 | I5: =((D5*H5)/60)/(200)/6.5 -> 0.18236346 | J5: =I5*(48000/30) -> 291.78154 | K5: =I5*(10785/30) -> 65.559664 | L5: =I5*(5283/30) -> 32.114206 | M5: =I5*(6432/30) -> 39.098726 | N5: =I5*(70500/30) -> 428.55413 | O5: =I5*0.85 -> 0.15500894 | P5: =(143-69)/60 -> 1.2333333 | Q5: =((D5*P5/100)/60)/(200/12)/6.5 -> 0.0074626154 | R5: =Q5*70500 -> 526.11438 | S5: =I5-O5 -> 0.027354519 | T5: =S5*(70500/30) -> 64.28312 | U5: =(5000/30) -> 166.66667 | V5: =(((D5/365)*(P5))/60)*(49000/(30*24)) -> 15.073839 | W5: =(21000/30)/3 -> 233.33333 | X5: 0 | Y5: =(((600000/4)/22)*19)/66 -> 1962.8099 | Z5: =((100000*2)/23)/30 -> 289.85507 | AA5: =SUM(T5:Z5)-W5-Y5 -> 535.8787 | AB5: =(N5-AA5) -> -107.32456 | AC5: =(N5-AA5)/N5 -> -0.25043409
A6: NA | B6: Job Architecture | C6: Y | D6: =VLOOKUP(B6,'RPA RoadMap'!B:R,3,) -> 10692 | E6: =VLOOKUP(B6,'RPA RoadMap'!B:AA,4,FALSE) -> NON-OCR | F6: =VLOOKUP(B6,'RPA RoadMap'!B:R,5,FALSE) -> Daily | G6: =VLOOKUP(B6,'RPA RoadMap'!B:R,13,FALSE) -> Medium | H6: =((142*2)-93)/60 -> 3.1833333 | I6: =((D6*H6)/60)/(200)/6.5 -> 0.43636154 | J6: =I6*(48000/30) -> 698.17846 | K6: =I6*(10785/30) -> 156.87197 | L6: =I6*(5283/30) -> 76.843267 | M6: =I6*(6432/30) -> 93.555914 | N6: =I6*(70500/30) -> 1025.4496 | O6: =I6*0.85 -> 0.37090731 | P6: =(142-93)/60 -> 0.81666667 | Q6: =((D6*P6/100)/60)/(200/12)/6.5 -> 0.013433538 | R6: =Q6*70500 -> 947.06446 | S6: =I6-O6 -> 0.065454231 | T6: =S6*(70500/30) -> 153.81744 | U6: =(5000/30) -> 166.66667 | V6: =(((D6/365)*(P6))/60)*(49000/(30*24)) -> 27.134589 | W6: =(21000/30)/3 -> 233.33333 | X6: 0 | Y6: =(((600000/4)/22)*29)/66 -> 2995.8678 | Z6: =((100000*2)/23)/30 -> 289.85507 | AA6: =SUM(T6:Z6)-W6-Y6 -> 637.47377 | AB6: =(N6-AA6) -> 387.97584 | AC6: =(N6-AA6)/N6 -> 0.37834706
A7: NA | B7: Ticket Creater | C7: Y | D7: =VLOOKUP(B7,'RPA RoadMap'!B:R,3,) -> 48701 | E7: =VLOOKUP(B7,'RPA RoadMap'!B:AA,4,FALSE) -> NON-OCR | F7: =VLOOKUP(B7,'RPA RoadMap'!B:R,5,FALSE) -> Daily | G7: =VLOOKUP(B7,'RPA RoadMap'!B:R,13,FALSE) -> Complex | H7: =VLOOKUP(B7,'RPA RoadMap'!B:R,6,FALSE) -> 10 | I7: =((D7*H7)/60)/(200)/6.5 -> 6.2437179 | J7: =I7*(48000/30) -> 9989.9487 | K7: =I7*(10785/30) -> 2244.6166 | L7: =I7*(5283/30) -> 1099.5187 | M7: =I7*(6432/30) -> 1338.6531 | N7: =I7*(70500/30) -> 14672.737 | O7: =I7*0.6 -> 3.7462308 | P7: =(191-160)/60 -> 0.51666667 | Q7: =((D7*P7/100)/60)/(200/12)/6.5 -> 0.038711051 | R7: =Q7*70500 -> 2729.1291 | S7: =I7-O7 -> 2.4974872 | T7: =S7*(70500/30) -> 5869.0949 | U7: =(5000/30) -> 166.66667 | V7: =(((D7/365)*(P7))/60)*(49000/(30*24)) -> 78.192985 | W7: =(21000/30)/3 -> 233.33333 | X7: 0 | Y7: =((600000/4)*(43/30))/66 -> 3257.5758 | Z7: =((100000*2)/23)/30 -> 289.85507 | AA7: =SUM(T7:Z7)-W7-Y7 -> 6403.8096 | AB7: =(N7-AA7) -> 8268.9276 | AC7: =(N7-AA7)/N7 -> 0.56355726
A8: NA | B8: Talent Profile Creation BOT | C8: Y | D8: =VLOOKUP(B8,'RPA RoadMap'!B:R,3,) -> 5310 | E8: =VLOOKUP(B8,'RPA RoadMap'!B:AA,4,FALSE) -> NON-OCR | F8: =VLOOKUP(B8,'RPA RoadMap'!B:R,5,FALSE) -> Based on requirement | G8: =VLOOKUP(B8,'RPA RoadMap'!B:R,13,FALSE) -> Complex | H8: =VLOOKUP(B8,'RPA RoadMap'!B:R,6,FALSE) -> 10 | I8: =((D8*H8)/60)/(200)/6.5 -> 0.68076923 | J8: =I8*(48000/30) -> 1089.2308 | K8: =I8*(10785/30) -> 244.73654 | L8: =I8*(5283/30) -> 119.88346 | M8: =I8*(6432/30) -> 145.95692 | N8: =I8*(70500/30) -> 1599.8077 | O8: =I8*0.6 -> 0.40846154 | P8: =(180-163)/60 -> 0.28333333 | Q8: =((D8*P8/100)/60)/(200/12)/6.5 -> 0.0023146154 | R8: =Q8*70500 -> 163.18038 | S8: =I8-O8 -> 0.27230769 | T8: =S8*(70500/30) -> 639.92308 | U8: =(5000/30) -> 166.66667 | V8: =(((D8/365)*(P8))/60)*(49000/(30*24)) -> 4.6753234 | W8: =(21000/30)/3 -> 233.33333 | X8: 0 | Y8: =(((600000/4))*(43/30))/66 -> 3257.5758 | Z8: =((100000*2)/23)/30 -> 289.85507 | AA8: =SUM(T8:Z8)-W8-Y8 -> 1101.1201 | AB8: =(N8-AA8) -> 498.68755 | AC8: =(N8-AA8)/N8 -> 0.31171719
A9: NA | B9: Poornata Status update - SR Update in Transaction | C9: Y | D9: =VLOOKUP(B9,'RPA RoadMap'!B:R,3,) -> 53182 | E9: =VLOOKUP(B9,'RPA RoadMap'!B:AA,4,FALSE) -> NON-OCR | F9: =VLOOKUP(B9,'RPA RoadMap'!B:R,5,FALSE) -> Daily | G9: =VLOOKUP(B9,'RPA RoadMap'!B:R,13,FALSE) -> Simple | H9: 5 | I9: =((D9*H9)/60)/(200)/6.5 -> 3.4091026 | J9: =I9*(48000/30) -> 5454.5641 | K9: =I9*(10785/30) -> 1225.5724 | L9: =I9*(5283/30) -> 600.34296 | M9: =I9*(6432/30) -> 730.91159 | N9: =I9*(70500/30) -> 8011.391 | O9: =I9*0.8 -> 2.7272821 | P9: =(24)/60 -> 0.4 | Q9: =((D9*P9/100)/60)/(200/12)/6.5 -> 0.032727385 | R9: =Q9*70500 -> 2307.2806 | S9: =I9-O9 -> 0.68182051 | T9: =S9*(70500/30) -> 1602.2782 | U9: =(5000/30) -> 166.66667 | V9: =(((D9/365)*(P9))/60)*(49000/(30*24)) -> 66.106494 | W9: =(21000/30)/3 -> 233.33333 | X9: 0 | Y9: =(((600000/4)/22)*24)/66 -> 2479.3388 | Z9: =((100000*2)/23)/30 -> 289.85507 | AA9: =SUM(T9:Z9)-W9-Y9 -> 2124.9064 | AB9: =(N9-AA9) -> 5886.4846 | AC9: =(N9-AA9)/N9 -> 0.73476436
A10: NA | B10: Audit Sampling | C10: Y | D10: =VLOOKUP(B10,'RPA RoadMap'!B:R,3,) -> 5000 | E10: =VLOOKUP(B10,'RPA RoadMap'!B:AA,4,FALSE) -> NON-OCR | F10: =VLOOKUP(B10,'RPA RoadMap'!B:R,5,FALSE) -> Based on requirement | G10: =VLOOKUP(B10,'RPA RoadMap'!B:R,13,FALSE) -> Simple | H10: =VLOOKUP(B10,'RPA RoadMap'!B:R,6,FALSE) -> 10 | I10: =((D10*H10)/60)/(200)/6.5 -> 0.64102564 | J10: =I10*(48000/30) -> 1025.641 | K10: =I10*(10785/30) -> 230.44872 | L10: =I10*(5283/30) -> 112.88462 | M10: =I10*(6432/30) -> 137.4359 | N10: =I10*(70500/30) -> 1506.4103 | O10: =I10*0.8 -> 0.51282051 | P10: =24/60 -> 0.4 | Q10: =((D10*P10/100)/60)/(200/12)/6.5 -> 0.0030769231 | R10: =Q10*70500 -> 216.92308 | S10: =I10-O10 -> 0.12820513 | T10: =S10*(70500/30) -> 301.28205 | U10: =(5000/30) -> 166.66667 | V10: =(((D10/365)*(P10))/60)*(49000/(30*24)) -> 6.2151192 | W10: =(21000/30)/3 -> 233.33333 | X10: 0 | Y10: =(((600000/4)/22)*24)/66 -> 2479.3388 | Z10: =((100000*2)/23)/30 -> 289.85507 | AA10: =SUM(T10:Z10)-W10-Y10 -> 764.01891 | AB10: =(N10-AA10) -> 742.39135 | AC10: =(N10-AA10)/N10 -> 0.49282149
A11: NA | B11: Cement ticket creator | C11: Y | D11: =VLOOKUP(B11,'RPA RoadMap'!B:R,3,) -> 5000 | E11: =VLOOKUP(B11,'RPA RoadMap'!B:AA,4,FALSE) -> NON-OCR | F11: =VLOOKUP(B11,'RPA RoadMap'!B:R,5,FALSE) -> Daily | G11: =VLOOKUP(B11,'RPA RoadMap'!B:R,13,FALSE) -> Complex | H11: =VLOOKUP(B11,'RPA RoadMap'!B:R,6,FALSE) -> 10 | I11: =((D11*H11)/60)/(200)/6.5 -> 0.64102564 | J11: =I11*(48000/30) -> 1025.641 | K11: =I11*(10785/30) -> 230.44872 | L11: =I11*(5283/30) -> 112.88462 | M11: =I11*(6432/30) -> 137.4359 | N11: =I11*(70500/30) -> 1506.4103 | O11: =I11*0.6 -> 0.38461538 | P11: =(127-80)/60 -> 0.78333333 | Q11: =((D11*P11/100)/60)/(200/12)/6.5 -> 0.006025641 | R11: =Q11*70500 -> 424.80769 | S11: =I11-O11 -> 0.25641026 | T11: =S11*(70500/30) -> 602.5641 | U11: =(5000/30) -> 166.66667 | V11: =(((D11/365)*(P11))/60)*(49000/(30*24)) -> 12.171275 | W11: =(21000/30)/3 -> 233.33333 | X11: 0 | Y11: =((600000/4)*(43/30))/66 -> 3257.5758 | Z11: =((100000*2)/23)/30 -> 289.85507 | AA11: =SUM(T11:Z11)-W11-Y11 -> 1071.2571 | AB11: =(N11-AA11) -> 435.15314 | AC11: =(N11-AA11)/N11 -> 0.28886762
A12: NA | B12: Potential Assesment | C12: Y | D12: =VLOOKUP(B12,'RPA RoadMap'!B:R,3,) -> 6316 | E12: =VLOOKUP(B12,'RPA RoadMap'!B:AA,4,FALSE) -> NON-OCR | F12: =VLOOKUP(B12,'RPA RoadMap'!B:R,5,FALSE) -> Based on requirement | G12: =VLOOKUP(B12,'RPA RoadMap'!B:R,13,FALSE) -> Medium | H12: =VLOOKUP(B12,'RPA RoadMap'!B:R,6,FALSE) -> 10 | I12: =((D12*H12)/60)/(200)/6.5 -> 0.80974359 | J12: =I12*(48000/30) -> 1295.5897 | K12: =I12*(10785/30) -> 291.10282 | L12: =I12*(5283/30) -> 142.59585 | M12: =I12*(6432/30) -> 173.60903 | N12: =I12*(70500/30) -> 1902.8974 | O12: =I12*0.7 -> 0.56682051 | P12: 8 | Q12: =((D12*P12/100)/60)/(200/12)/6.5 -> 0.077735385 | R12: =Q12*70500 -> 5480.3446 | S12: =I12-O12 -> 0.24292308 | T12: =S12*(70500/30) -> 570.86923 | U12: =(5000/30) -> 166.66667 | V12: =(((D12/365)*(P12))/60)*(49000/(30*24)) -> 157.01877 | W12: =(21000/30)/3 -> 233.33333 | X12: 0 | Y12: =(((600000/4)/22)*29)/66 -> 2995.8678 | Z12: =((100000*2)/23)/30 -> 289.85507 | AA12: =SUM(T12:Z12)-W12-Y12 -> 1184.4097 | AB12: =(N12-AA12) -> 718.48769 | AC12: =(N12-AA12)/N12 -> 0.37757563
A13: 0 | B13: Job Description Update | C13: N | D13: =VLOOKUP(B13,'RPA RoadMap'!B:R,3,) -> 7168 | E13: =VLOOKUP(B13,'RPA RoadMap'!B:AA,4,FALSE) -> NON-OCR | F13: =VLOOKUP(B13,'RPA RoadMap'!B:R,5,FALSE) -> Daily | G13: =VLOOKUP(B13,'RPA RoadMap'!B:R,13,FALSE) -> Complex | H13: =VLOOKUP(B13,'RPA RoadMap'!B:R,6,FALSE) -> 10 | I13: =((D13*H13)/60)/(200)/6.5 -> 0.91897436 | J13: =I13*(48000/30) -> 1470.359 | K13: =I13*(10785/30) -> 330.37128 | L13: =I13*(5283/30) -> 161.83138 | M13: =I13*(6432/30) -> 197.0281 | N13: =I13*(70500/30) -> 2159.5897 | O13: =I13*0.6 -> 0.55138462 | P13: 8 | Q13: =((D13*P13/100)/60)/(200/12)/6.5 -> 0.088221538 | R13: =Q13*70500 -> 6219.6185 | S13: =I13-O13 -> 0.36758974 | T13: =S13*(70500/30) -> 863.8359 | U13: =(5000/30) -> 166.66667 | V13: =(((D13/365)*(P13))/60)*(49000/(30*24)) -> 178.1999 | W13: =(21000/30)/3 -> 233.33333 | X13: 0 | Y13: =(((600000/4)/22)*29)/66 -> 2995.8678 | Z13: =((100000*2)/23)/30 -> 289.85507 | AA13: =SUM(T13:Z13)-W13-Y13 -> 1498.5575 | AB13: =(N13-AA13) -> 661.03221 | AC13: =(N13-AA13)/N13 -> 0.30609157
A14: 0 | B14: FnF Settlement | C14: N | D14: =VLOOKUP(B14,'RPA RoadMap'!B:R,3,) -> 12829 | E14: =VLOOKUP(B14,'RPA RoadMap'!B:AA,4,FALSE) -> NON-OCR | F14: =VLOOKUP(B14,'RPA RoadMap'!B:R,5,FALSE) -> Monthly | G14: =VLOOKUP(B14,'RPA RoadMap'!B:R,13,FALSE) -> Complex | H14: =VLOOKUP(B14,'RPA RoadMap'!B:R,6,FALSE) -> 10 | I14: =((D14*H14)/60)/(200)/6.5 -> 1.6447436 | J14: =I14*(48000/30) -> 2631.5897 | K14: =I14*(10785/30) -> 591.28532 | L14: =I14*(5283/30) -> 289.63935 | M14: =I14*(6432/30) -> 352.63303 | N14: =I14*(70500/30) -> 3865.1474 | O14: =I14*0.6 -> 0.98684615 | P14: 8 | Q14: =((D14*P14/100)/60)/(200/12)/6.5 -> 0.15789538 | R14: =Q14*70500 -> 11131.625 | S14: =I14-O14 -> 0.65789744 | T14: =S14*(70500/30) -> 1546.059 | U14: =(5000/30) -> 166.66667 | V14: =(((D14/365)*(P14))/60)*(49000/(30*24)) -> 318.93506 | W14: =(21000/30)/3 -> 233.33333 | X14: 0 | Y14: =(((600000/4)/22)*29)/66 -> 2995.8678 | Z14: =((100000*2)/23)/30 -> 289.85507 | AA14: =SUM(T14:Z14)-W14-Y14 -> 2321.5158 | AB14: =(N14-AA14) -> 1543.6317 | AC14: =(N14-AA14)/N14 -> 0.399372
A15: 1 | B15: Initiate EJF Verification Process | C15: N | D15: =VLOOKUP(B15,'RPA_SOP_Analysis_ABG Team SI-2'!A:G,4,) -> 14999 | E15: OCR | F15: =VLOOKUP(B15,'RPA_SOP_Analysis_ABG Team SI-2'!A:G,6,FALSE) -> 0 | G15: Complex | H15: 30 | I15: =((D15*H15)/60)/(200)/6.5 -> 5.7688462 | J15: =I15*(48000/30) -> 9230.1538 | K15: =I15*(10785/30) -> 2073.9002 | L15: =I15*(5283/30) -> 1015.8938 | M15: =I15*(6432/30) -> 1236.8406 | N15: =I15*(70500/30) -> 13556.788 | O15: =I15*0.6 -> 3.4613077 | P15: 8 | Q15: =((D15*P15/100)/60)/(200/12)/6.5 -> 0.18460308 | R15: =Q15*70500 -> 13014.517 | S15: =I15-O15 -> 2.3075385 | T15: =S15*(70500/30) -> 5422.7154 | U15: =(5000/30) -> 166.66667 | V15: =(((D15/365)*(P15))/60)*(49000/(30*24)) -> 372.88229 | W15: =(21000/30)/3 -> 233.33333 | X15: =(1400000/365)/8 -> 479.45205 | Y15: =((600000/4)*(58/30))/66 -> 4393.9394 | Z15: =((100000*2)/23)/30 -> 289.85507 | AA15: =SUM(T15:Z15)-W15-Y15 -> 6731.5715 | AB15: =(N15-AA15) -> 6825.217 | AC15: =(N15-AA15)/N15 -> 0.50345382
A16: 2 | B16: Poornata ID Creation (Add a Person) (Proposed Process Change) | C16: N | D16: =VLOOKUP(B16,'RPA RoadMap'!B:R,3,) -> 8925 | E16: =VLOOKUP(B16,'RPA RoadMap'!B:AA,4,FALSE) -> OCR | F16: =VLOOKUP(B16,'RPA RoadMap'!B:R,5,FALSE) -> Daily | G16: =VLOOKUP(B16,'RPA RoadMap'!B:R,13,FALSE) -> Complex | H16: =VLOOKUP(B16,'RPA RoadMap'!B:R,6,FALSE) -> 25 | I16: =((D16*H16)/60)/(200)/6.5 -> 2.8605769 | J16: =I16*(48000/30) -> 4576.9231 | K16: =I16*(10785/30) -> 1028.3774 | L16: =I16*(5283/30) -> 503.7476 | M16: =I16*(6432/30) -> 613.30769 | N16: =I16*(70500/30) -> 6722.3558 | O16: =I16*0.6 -> 1.7163462 | P16: 8 | Q16: =((D16*P16/100)/60)/(200/12)/6.5 -> 0.10984615 | R16: =Q16*70500 -> 7744.1538 | S16: =I16-O16 -> 1.1442308 | T16: =S16*(70500/30) -> 2688.9423 | U16: =(5000/30) -> 166.66667 | V16: =(((D16/365)*(P16))/60)*(49000/(30*24)) -> 221.87976 | W16: =(21000/30)/3 -> 233.33333 | X16: =(1400000/365)/8 -> 479.45205 | Y16: =((600000/4)*(58/30))/66 -> 4393.9394 | Z16: =((100000*2)/23)/30 -> 289.85507 | AA16: =SUM(T16:Z16)-W16-Y16 -> 3846.7959 | AB16: =(N16-AA16) -> 2875.5599 | AC16: =(N16-AA16)/N16 -> 0.42776074
A17: 2 | B17: Poornata ID creation (Through External Hire) – QC action and update if missing data-Proposed process change | C17: N | D17: =VLOOKUP(B17,'RPA RoadMap'!B:R,3,) -> 5854 | E17: =VLOOKUP(B17,'RPA RoadMap'!B:AA,4,FALSE) -> OCR | F17: =VLOOKUP(B17,'RPA RoadMap'!B:R,5,FALSE) -> Daily | G17: =VLOOKUP(B17,'RPA RoadMap'!B:R,13,FALSE) -> Complex | H17: =VLOOKUP(B17,'RPA RoadMap'!B:R,6,FALSE) -> 25 | I17: =((D17*H17)/60)/(200)/6.5 -> 1.8762821 | J17: =I17*(48000/30) -> 3002.0513 | K17: =I17*(10785/30) -> 674.5234 | L17: =I17*(5283/30) -> 330.41327 | M17: =I17*(6432/30) -> 402.27487 | N17: =I17*(70500/30) -> 4409.2628 | O17: =I17*0.6 -> 1.1257692 | P17: 8 | Q17: =((D17*P17/100)/60)/(200/12)/6.5 -> 0.072049231 | R17: =Q17*70500 -> 5079.4708 | S17: =I17-O17 -> 0.75051282 | T17: =S17*(70500/30) -> 1763.7051 | U17: =(5000/30) -> 166.66667 | V17: =(((D17/365)*(P17))/60)*(49000/(30*24)) -> 145.53323 | W17: =(21000/30)/3 -> 233.33333 | X17: =(1400000/365)/8 -> 479.45205 | Y17: =((600000/4)*(58/30))/66 -> 4393.9394 | Z17: =((100000*2)/23)/30 -> 289.85507 | AA17: =SUM(T17:Z17)-W17-Y17 -> 2845.2122 | AB17: =(N17-AA17) -> 1564.0507 | AC17: =(N17-AA17)/N17 -> 0.35471931
A18: 3 | B18: Pratibha - OCR | C18: N | D18: =VLOOKUP(B18,'RPA_SOP_Analysis_ABG Team SI-2'!A:G,4,) -> 540 | E18: =VLOOKUP(B18,'RPA_SOP_Analysis_ABG Team SI-2'!A:G,5,FALSE) -> OCR | F18: =VLOOKUP(B18,'RPA_SOP_Analysis_ABG Team SI-2'!A:G,6,FALSE) -> Yearly | G18: Complex | H18: 120 | I18: =((D18*H18)/60)/(200)/6.5 -> 0.83076923 | J18: =I18*(48000/30) -> 1329.2308 | K18: =I18*(10785/30) -> 298.66154 | L18: =I18*(5283/30) -> 146.29846 | M18: =I18*(6432/30) -> 178.11692 | N18: =I18*(70500/30) -> 1952.3077 | O18: =I18*0.6 -> 0.49846154 | P18: 8 | Q18: =((D18*P18/100)/60)/(200/12)/6.5 -> 0.0066461538 | R18: =Q18*70500 -> 468.55385 | S18: =I18-O18 -> 0.33230769 | T18: =S18*(70500/30) -> 780.92308 | U18: =(5000/30) -> 166.66667 | V18: =(((D18/365)*(P18))/60)*(49000/(30*24)) -> 13.424658 | W18: =(21000/30)/3 -> 233.33333 | X18: =(1400000/365)/8 -> 479.45205 | Y18: =((600000/4)*(58/30))/66 -> 4393.9394 | Z18: =((100000*2)/23)/30 -> 289.85507 | AA18: =SUM(T18:Z18)-W18-Y18 -> 1730.3215 | AB18: =(N18-AA18) -> 221.98616 | AC18: =(N18-AA18)/N18 -> 0.1137045
A19: 4 | B19: AWOO(A world of opprtunity) - OCR | C19: N | D19: =VLOOKUP(B19,'RPA_SOP_Analysis_ABG Team SI-2'!A:G,4,) -> 2700 | E19: =VLOOKUP(B19,'RPA_SOP_Analysis_ABG Team SI-2'!A:G,5,FALSE) -> OCR | F19: =VLOOKUP(B19,'RPA_SOP_Analysis_ABG Team SI-2'!A:G,6,FALSE) -> Yearly | G19: Complex | H19: 120 | I19: =((D19*H19)/60)/(200)/6.5 -> 4.1538462 | J19: =I19*(48000/30) -> 6646.1538 | K19: =I19*(10785/30) -> 1493.3077 | L19: =I19*(5283/30) -> 731.49231 | M19: =I19*(6432/30) -> 890.58462 | N19: =I19*(70500/30) -> 9761.5385 | O19: =I19*0.6 -> 2.4923077 | P19: 8 | Q19: =((D19*P19/100)/60)/(200/12)/6.5 -> 0.033230769 | R19: =Q19*70500 -> 2342.7692 | S19: =I19-O19 -> 1.6615385 | T19: =S19*(70500/30) -> 3904.6154 | U19: =(5000/30) -> 166.66667 | V19: =(((D19/365)*(P19))/60)*(49000/(30*24)) -> 67.123288 | W19: =(21000/30)/3 -> 233.33333 | X19: =(1400000/365)/8 -> 479.45205 | Y19: =((600000/4)*(58/30))/66 -> 4393.9394 | Z19: =((100000*2)/23)/30 -> 289.85507 | AA19: =SUM(T19:Z19)-W19-Y19 -> 4907.7125 | AB19: =(N19-AA19) -> 4853.826 | AC19: =(N19-AA19)/N19 -> 0.49723986
A20: 5 | B20: Bank Data Update | C20: N | D20: =VLOOKUP(B20,'RPA RoadMap'!B:R,3,) -> 3695 | E20: =VLOOKUP(B20,'RPA RoadMap'!B:AA,4,FALSE) -> OCR | F20: =VLOOKUP(B20,'RPA RoadMap'!B:R,5,FALSE) -> Weekly | G20: =VLOOKUP(B20,'RPA RoadMap'!B:R,13,FALSE) -> Medium | H20: =VLOOKUP(B20,'RPA RoadMap'!B:R,6,FALSE) -> 8 | I20: =((D20*H20)/60)/(200)/6.5 -> 0.37897436 | J20: =I20*(48000/30) -> 606.35897 | K20: =I20*(10785/30) -> 136.24128 | L20: =I20*(5283/30) -> 66.737385 | M20: =I20*(6432/30) -> 81.252103 | N20: =I20*(70500/30) -> 890.58974 | O20: =I20*0.7 -> 0.26528205 | P20: 8 | Q20: =((D20*P20/100)/60)/(200/12)/6.5 -> 0.045476923 | R20: =Q20*70500 -> 3206.1231 | S20: =I20-O20 -> 0.11369231 | T20: =S20*(70500/30) -> 267.17692 | U20: =(5000/30) -> 166.66667 | V20: =(((D20/365)*(P20))/60)*(49000/(30*24)) -> 91.859462 | W20: =(21000/30)/3 -> 233.33333 | X20: =(1400000/365)/8 -> 479.45205 | Y20: =((600000/4)*(44/30))/66 -> 3333.3333 | Z20: =((100000*2)/23)/30 -> 289.85507 | AA20: =SUM(T20:Z20)-W20-Y20 -> 1295.0102 | AB20: =(N20-AA20) -> -404.42044 | AC20: =(N20-AA20)/N20 -> -0.45410408
A21: 6 | B21: Education Data | C21: N | D21: =VLOOKUP(B21,'RPA RoadMap'!B:R,3,) -> 2981 | E21: =VLOOKUP(B21,'RPA RoadMap'!B:AA,4,FALSE) -> OCR | F21: =VLOOKUP(B21,'RPA RoadMap'!B:R,5,FALSE) -> Daily | G21: =VLOOKUP(B21,'RPA RoadMap'!B:R,13,FALSE) -> Complex | H21: =VLOOKUP(B21,'RPA RoadMap'!B:R,6,FALSE) -> 7 | I21: =((D21*H21)/60)/(200)/6.5 -> 0.26752564 | J21: =I21*(48000/30) -> 428.04103 | K21: =I21*(10785/30) -> 96.175468 | L21: =I21*(5283/30) -> 47.111265 | M21: =I21*(6432/30) -> 57.357497 | N21: =I21*(70500/30) -> 628.68526 | O21: =I21*0.6 -> 0.16051538 | P21: 8 | Q21: =((D21*P21/100)/60)/(200/12)/6.5 -> 0.036689231 | R21: =Q21*70500 -> 2586.5908 | S21: =I21-O21 -> 0.10701026 | T21: =S21*(70500/30) -> 251.4741 | U21: =(5000/30) -> 166.66667 | V21: =(((D21/365)*(P21))/60)*(49000/(30*24)) -> 74.109082 | W21: =(21000/30)/3 -> 233.33333 | X21: =(1400000/365)/8 -> 479.45205 | Y21: =((600000/4)*(58/30))/66 -> 4393.9394 | Z21: =((100000*2)/23)/30 -> 289.85507 | AA21: =SUM(T21:Z21)-W21-Y21 -> 1261.557 | AB21: =(N21-AA21) -> -632.87172 | AC21: =(N21-AA21)/N21 -> -1.0066591
A22: 6 | B22: National ID, PAN, Aadhar, Passport, Visa, Address | C22: N | D22: =VLOOKUP(B22,'RPA RoadMap'!B:R,3,) -> 9845 | E22: =VLOOKUP(B22,'RPA RoadMap'!B:AA,4,FALSE) -> OCR | F22: =VLOOKUP(B22,'RPA RoadMap'!B:R,5,FALSE) -> Weekly | G22: =VLOOKUP(B22,'RPA RoadMap'!B:R,13,FALSE) -> Complex | H22: =VLOOKUP(B22,'RPA RoadMap'!B:R,6,FALSE) -> 10 | I22: =((D22*H22)/60)/(200)/6.5 -> 1.2621795 | J22: =I22*(48000/30) -> 2019.4872 | K22: =I22*(10785/30) -> 453.75353 | L22: =I22*(5283/30) -> 222.26981 | M22: =I22*(6432/30) -> 270.61128 | N22: =I22*(70500/30) -> 2966.1218 | O22: =I22*0.6 -> 0.75730769 | P22: 8 | Q22: =((D22*P22/100)/60)/(200/12)/6.5 -> 0.12116923 | R22: =Q22*70500 -> 8542.4308 | S22: =I22-O22 -> 0.50487179 | T22: =S22*(70500/30) -> 1186.4487 | U22: =(5000/30) -> 166.66667 | V22: =(((D22/365)*(P22))/60)*(49000/(30*24)) -> 244.7514 | W22: =(21000/30)/3 -> 233.33333 | X22: =(1400000/365)/8 -> 479.45205 | Y22: =((600000/4)*(58/30))/66 -> 4393.9394 | Z22: =((100000*2)/23)/30 -> 289.85507 | AA22: =SUM(T22:Z22)-W22-Y22 -> 2367.1739 | AB22: =(N22-AA22) -> 598.94789 | AC22: =(N22-AA22)/N22 -> 0.20192963
A23: 7 | B23: Holiday Schedule upload | C23: N | D23: =VLOOKUP(B23,'RPA RoadMap'!B:R,3,) -> 10287 | E23: =VLOOKUP(B23,'RPA RoadMap'!B:AA,4,FALSE) -> NON-OCR | F23: =VLOOKUP(B23,'RPA RoadMap'!B:R,5,FALSE) -> Monthly | G23: =VLOOKUP(B23,'RPA RoadMap'!B:R,13,FALSE) -> Simple | H23: =VLOOKUP(B23,'RPA RoadMap'!B:R,6,FALSE) -> 10 | I23: =((D23*H23)/60)/(200)/6.5 -> 1.3188462 | J23: =I23*(48000/30) -> 2110.1538 | K23: =I23*(10785/30) -> 474.12519 | L23: =I23*(5283/30) -> 232.24881 | M23: =I23*(6432/30) -> 282.76062 | N23: =I23*(70500/30) -> 3099.2885 | O23: =I23*0.8 -> 1.0550769 | P23: 8 | Q23: =((D23*P23/100)/60)/(200/12)/6.5 -> 0.12660923 | R23: =Q23*70500 -> 8925.9508 | S23: =I23-O23 -> 0.26376923 | T23: =S23*(70500/30) -> 619.85769 | U23: =(5000/30) -> 166.66667 | V23: =(((D23/365)*(P23))/60)*(49000/(30*24)) -> 255.73973 | W23: =(21000/30)/3 -> 233.33333 | X23: =(1400000/365)/8 -> 479.45205 | Y23: =(((600000/4)/22)*24)/66 -> 2479.3388 | Z23: =((100000*2)/23)/30 -> 289.85507 | AA23: =SUM(T23:Z23)-W23-Y23 -> 1811.5712 | AB23: =(N23-AA23) -> 1287.7172 | AC23: =(N23-AA23)/N23 -> 0.41548803
A24: 8 | B24: Transfer of performance document | C24: N | D24: =VLOOKUP(B24,'RPA_SOP_Analysis_ABG Team SI-2'!A:G,4,) -> 3558 | E24: NON-OCR | F24: =VLOOKUP(B24,'RPA_SOP_Analysis_ABG Team SI-2'!A:G,6,FALSE) -> 0 | G24: Medium | H24: 10 | I24: =((D24*H24)/60)/(200)/6.5 -> 0.45615385 | J24: =I24*(48000/30) -> 729.84615 | K24: =I24*(10785/30) -> 163.98731 | L24: =I24*(5283/30) -> 80.328692 | M24: =I24*(6432/30) -> 97.799385 | N24: =I24*(70500/30) -> 1071.9615 | O24: =I24*0.7 -> 0.31930769 | P24: 8 | Q24: =((D24*P24/100)/60)/(200/12)/6.5 -> 0.043790769 | R24: =Q24*70500 -> 3087.2492 | S24: =I24-O24 -> 0.13684615 | T24: =S24*(70500/30) -> 321.58846 | U24: =(5000/30) -> 166.66667 | V24: =(((D24/365)*(P24))/60)*(49000/(30*24)) -> 88.453577 | W24: =(21000/30)/3 -> 233.33333 | X24: =(1400000/365)/8 -> 479.45205 | Y24: =(((600000/4)/22)*29)/66 -> 2995.8678 | Z24: =((100000*2)/23)/30 -> 289.85507 | AA24: =SUM(T24:Z24)-W24-Y24 -> 1346.0158 | AB24: =(N24-AA24) -> -274.05429 | AC24: =(N24-AA24)/N24 -> -0.25565683
A25: 9 | B25: Job Data Update (Excel Input / Bulk Data Update) | C25: N | D25: =VLOOKUP(B25,'RPA_SOP_Analysis_ABG Team SI-2'!A:G,4,) -> 45835 | E25: =VLOOKUP(B25,'RPA_SOP_Analysis_ABG Team SI-2'!A:G,5,FALSE) -> NON-OCR | F25: =VLOOKUP(B25,'RPA_SOP_Analysis_ABG Team SI-2'!A:G,6,FALSE) -> Daily | G25: Medium | H25: =VLOOKUP(B25,'RPA_SOP_Analysis_ABG Team SI-2'!A:G,7,FALSE) -> 10 | I25: =((D25*H25)/60)/(200)/6.5 -> 5.8762821 | J25: =I25*(48000/30) -> 9402.0513 | K25: =I25*(10785/30) -> 2112.5234 | L25: =I25*(5283/30) -> 1034.8133 | M25: =I25*(6432/30) -> 1259.8749 | N25: =I25*(70500/30) -> 13809.263 | O25: =I25*0.7 -> 4.1133974 | P25: 8 | Q25: =((D25*P25/100)/60)/(200/12)/6.5 -> 0.56412308 | R25: =Q25*70500 -> 39770.677 | S25: =I25-O25 -> 1.7628846 | T25: =S25*(70500/30) -> 4142.7788 | U25: =(5000/30) -> 166.66667 | V25: =(((D25/365)*(P25))/60)*(49000/(30*24)) -> 1139.48 | W25: =(21000/30)/3 -> 233.33333 | X25: =(1400000/365)/8 -> 479.45205 | Y25: =(((600000/4)/22)*29)/66 -> 2995.8678 | Z25: =((100000*2)/23)/30 -> 289.85507 | AA25: =SUM(T25:Z25)-W25-Y25 -> 6218.2326 | AB25: =(N25-AA25) -> 7591.0302 | AC25: =(N25-AA25)/N25 -> 0.54970568
A26: 10 | B26: Data Change – Data Change | C26: N | D26: =VLOOKUP(B26,'RPA RoadMap'!B:R,3,) -> 6804 | E26: =VLOOKUP(B26,'RPA RoadMap'!B:AA,4,FALSE) -> NON-OCR | F26: =VLOOKUP(B26,'RPA RoadMap'!B:R,5,FALSE) -> Daily | G26: =VLOOKUP(B26,'RPA RoadMap'!B:R,13,FALSE) -> Medium | H26: =VLOOKUP(B26,'RPA RoadMap'!B:R,6,FALSE) -> 10 | I26: =((D26*H26)/60)/(200)/6.5 -> 0.87230769 | J26: =I26*(48000/30) -> 1395.6923 | K26: =I26*(10785/30) -> 313.59462 | L26: =I26*(5283/30) -> 153.61338 | M26: =I26*(6432/30) -> 187.02277 | N26: =I26*(70500/30) -> 2049.9231 | O26: =I26*0.7 -> 0.61061538 | P26: 8 | Q26: =((D26*P26/100)/60)/(200/12)/6.5 -> 0.083741538 | R26: =Q26*70500 -> 5903.7785 | S26: =I26-O26 -> 0.26169231 | T26: =S26*(70500/30) -> 614.97692 | U26: =(5000/30) -> 166.66667 | V26: =(((D26/365)*(P26))/60)*(49000/(30*24)) -> 169.15068 | W26: =(21000/30)/3 -> 233.33333 | X26: =(1400000/365)/8 -> 479.45205 | Y26: =(((600000/4)/22)*29)/66 -> 2995.8678 | Z26: =((100000*2)/23)/30 -> 289.85507 | AA26: =SUM(T26:Z26)-W26-Y26 -> 1720.1014 | AB26: =(N26-AA26) -> 329.82167 | AC26: =(N26-AA26)/N26 -> 0.16089466
A28: Overall Program ROI | I28: =SUM(I4:I26) -> 41.828362 | N28: =SUM(N4:N26) -> 98296.651 | S28: =SUM(S4:S26) -> 14.589036 | T28: =SUM(T4:T26) -> 34284.235 | AA28: =SUM(AA4:AA26) -> 54328.03 | AB28: =(N28-AA28) -> 43968.621 | AC28: =(N28-AA28)/N28 -> 0.44730538

Sheet ROI-V2
A1: Use Case Meta Data | I1: Existing Manual Monthly Cost | O1: FTE Saved/Month | P1: BOT AHT | Q1: BOT FTE | R1: FTE Cost | S1: BOT Monthly Cost | AB1: ROI
A2: #Priority | B2: UseCase | C2: Already in Production | D2: AverageTransactions(Annual) | E2: OCR/NON-OCR | F2: Frequency | G2: Complexity | H2: Manual AHT in Min /Transaction | I2: Manual FTE Required/Month | J2: FTE Cost | K2: Seat Cost | L2: Employee Cost (Others - Paid by ABG)* | M2: Other OPEX Cost* | N2: Total Cost | S2: BOT FTE Required / Month | T2: FTE Cost | U2: Infra Cost | V2: License Cost | Y2: Development & Support | AA2: Total Cost | AB2: ROI in Rupees | AC2: ROI In Percent
V3: Runner | W3: Creater | X3: Document Automation | Y3: Development | Z3: Support
A4: NA | B4: Data Change – Override Manager | C4: Y | D4: =VLOOKUP(B4,'RPA RoadMap'!B:R,3,) -> 6089 | E4: =VLOOKUP(B4,'RPA RoadMap'!B:AA,4,FALSE) -> NON-OCR | F4: =VLOOKUP(B4,'RPA RoadMap'!B:R,5,FALSE) -> Daily | G4: =VLOOKUP(B4,'RPA RoadMap'!B:R,13,FALSE) -> Medium | H4: =((150*2)-71)/60 -> 3.8166667 | I4: =((D4*H4)/60)/(200/12)/6.5 -> 3.5753359 | J4: =I4*48000 -> 171616.12 | K4: =I4*10785 -> 38559.998 | L4: =I4*5283 -> 18888.5 | M4: =I4*6432 -> 22996.56 | N4: =I4*70500 -> 252061.18 | O4: =I4*0.85 -> 3.0390355 | P4: =(205-71)/60 -> 2.2333333 | Q4: =((D4*P4/100)/60)/(200/12)/6.5 -> 0.020921179 | R4: =Q4*70500 -> 1474.9432 | S4: =I4-O4 -> 0.53630038 | T4: =S4*70500 -> 37809.177 | U4: 5000 | V4: =(((D4/Configurations!$B$2)*(Configurations!$B$2/12))*(P4/100))*((49000/(Configurations!$B$2/12))/1440) -> 23.136791 | W4: 21000 | X4: 0 | Y4: =((600000/4)/22)*29 -> 197727.27 | Z4: =(175000*3)/23 -> 22826.087 | AA4: =SUM(T4:Z4)-W4 -> 263385.67 | AB4: =(N4-AA4) -> -11324.493 | AC4: =(N4-AA4)/N4 -> -0.044927556
A5: NA | B5: Data Change – Use Position Reports To | C5: Y | D5: =VLOOKUP(B5,'RPA RoadMap'!B:R,3,) -> 3933 | E5: =VLOOKUP(B5,'RPA RoadMap'!B:AA,4,FALSE) -> NON-OCR | F5: =VLOOKUP(B5,'RPA RoadMap'!B:R,5,FALSE) -> Daily | G5: =VLOOKUP(B5,'RPA RoadMap'!B:R,13,FALSE) -> Simple | H5: =((143*2)-69)/60 -> 3.6166667 | I5: =((D5*H5)/60)/(200/12)/6.5 -> 2.1883615 | J5: =I5*48000 -> 105041.35 | K5: =I5*10785 -> 23601.479 | L5: =I5*5283 -> 11561.114 | M5: =I5*6432 -> 14075.541 | N5: =I5*70500 -> 154279.49 | O5: =I5*0.85 -> 1.8601073 | P5: =(143-69)/60 -> 1.2333333 | Q5: =((D5*P5/100)/60)/(200/12)/6.5 -> 0.0074626154 | R5: =Q5*70500 -> 526.11438 | S5: =I5-O5 -> 0.32825423 | T5: =S5*70500 -> 23141.923 | U5: 5000 | V5: =(((D5/Configurations!$B$2)*(Configurations!$B$2/12))*(P5/100))*((49000/(Configurations!$B$2/12))/1440) -> 8.2529271 | W5: 21000 | X5: 0 | Y5: =((600000/4)/22)*19 -> 129545.45 | Z5: =(175000*3)/23 -> 22826.087 | AA5: =SUM(T5:Z5)-W5 -> 180521.72 | AB5: =(N5-AA5) -> -26242.229 | AC5: =(N5-AA5)/N5 -> -0.17009539
A6: NA | B6: Job Architecture | C6: Y | D6: =VLOOKUP(B6,'RPA RoadMap'!B:R,3,) -> 10692 | E6: =VLOOKUP(B6,'RPA RoadMap'!B:AA,4,FALSE) -> NON-OCR | F6: =VLOOKUP(B6,'RPA RoadMap'!B:R,5,FALSE) -> Daily | G6: =VLOOKUP(B6,'RPA RoadMap'!B:R,13,FALSE) -> Medium | H6: =((142*2)-93)/60 -> 3.1833333 | I6: =((D6*H6)/60)/(200/12)/6.5 -> 5.2363385 | J6: =I6*48000 -> 251344.25 | K6: =I6*10785 -> 56473.91 | L6: =I6*5283 -> 27663.576 | M6: =I6*6432 -> 33680.129 | N6: =I6*70500 -> 369161.86 | O6: =I6*0.85 -> 4.4508877 | P6: =(142-93)/60 -> 0.81666667 | Q6: =((D6*P6/100)/60)/(200/12)/6.5 -> 0.013433538 | R6: =Q6*70500 -> 947.06446 | S6: =I6-O6 -> 0.78545077 | T6: =S6*70500 -> 55374.279 | U6: 5000 | V6: =(((D6/Configurations!$B$2)*(Configurations!$B$2/12))*(P6/100))*((49000/(Configurations!$B$2/12))/1440) -> 14.856188 | W6: 21000 | X6: 0 | Y6: =((600000/4)/22)*29 -> 197727.27 | Z6: =(175000*3)/23 -> 22826.087 | AA6: =SUM(T6:Z6)-W6 -> 280942.5 | AB6: =(N6-AA6) -> 88219.366 | AC6: =(N6-AA6)/N6 -> 0.23897205
A7: NA | B7: Ticket Creater | C7: Y | D7: =VLOOKUP(B7,'RPA RoadMap'!B:R,3,) -> 48701 | E7: =VLOOKUP(B7,'RPA RoadMap'!B:AA,4,FALSE) -> NON-OCR | F7: =VLOOKUP(B7,'RPA RoadMap'!B:R,5,FALSE) -> Daily | G7: =VLOOKUP(B7,'RPA RoadMap'!B:R,13,FALSE) -> Complex | H7: =VLOOKUP(B7,'RPA RoadMap'!B:R,6,FALSE) -> 10 | I7: =((D7*H7)/60)/(200/12)/6.5 -> 74.924615 | J7: =I7*48000 -> 3596381.5 | K7: =I7*10785 -> 808061.98 | L7: =I7*5283 -> 395826.74 | M7: =I7*6432 -> 481915.13 | N7: =I7*70500 -> 5282185.4 | O7: =I7*0.6 -> 44.954769 | P7: =(191-160)/60 -> 0.51666667 | Q7: =((D7*P7/100)/60)/(200/12)/6.5 -> 0.038711051 | R7: =Q7*70500 -> 2729.1291 | S7: =I7-O7 -> 29.969846 | T7: =S7*70500 -> 2112874.2 | U7: 5000 | V7: =(((D7/Configurations!$B$2)*(Configurations!$B$2/12))*(P7/100))*((49000/(Configurations!$B$2/12))/1440) -> 42.810659 | W7: 21000 | X7: 0 | Y7: =(600000/4)*(43/30) -> 215000 | Z7: =(175000*3)/23 -> 22826.087 | AA7: =SUM(T7:Z7)-W7 -> 2355743.1 | AB7: =(N7-AA7) -> 2926442.3 | AC7: =(N7-AA7)/N7 -> 0.55402113
A8: NA | B8: Talent Profile Creation BOT | C8: Y | D8: =VLOOKUP(B8,'RPA RoadMap'!B:R,3,) -> 5310 | E8: =VLOOKUP(B8,'RPA RoadMap'!B:AA,4,FALSE) -> NON-OCR | F8: =VLOOKUP(B8,'RPA RoadMap'!B:R,5,FALSE) -> Based on requirement | G8: =VLOOKUP(B8,'RPA RoadMap'!B:R,13,FALSE) -> Complex | H8: =VLOOKUP(B8,'RPA RoadMap'!B:R,6,FALSE) -> 10 | I8: =((D8*H8)/60)/(200/12)/6.5 -> 8.1692308 | J8: =I8*48000 -> 392123.08 | K8: =I8*10785 -> 88105.154 | L8: =I8*5283 -> 43158.046 | M8: =I8*6432 -> 52544.492 | N8: =I8*70500 -> 575930.77 | O8: =I8*0.6 -> 4.9015385 | P8: =(180-163)/60 -> 0.28333333 | Q8: =((D8*P8/100)/60)/(200/12)/6.5 -> 0.0023146154 | R8: =Q8*70500 -> 163.18038 | S8: =I8-O8 -> 3.2676923 | T8: =S8*70500 -> 230372.31 | U8: 5000 | V8: =(((D8/Configurations!$B$2)*(Configurations!$B$2/12))*(P8/100))*((49000/(Configurations!$B$2/12))/1440) -> 2.5597396 | W8: 21000 | X8: 0 | Y8: =((600000/4))*(43/30) -> 215000 | Z8: =(175000*3)/23 -> 22826.087 | AA8: =SUM(T8:Z8)-W8 -> 473200.95 | AB8: =(N8-AA8) -> 102729.81 | AC8: =(N8-AA8)/N8 -> 0.17837181
A9: NA | B9: Poornata Status update - SR Update in Transaction | C9: Y | D9: =VLOOKUP(B9,'RPA RoadMap'!B:R,3,) -> 53182 | E9: =VLOOKUP(B9,'RPA RoadMap'!B:AA,4,FALSE) -> NON-OCR | F9: =VLOOKUP(B9,'RPA RoadMap'!B:R,5,FALSE) -> Daily | G9: =VLOOKUP(B9,'RPA RoadMap'!B:R,13,FALSE) -> Simple | H9: 5 | I9: =((D9*H9)/60)/(200/12)/6.5 -> 40.909231 | J9: =I9*48000 -> 1963643.1 | K9: =I9*10785 -> 441206.05 | L9: =I9*5283 -> 216123.47 | M9: =I9*6432 -> 263128.17 | N9: =I9*70500 -> 2884100.8 | O9: =I9*0.8 -> 32.727385 | P9: =(24)/60 -> 0.4 | Q9: =((D9*P9/100)/60)/(200/12)/6.5 -> 0.032727385 | R9: =Q9*70500 -> 2307.2806 | S9: =I9-O9 -> 8.1818462 | T9: =S9*70500 -> 576820.15 | U9: 5000 | V9: =(((D9/Configurations!$B$2)*(Configurations!$B$2/12))*(P9/100))*((49000/(Configurations!$B$2/12))/1440) -> 36.193306 | W9: 21000 | X9: 0 | Y9: =((600000/4)/22)*24 -> 163636.36 | Z9: =(175000*3)/23 -> 22826.087 | AA9: =SUM(T9:Z9)-W9 -> 768318.8 | AB9: =(N9-AA9) -> 2115782 | AC9: =(N9-AA9)/N9 -> 0.73360196
A10: NA | B10: Audit Sampling | C10: Y | D10: =VLOOKUP(B10,'RPA RoadMap'!B:R,3,) -> 5000 | E10: =VLOOKUP(B10,'RPA RoadMap'!B:AA,4,FALSE) -> NON-OCR | F10: =VLOOKUP(B10,'RPA RoadMap'!B:R,5,FALSE) -> Based on requirement | G10: =VLOOKUP(B10,'RPA RoadMap'!B:R,13,FALSE) -> Simple | H10: =VLOOKUP(B10,'RPA RoadMap'!B:R,6,FALSE) -> 10 | I10: =((D10*H10)/60)/(200/12)/6.5 -> 7.6923077 | J10: =I10*48000 -> 369230.77 | K10: =I10*10785 -> 82961.538 | L10: =I10*5283 -> 40638.462 | M10: =I10*6432 -> 49476.923 | N10: =I10*70500 -> 542307.69 | O10: =I10*0.8 -> 6.1538462 | P10: =24/60 -> 0.4 | Q10: =((D10*P10/100)/60)/(200/12)/6.5 -> 0.0030769231 | R10: =Q10*70500 -> 216.92308 | S10: =I10-O10 -> 1.5384615 | T10: =S10*70500 -> 108461.54 | U10: 5000 | V10: =(((D10/Configurations!$B$2)*(Configurations!$B$2/12))*(P10))*((49000/(Configurations!$B$2/12))/1440) -> 340.27778 | W10: 21000 | X10: 0 | Y10: =((600000/4)/22)*24 -> 163636.36 | Z10: =(175000*3)/23 -> 22826.087 | AA10: =SUM(T10:Z10)-W10 -> 300264.27 | AB10: =(N10-AA10) -> 242043.43 | AC10: =(N10-AA10)/N10 -> 0.44632121
A11: NA | B11: Cement ticket creator | C11: Y | D11: =VLOOKUP(B11,'RPA RoadMap'!B:R,3,) -> 5000 | E11: =VLOOKUP(B11,'RPA RoadMap'!B:AA,4,FALSE) -> NON-OCR | F11: =VLOOKUP(B11,'RPA RoadMap'!B:R,5,FALSE) -> Daily | G11: =VLOOKUP(B11,'RPA RoadMap'!B:R,13,FALSE) -> Complex | H11: =VLOOKUP(B11,'RPA RoadMap'!B:R,6,FALSE) -> 10 | I11: =((D11*H11)/60)/(200/12)/6.5 -> 7.6923077 | J11: =I11*48000 -> 369230.77 | K11: =I11*10785 -> 82961.538 | L11: =I11*5283 -> 40638.462 | M11: =I11*6432 -> 49476.923 | N11: =I11*70500 -> 542307.69 | O11: =I11*0.6 -> 4.6153846 | P11: =(127-80)/60 -> 0.78333333 | Q11: =((D11*P11/100)/60)/(200/12)/6.5 -> 0.006025641 | R11: =Q11*70500 -> 424.80769 | S11: =I11-O11 -> 3.0769231 | T11: =S11*70500 -> 216923.08 | U11: 5000 | V11: =(((D11/Configurations!$B$2)*(Configurations!$B$2/12))*(P11/100))*((49000/(Configurations!$B$2/12))/1440) -> 6.6637731 | W11: 21000 | X11: 0 | Y11: =(600000/4)*(43/30) -> 215000 | Z11: =(175000*3)/23 -> 22826.087 | AA11: =SUM(T11:Z11)-W11 -> 459755.83 | AB11: =(N11-AA11) -> 82551.865 | AC11: =(N11-AA11)/N11 -> 0.1522233
A12: NA | B12: Potential Assesment | C12: Y | D12: =VLOOKUP(B12,'RPA RoadMap'!B:R,3,) -> 6316 | E12: =VLOOKUP(B12,'RPA RoadMap'!B:AA,4,FALSE) -> NON-OCR | F12: =VLOOKUP(B12,'RPA RoadMap'!B:R,5,FALSE) -> Based on requirement | G12: =VLOOKUP(B12,'RPA RoadMap'!B:R,13,FALSE) -> Medium | H12: =VLOOKUP(B12,'RPA RoadMap'!B:R,6,FALSE) -> 10 | I12: =((D12*H12)/60)/(200/12)/6.5 -> 9.7169231 | J12: =I12*48000 -> 466412.31 | K12: =I12*10785 -> 104797.02 | L12: =I12*5283 -> 51334.505 | M12: =I12*6432 -> 62499.249 | N12: =I12*70500 -> 685043.08 | O12: =I12*0.7 -> 6.8018462 | P12: 8 | Q12: =((D12*P12/100)/60)/(200/12)/6.5 -> 0.077735385 | R12: =Q12*70500 -> 5480.3446 | S12: =I12-O12 -> 2.9150769 | T12: =S12*70500 -> 205512.92 | U12: 5000 | V12: =(((D12/Configurations!$B$2)*(Configurations!$B$2/12))*(P12/100))*((49000/(Configurations!$B$2/12))/1440) -> 85.967778 | W12: 21000 | X12: 0 | Y12: =((600000/4)/22)*29 -> 197727.27 | Z12: =(175000*3)/23 -> 22826.087 | AA12: =SUM(T12:Z12)-W12 -> 431152.25 | AB12: =(N12-AA12) -> 253890.83 | AC12: =(N12-AA12)/N12 -> 0.37062024
A13: 0 | B13: Job Description Update | C13: N | D13: =VLOOKUP(B13,'RPA RoadMap'!B:R,3,) -> 7168 | E13: =VLOOKUP(B13,'RPA RoadMap'!B:AA,4,FALSE) -> NON-OCR | F13: =VLOOKUP(B13,'RPA RoadMap'!B:R,5,FALSE) -> Daily | G13: =VLOOKUP(B13,'RPA RoadMap'!B:R,13,FALSE) -> Complex | H13: =VLOOKUP(B13,'RPA RoadMap'!B:R,6,FALSE) -> 10 | I13: =((D13*H13)/60)/(200/12)/6.5 -> 11.027692 | J13: =I13*48000 -> 529329.23 | K13: =I13*10785 -> 118933.66 | L13: =I13*5283 -> 58259.298 | M13: =I13*6432 -> 70930.117 | N13: =I13*70500 -> 777452.31 | O13: =I13*0.6 -> 6.6166154 | P13: 8 | Q13: =((D13*P13/100)/60)/(200/12)/6.5 -> 0.088221538 | R13: =Q13*70500 -> 6219.6185 | S13: =I13-O13 -> 4.4110769 | T13: =S13*70500 -> 310980.92 | U13: 5000 | V13: =(((D13/Configurations!$B$2)*(Configurations!$B$2/12))*(P13/100))*((49000/(Configurations!$B$2/12))/1440) -> 97.564444 | W13: 21000 | X13: 0 | Y13: =((600000/4)/22)*29 -> 197727.27 | Z13: =(175000*3)/23 -> 22826.087 | AA13: =SUM(T13:Z13)-W13 -> 536631.85 | AB13: =(N13-AA13) -> 240820.46 | AC13: =(N13-AA13)/N13 -> 0.30975593
A14: 0 | B14: FnF Settlement | C14: N | D14: =VLOOKUP(B14,'RPA RoadMap'!B:R,3,) -> 12829 | E14: =VLOOKUP(B14,'RPA RoadMap'!B:AA,4,FALSE) -> NON-OCR | F14: =VLOOKUP(B14,'RPA RoadMap'!B:R,5,FALSE) -> Monthly | G14: =VLOOKUP(B14,'RPA RoadMap'!B:R,13,FALSE) -> Complex | H14: =VLOOKUP(B14,'RPA RoadMap'!B:R,6,FALSE) -> 10 | I14: =((D14*H14)/60)/(200/12)/6.5 -> 19.736923 | J14: =I14*48000 -> 947372.31 | K14: =I14*10785 -> 212862.72 | L14: =I14*5283 -> 104270.16 | M14: =I14*6432 -> 126947.89 | N14: =I14*70500 -> 1391453.1 | O14: =I14*0.6 -> 11.842154 | P14: 8 | Q14: =((D14*P14/100)/60)/(200/12)/6.5 -> 0.15789538 | R14: =Q14*70500 -> 11131.625 | S14: =I14-O14 -> 7.8947692 | T14: =S14*70500 -> 556581.23 | U14: 5000 | V14: =(((D14/Configurations!$B$2)*(Configurations!$B$2/12))*(P14/100))*((49000/(Configurations!$B$2/12))/1440) -> 174.61694 | W14: 21000 | X14: 0 | Y14: =((600000/4)/22)*29 -> 197727.27 | Z14: =(175000*3)/23 -> 22826.087 | AA14: =SUM(T14:Z14)-W14 -> 782309.21 | AB14: =(N14-AA14) -> 609143.87 | AC14: =(N14-AA14)/N14 -> 0.43777536
A15: 1 | B15: Initiate EJF Verification Process | C15: N | D15: =VLOOKUP(B15,'RPA_SOP_Analysis_ABG Team SI-2'!A:G,4,) -> 14999 | E15: OCR | F15: =VLOOKUP(B15,'RPA_SOP_Analysis_ABG Team SI-2'!A:G,6,FALSE) -> 0 | G15: Complex | H15: 30 | I15: =((D15*H15)/60)/(200/12)/6.5 -> 69.226154 | J15: =I15*48000 -> 3322855.4 | K15: =I15*10785 -> 746604.07 | L15: =I15*5283 -> 365721.77 | M15: =I15*6432 -> 445262.62 | N15: =I15*70500 -> 4880443.8 | O15: =I15*0.6 -> 41.535692 | P15: 8 | Q15: =((D15*P15/100)/60)/(200/12)/6.5 -> 0.18460308 | R15: =Q15*70500 -> 13014.517 | S15: =I15-O15 -> 27.690462 | T15: =S15*70500 -> 1952177.5 | U15: 5000 | V15: =(((D15/Configurations!$B$2)*(Configurations!$B$2/12))*(P15/100))*((49000/(Configurations!$B$2/12))/1440) -> 204.15306 | W15: 21000 | X15: =(1400000/12)/8 -> 14583.333 | Y15: =(600000/4)*(58/30) -> 290000 | Z15: =(175000*3)/23 -> 22826.087 | AA15: =SUM(T15:Z15)-W15 -> 2284791.1 | AB15: =(N15-AA15) -> 2595652.7 | AC15: =(N15-AA15)/N15 -> 0.53184768
A16: 2 | B16: Poornata ID Creation (Add a Person) (Proposed Process Change) | C16: N | D16: =VLOOKUP(B16,'RPA RoadMap'!B:R,3,) -> 8925 | E16: =VLOOKUP(B16,'RPA RoadMap'!B:AA,4,FALSE) -> OCR | F16: =VLOOKUP(B16,'RPA RoadMap'!B:R,5,FALSE) -> Daily | G16: =VLOOKUP(B16,'RPA RoadMap'!B:R,13,FALSE) -> Complex | H16: =VLOOKUP(B16,'RPA RoadMap'!B:R,6,FALSE) -> 25 | I16: =((D16*H16)/60)/(200/12)/6.5 -> 34.326923 | J16: =I16*48000 -> 1647692.3 | K16: =I16*10785 -> 370215.87 | L16: =I16*5283 -> 181349.13 | M16: =I16*6432 -> 220790.77 | N16: =I16*70500 -> 2420048.1 | O16: =I16*0.6 -> 20.596154 | P16: 8 | Q16: =((D16*P16/100)/60)/(200/12)/6.5 -> 0.10984615 | R16: =Q16*70500 -> 7744.1538 | S16: =I16-O16 -> 13.730769 | T16: =S16*70500 -> 968019.23 | U16: 5000 | V16: =(((D16/Configurations!$B$2)*(Configurations!$B$2/12))*(P16/100))*((49000/(Configurations!$B$2/12))/1440) -> 121.47917 | W16: 21000 | X16: =(1400000/12)/8 -> 14583.333 | Y16: =(600000/4)*(58/30) -> 290000 | Z16: =(175000*3)/23 -> 22826.087 | AA16: =SUM(T16:Z16)-W16 -> 1300550.1 | AB16: =(N16-AA16) -> 1119497.9 | AC16: =(N16-AA16)/N16 -> 0.46259327
A17: 2 | B17: Poornata ID creation (Through External Hire) – QC action and update if missing data-Proposed process change | C17: N | D17: =VLOOKUP(B17,'RPA RoadMap'!B:R,3,) -> 5854 | E17: =VLOOKUP(B17,'RPA RoadMap'!B:AA,4,FALSE) -> OCR | F17: =VLOOKUP(B17,'RPA RoadMap'!B:R,5,FALSE) -> Daily | G17: =VLOOKUP(B17,'RPA RoadMap'!B:R,13,FALSE) -> Complex | H17: =VLOOKUP(B17,'RPA RoadMap'!B:R,6,FALSE) -> 25 | I17: =((D17*H17)/60)/(200/12)/6.5 -> 22.515385 | J17: =I17*48000 -> 1080738.5 | K17: =I17*10785 -> 242828.42 | L17: =I17*5283 -> 118948.78 | M17: =I17*6432 -> 144818.95 | N17: =I17*70500 -> 1587334.6 | O17: =I17*0.6 -> 13.509231 | P17: 8 | Q17: =((D17*P17/100)/60)/(200/12)/6.5 -> 0.072049231 | R17: =Q17*70500 -> 5079.4708 | S17: =I17-O17 -> 9.0061538 | T17: =S17*70500 -> 634933.85 | U17: 5000 | V17: =(((D17/Configurations!$B$2)*(Configurations!$B$2/12))*(P17/100))*((49000/(Configurations!$B$2/12))/1440) -> 79.679444 | W17: 21000 | X17: =(1400000/12)/8 -> 14583.333 | Y17: =(600000/4)*(58/30) -> 290000 | Z17: =(175000*3)/23 -> 22826.087 | AA17: =SUM(T17:Z17)-W17 -> 967422.95 | AB17: =(N17-AA17) -> 619911.67 | AC17: =(N17-AA17)/N17 -> 0.39053623
A18: 3 | B18: Pratibha - OCR | C18: N | D18: =VLOOKUP(B18,'RPA_SOP_Analysis_ABG Team SI-2'!A:G,4,) -> 540 | E18: =VLOOKUP(B18,'RPA_SOP_Analysis_ABG Team SI-2'!A:G,5,FALSE) -> OCR | F18: =VLOOKUP(B18,'RPA_SOP_Analysis_ABG Team SI-2'!A:G,6,FALSE) -> Yearly | G18: Complex | H18: 120 | I18: =((D18*H18)/60)/(200/12)/6.5 -> 9.9692308 | J18: =I18*48000 -> 478523.08 | K18: =I18*10785 -> 107518.15 | L18: =I18*5283 -> 52667.446 | M18: =I18*6432 -> 64122.092 | N18: =I18*70500 -> 702830.77 | O18: =I18*0.6 -> 5.9815385 | P18: 8 | Q18: =((D18*P18/100)/60)/(200/12)/6.5 -> 0.0066461538 | R18: =Q18*70500 -> 468.55385 | S18: =I18-O18 -> 3.9876923 | T18: =S18*70500 -> 281132.31 | U18: 5000 | V18: =(((D18/Configurations!$B$2)*(Configurations!$B$2/12))*(P18/100))*((49000/(Configurations!$B$2/12))/1440) -> 7.35 | W18: 21000 | X18: =(1400000/12)/8 -> 14583.333 | Y18: =(600000/4)*(58/30) -> 290000 | Z18: =(175000*3)/23 -> 22826.087 | AA18: =SUM(T18:Z18)-W18 -> 613549.08 | AB18: =(N18-AA18) -> 89281.691 | AC18: =(N18-AA18)/N18 -> 0.12703156
A19: 4 | B19: AWOO(A world of opprtunity) - OCR | C19: N | D19: =VLOOKUP(B19,'RPA_SOP_Analysis_ABG Team SI-2'!A:G,4,) -> 2700 | E19: =VLOOKUP(B19,'RPA_SOP_Analysis_ABG Team SI-2'!A:G,5,FALSE) -> OCR | F19: =VLOOKUP(B19,'RPA_SOP_Analysis_ABG Team SI-2'!A:G,6,FALSE) -> Yearly | G19: Complex | H19: 120 | I19: =((D19*H19)/60)/(200/12)/6.5 -> 49.846154 | J19: =I19*48000 -> 2392615.4 | K19: =I19*10785 -> 537590.77 | L19: =I19*5283 -> 263337.23 | M19: =I19*6432 -> 320610.46 | N19: =I19*70500 -> 3514153.8 | O19: =I19*0.6 -> 29.907692 | P19: 8 | Q19: =((D19*P19/100)/60)/(200/12)/6.5 -> 0.033230769 | R19: =Q19*70500 -> 2342.7692 | S19: =I19-O19 -> 19.938462 | T19: =S19*70500 -> 1405661.5 | U19: 5000 | V19: =(((D19/Configurations!$B$2)*(Configurations!$B$2/12))*(P19/100))*((49000/(Configurations!$B$2/12))/1440) -> 36.75 | W19: 21000 | X19: =(1400000/12)/8 -> 14583.333 | Y19: =(600000/4)*(58/30) -> 290000 | Z19: =(175000*3)/23 -> 22826.087 | AA19: =SUM(T19:Z19)-W19 -> 1738107.7 | AB19: =(N19-AA19) -> 1776046.1 | AC19: =(N19-AA19)/N19 -> 0.50539795
A20: 5 | B20: Bank Data Update | C20: N | D20: =VLOOKUP(B20,'RPA RoadMap'!B:R,3,) -> 3695 | E20: =VLOOKUP(B20,'RPA RoadMap'!B:AA,4,FALSE) -> OCR | F20: =VLOOKUP(B20,'RPA RoadMap'!B:R,5,FALSE) -> Weekly | G20: =VLOOKUP(B20,'RPA RoadMap'!B:R,13,FALSE) -> Medium | H20: =VLOOKUP(B20,'RPA RoadMap'!B:R,6,FALSE) -> 8 | I20: =((D20*H20)/60)/(200/12)/6.5 -> 4.5476923 | J20: =I20*48000 -> 218289.23 | K20: =I20*10785 -> 49046.862 | L20: =I20*5283 -> 24025.458 | M20: =I20*6432 -> 29250.757 | N20: =I20*70500 -> 320612.31 | O20: =I20*0.7 -> 3.1833846 | P20: 8 | Q20: =((D20*P20/100)/60)/(200/12)/6.5 -> 0.045476923 | R20: =Q20*70500 -> 3206.1231 | S20: =I20-O20 -> 1.3643077 | T20: =S20*70500 -> 96183.692 | U20: 5000 | V20: =(((D20/Configurations!$B$2)*(Configurations!$B$2/12))*(P20/100))*((49000/(Configurations!$B$2/12))/1440) -> 50.293056 | W20: 21000 | X20: =(1400000/12)/8 -> 14583.333 | Y20: =(600000/4)*(44/30) -> 220000 | Z20: =(175000*3)/23 -> 22826.087 | AA20: =SUM(T20:Z20)-W20 -> 358643.41 | AB20: =(N20-AA20) -> -38031.098 | AC20: =(N20-AA20)/N20 -> -0.11862021
A21: 6 | B21: Education Data | C21: N | D21: =VLOOKUP(B21,'RPA RoadMap'!B:R,3,) -> 2981 | E21: =VLOOKUP(B21,'RPA RoadMap'!B:AA,4,FALSE) -> OCR | F21: =VLOOKUP(B21,'RPA RoadMap'!B:R,5,FALSE) -> Daily | G21: =VLOOKUP(B21,'RPA RoadMap'!B:R,13,FALSE) -> Complex | H21: =VLOOKUP(B21,'RPA RoadMap'!B:R,6,FALSE) -> 7 | I21: =((D21*H21)/60)/(200/12)/6.5 -> 3.2103077 | J21: =I21*48000 -> 154094.77 | K21: =I21*10785 -> 34623.168 | L21: =I21*5283 -> 16960.056 | M21: =I21*6432 -> 20648.699 | N21: =I21*70500 -> 226326.69 | O21: =I21*0.6 -> 1.9261846 | P21: 8 | Q21: =((D21*P21/100)/60)/(200/12)/6.5 -> 0.036689231 | R21: =Q21*70500 -> 2586.5908 | S21: =I21-O21 -> 1.2841231 | T21: =S21*70500 -> 90530.677 | U21: 5000 | V21: =(((D21/Configurations!$B$2)*(Configurations!$B$2/12))*(P21/100))*((49000/(Configurations!$B$2/12))/1440) -> 40.574722 | W21: 21000 | X21: =(1400000/12)/8 -> 14583.333 | Y21: =(600000/4)*(58/30) -> 290000 | Z21: =(175000*3)/23 -> 22826.087 | AA21: =SUM(T21:Z21)-W21 -> 422980.67 | AB21: =(N21-AA21) -> -196653.98 | AC21: =(N21-AA21)/N21 -> -0.86889433
A22: 6 | B22: National ID, PAN, Aadhar, Passport, Visa, Address | C22: N | D22: =VLOOKUP(B22,'RPA RoadMap'!B:R,3,) -> 9845 | E22: =VLOOKUP(B22,'RPA RoadMap'!B:AA,4,FALSE) -> OCR | F22: =VLOOKUP(B22,'RPA RoadMap'!B:R,5,FALSE) -> Weekly | G22: =VLOOKUP(B22,'RPA RoadMap'!B:R,13,FALSE) -> Complex | H22: =VLOOKUP(B22,'RPA RoadMap'!B:R,6,FALSE) -> 10 | I22: =((D22*H22)/60)/(200/12)/6.5 -> 15.146154 | J22: =I22*48000 -> 727015.38 | K22: =I22*10785 -> 163351.27 | L22: =I22*5283 -> 80017.131 | M22: =I22*6432 -> 97420.062 | N22: =I22*70500 -> 1067803.8 | O22: =I22*0.6 -> 9.0876923 | P22: 8 | Q22: =((D22*P22/100)/60)/(200/12)/6.5 -> 0.12116923 | R22: =Q22*70500 -> 8542.4308 | S22: =I22-O22 -> 6.0584615 | T22: =S22*70500 -> 427121.54 | U22: 5000 | V22: =(((D22/Configurations!$B$2)*(Configurations!$B$2/12))*(P22/100))*((49000/(Configurations!$B$2/12))/1440) -> 134.00139 | W22: 21000 | X22: =(1400000/12)/8 -> 14583.333 | Y22: =(600000/4)*(58/30) -> 290000 | Z22: =(175000*3)/23 -> 22826.087 | AA22: =SUM(T22:Z22)-W22 -> 759664.96 | AB22: =(N22-AA22) -> 308138.89 | AC22: =(N22-AA22)/N22 -> 0.28857256
A23: 7 | B23: Holiday Schedule upload | C23: N | D23: =VLOOKUP(B23,'RPA RoadMap'!B:R,3,) -> 10287 | E23: =VLOOKUP(B23,'RPA RoadMap'!B:AA,4,FALSE) -> NON-OCR | F23: =VLOOKUP(B23,'RPA RoadMap'!B:R,5,FALSE) -> Monthly | G23: =VLOOKUP(B23,'RPA RoadMap'!B:R,13,FALSE) -> Simple | H23: =VLOOKUP(B23,'RPA RoadMap'!B:R,6,FALSE) -> 10 | I23: =((D23*H23)/60)/(200/12)/6.5 -> 15.826154 | J23: =I23*48000 -> 759655.38 | K23: =I23*10785 -> 170685.07 | L23: =I23*5283 -> 83609.571 | M23: =I23*6432 -> 101793.82 | N23: =I23*70500 -> 1115743.8 | O23: =I23*0.8 -> 12.660923 | P23: 8 | Q23: =((D23*P23/100)/60)/(200/12)/6.5 -> 0.12660923 | R23: =Q23*70500 -> 8925.9508 | S23: =I23-O23 -> 3.1652308 | T23: =S23*70500 -> 223148.77 | U23: 5000 | V23: =(((D23/Configurations!$B$2)*(Configurations!$B$2/12))*(P23/100))*((49000/(Configurations!$B$2/12))/1440) -> 140.0175 | W23: 21000 | X23: 0 | Y23: =((600000/4)/22)*24 -> 163636.36 | Z23: =(175000*3)/23 -> 22826.087 | AA23: =SUM(T23:Z23)-W23 -> 414751.24 | AB23: =(N23-AA23) -> 700992.61 | AC23: =(N23-AA23)/N23 -> 0.62827378
A24: 8 | B24: Transfer of performance document | C24: N | D24: =VLOOKUP(B24,'RPA_SOP_Analysis_ABG Team SI-2'!A:G,4,) -> 3558 | E24: NON-OCR | F24: =VLOOKUP(B24,'RPA_SOP_Analysis_ABG Team SI-2'!A:G,6,FALSE) -> 0 | G24: Medium | H24: 10 | I24: =((D24*H24)/60)/(200/12)/6.5 -> 5.4738462 | J24: =I24*48000 -> 262744.62 | K24: =I24*10785 -> 59035.431 | L24: =I24*5283 -> 28918.329 | M24: =I24*6432 -> 35207.778 | N24: =I24*70500 -> 385906.15 | O24: =I24*0.7 -> 3.8316923 | P24: 8 | Q24: =((D24*P24/100)/60)/(200/12)/6.5 -> 0.043790769 | R24: =Q24*70500 -> 3087.2492 | S24: =I24-O24 -> 1.6421538 | T24: =S24*70500 -> 115771.85 | U24: 5001 | V24: =(((D24/Configurations!$B$2)*(Configurations!$B$2/12))*(P24/100))*((49000/(Configurations!$B$2/12))/1440) -> 48.428333 | W24: 21000 | X24: 0 | Y24: =((600000/4)/22)*29 -> 197727.27 | Z24: =(175000*3)/23 -> 22826.087 | AA24: =SUM(T24:Z24)-W24 -> 341374.63 | AB24: =(N24-AA24) -> 44531.52 | AC24: =(N24-AA24)/N24 -> 0.11539469
A25: 9 | B25: Job Data Update (Excel Input / Bulk Data Update) | C25: N | D25: =VLOOKUP(B25,'RPA_SOP_Analysis_ABG Team SI-2'!A:G,4,) -> 45835 | E25: =VLOOKUP(B25,'RPA_SOP_Analysis_ABG Team SI-2'!A:G,5,FALSE) -> NON-OCR | F25: =VLOOKUP(B25,'RPA_SOP_Analysis_ABG Team SI-2'!A:G,6,FALSE) -> Daily | G25: Medium | H25: =VLOOKUP(B25,'RPA_SOP_Analysis_ABG Team SI-2'!A:G,7,FALSE) -> 10 | I25: =((D25*H25)/60)/(200/12)/6.5 -> 70.515385 | J25: =I25*48000 -> 3384738.5 | K25: =I25*10785 -> 760508.42 | L25: =I25*5283 -> 372532.78 | M25: =I25*6432 -> 453554.95 | N25: =I25*70500 -> 4971334.6 | O25: =I25*0.7 -> 49.360769 | P25: 8 | Q25: =((D25*P25/100)/60)/(200/12)/6.5 -> 0.56412308 | R25: =Q25*70500 -> 39770.677 | S25: =I25-O25 -> 21.154615 | T25: =S25*70500 -> 1491400.4 | U25: 5000 | V25: =(((D25/Configurations!$B$2)*(Configurations!$B$2/12))*(P25/100))*((49000/(Configurations!$B$2/12))/1440) -> 623.86528 | W25: 21000 | X25: 0 | Y25: =((600000/4)/22)*29 -> 197727.27 | Z25: =(175000*3)/23 -> 22826.087 | AA25: =SUM(T25:Z25)-W25 -> 1717577.6 | AB25: =(N25-AA25) -> 3253757 | AC25: =(N25-AA25)/N25 -> 0.65450372
A26: 10 | B26: Data Change – Data Change | C26: N | D26: =VLOOKUP(B26,'RPA RoadMap'!B:R,3,) -> 6804 | E26: =VLOOKUP(B26,'RPA RoadMap'!B:AA,4,FALSE) -> NON-OCR | F26: =VLOOKUP(B26,'RPA RoadMap'!B:R,5,FALSE) -> Daily | G26: =VLOOKUP(B26,'RPA RoadMap'!B:R,13,FALSE) -> Medium | H26: =VLOOKUP(B26,'RPA RoadMap'!B:R,6,FALSE) -> 10 | I26: =((D26*H26)/60)/(200/12)/6.5 -> 10.467692 | J26: =I26*48000 -> 502449.23 | K26: =I26*10785 -> 112894.06 | L26: =I26*5283 -> 55300.818 | M26: =I26*6432 -> 67328.197 | N26: =I26*70500 -> 737972.31 | O26: =I26*0.7 -> 7.3273846 | P26: 8 | Q26: =((D26*P26/100)/60)/(200/12)/6.5 -> 0.083741538 | R26: =Q26*70500 -> 5903.7785 | S26: =I26-O26 -> 3.1403077 | T26: =S26*70500 -> 221391.69 | U26: 5000 | V26: =(((D26/Configurations!$B$2)*(Configurations!$B$2/12))*(P26/100))*((49000/(Configurations!$B$2/12))/1440) -> 92.61 | W26: 21000 | X26: 0 | Y26: =((600000/4)/22)*29 -> 197727.27 | Z26: =(175000*3)/23 -> 22826.087 | AA26: =SUM(T26:Z26)-W26 -> 447037.66 | AB26: =(N26-AA26) -> 290934.65 | AC26: =(N26-AA26)/N26 -> 0.39423518
I27: =SUM(I4:I26) -> 501.94034 | J27: =I27*48000 -> 24093136 | K27: =I27*10785 -> 5413426.6 | L27: =I27*5283 -> 2651750.8 | M27: =I27*6432 -> 3228480.3 | N27: =I27*70500 -> 35386794 | O27: =SUM(O4:O26) -> 326.87191 | S27: =SUM(S4:S26) -> 175.06844
A28: Overall Program ROI | N28: =SUM(N4:N27) -> 70773588 | AA28: =SUM(AA4:AA26) -> 18198677 | AB28: =(N28-AA28) -> 52574911 | AC28: =(N28-AA28)/N28 -> 0.74286061

Sheet Configurations
A1: Parameter | B1: Value
A2: Days Per Year | B2: 200
A3: Days Per Month | B3: =B2/12 -> 16.666667
A4: Infra Cost | B4: 5000
A5: Working Hours Per day | B5: 6.5
A6: Mins Per Hour | B6: 60
A7: FTE Saved Simple | B7: 0.8
A8: FTE Saved Medium | B8: 0.7
A9: FTE Saved Complex | B9: 0.6

Sheet Runner Cost Verification
A1: Runner License Verification | G1: Annual Transaction | H1: AHT Per transaction | I1: Total Annual Mins | K1: Total Annual HR | M1: Total Monthly HR | O1: FTE Required
A2: Transactions per year | B2: 6089 | E2: 6089 | G2: 6089 | H2: 3.82 | I2: =G2*H2 -> 23259.98 | K2: =I2/60 -> 387.66633 | M2: =K2/(200/12) -> 23.25998 | O2: =M2/6.5 -> 3.5784585
A3: Days per year | B3: 200 | E3: 200 | G3: 3933 | H3: 3.62 | I3: =G3*H3 -> 14237.46 | K3: =I3/60 -> 237.291 | M3: =K3/(200/12) -> 14.23746 | O3: =M3/6.5 -> 2.1903785
A4: Transaction Per Month | B4: =(B2/B3)*(B3/12) -> 507.41667 | E4: =E2/E3 -> 30.445 | G4: 10692 | H4: 3.18 | I4: =G4*H4 -> 34000.56 | K4: =I4/60 -> 566.676 | M4: =K4/(200/12) -> 34.00056 | O4: =M4/6.5 -> 5.2308554
A5: AHT per transaction (mins) | B5: =2.23/100 -> 0.0223 | G5: 48701 | H5: 10 | I5: =G5*H5 -> 487010 | K5: =I5/60 -> 8116.8333 | M5: =K5/(200/12) -> 487.01 | O5: =M5/6.5 -> 74.924615
A6: Runner license cost per month (INR) | B6: 49000 | G6: 5310 | H6: 10 | I6: =G6*H6 -> 53100 | K6: =I6/60 -> 885 | M6: =K6/(200/12) -> 53.1 | O6: =M6/6.5 -> 8.1692308
A7: Runner license cost per day (INR) | B7: =B6/(B3/12) -> 2940 | G7: 53182 | H7: 5 | I7: =G7*H7 -> 265910 | K7: =I7/60 -> 4431.8333 | M7: =K7/(200/12) -> 265.91 | O7: =M7/6.5 -> 40.909231
A8: Minutes per day | B8: =24*60 -> 1440 | G8: 5000 | H8: 10 | I8: =G8*H8 -> 50000 | K8: =I8/60 -> 833.33333 | M8: =K8/(200/12) -> 50 | O8: =M8/6.5 -> 7.6923077
A9: Runner license cost per minute (INR) | B9: =B7/B8 -> 2.0416667 | G9: 5000 | H9: 10 | I9: =G9*H9 -> 50000 | K9: =I9/60 -> 833.33333 | M9: =K9/(200/12) -> 50 | O9: =M9/6.5 -> 7.6923077
A10: Time required for BOT | B10: =B4*B5 -> 11.315392 | G10: 6316 | H10: 10 | I10: =G10*H10 -> 63160 | K10: =I10/60 -> 1052.6667 | M10: =K10/(200/12) -> 63.16 | O10: =M10/6.5 -> 9.7169231
A11: Total cost | B11: =B10*B9 -> 23.102258 | G11: 7168 | H11: 10 | I11: =G11*H11 -> 71680 | K11: =I11/60 -> 1194.6667 | M11: =K11/(200/12) -> 71.68 | O11: =M11/6.5 -> 11.027692
G12: 12829 | H12: 10 | I12: =G12*H12 -> 128290 | K12: =I12/60 -> 2138.1667 | M12: =K12/(200/12) -> 128.29 | O12: =M12/6.5 -> 19.736923
G13: 14999 | H13: 30 | I13: =G13*H13 -> 449970 | K13: =I13/60 -> 7499.5 | M13: =K13/(200/12) -> 449.97 | O13: =M13/6.5 -> 69.226154
G14: 8925 | H14: 25 | I14: =G14*H14 -> 223125 | K14: =I14/60 -> 3718.75 | M14: =K14/(200/12) -> 223.125 | O14: =M14/6.5 -> 34.326923
G15: 5854 | H15: 25 | I15: =G15*H15 -> 146350 | K15: =I15/60 -> 2439.1667 | M15: =K15/(200/12) -> 146.35 | O15: =M15/6.5 -> 22.515385
G16: 540 | H16: 120 | I16: =G16*H16 -> 64800 | K16: =I16/60 -> 1080 | M16: =K16/(200/12) -> 64.8 | O16: =M16/6.5 -> 9.9692308
G17: 2700 | H17: 120 | I17: =G17*H17 -> 324000 | K17: =I17/60 -> 5400 | M17: =K17/(200/12) -> 324 | O17: =M17/6.5 -> 49.846154
G18: 3695 | H18: 8 | I18: =G18*H18 -> 29560 | K18: =I18/60 -> 492.66667 | M18: =K18/(200/12) -> 29.56 | O18: =M18/6.5 -> 4.5476923
G19: 2981 | H19: 7 | I19: =G19*H19 -> 20867 | K19: =I19/60 -> 347.78333 | M19: =K19/(200/12) -> 20.867 | O19: =M19/6.5 -> 3.2103077
G20: 9845 | H20: 10 | I20: =G20*H20 -> 98450 | K20: =I20/60 -> 1640.8333 | M20: =K20/(200/12) -> 98.45 | O20: =M20/6.5 -> 15.146154
G21: 10287 | H21: 10 | I21: =G21*H21 -> 102870 | K21: =I21/60 -> 1714.5 | M21: =K21/(200/12) -> 102.87 | O21: =M21/6.5 -> 15.826154
G22: 3558 | H22: 10 | I22: =G22*H22 -> 35580 | K22: =I22/60 -> 593 | M22: =K22/(200/12) -> 35.58 | O22: =M22/6.5 -> 5.4738462
G23: 45835 | H23: 10 | I23: =G23*H23 -> 458350 | K23: =I23/60 -> 7639.1667 | M23: =K23/(200/12) -> 458.35 | O23: =M23/6.5 -> 70.515385
G24: 6804 | H24: 10 | I24: =G24*H24 -> 68040 | K24: =I24/60 -> 1134 | M24: =K24/(200/12) -> 68.04 | O24: =M24/6.5 -> 10.467692
H26: Total Hours Annual | I26: =SUM(I2:I24)/60 -> 54376.833
H27: Total Hours /Month | I27: =I26/(200/12) -> 3262.61
H28: FTE Required | I28: =I27/6.5 -> 501.94 | O28: =SUM(O2:O24) -> 501.94
O29: =O28*70500 -> 35386770

Sheet Assumptions
A2: Assumptions | B2: Value
A3: Working Days in a Year | B3: 200
A4: Working Days per Month | B4: 22
A5: Working Hours per Day | B5: 6.5
A6: BOT Accuracy - Complex | B6: 0.7
A7: BOT Accuracy - Medium | B7: 0.8
A8: BOT Accuracy - Simple | B8: 0.9
A9: Monthly VM Cost | B9: 57.790106
A10: Mins Per Hour | B10: 60
A11: Monthly FTE Cost | B11: 554.78502
A12: Monthly Paid Days for FTE | B12: 30
A13: Monthly Seat Cost | B13: 124.65326
A14: Monthly FTEOther Cost | B14: 61.061026
... A27: Support Cost Per resource | B27: 1155.8021

Sheet Estimation Guidelines
A1: Type | B1: Complexity | C1: Concat | D1: Requirement Gathering & PDD | E1: SDD | F1: Development | G1: QA | H1: UAT | I1: Production Deployment | J1: Hypercare | K1: Total Man Days | L1: Total Efforts(Weeks)
A2: OCR | B2: Simple | C2: =_xlfn.CONCAT(A2,B2) -> OCRSimple | D2: 2 | E2: 2 | F2: 10 | G2: =F2*30% -> 3 | H2: =F2*20% -> 2 | I2: 2 | J2: 10 | K2: =SUM(D2:J2) -> 31 | L2: =K2/5 -> 6.2
A3: OCR | B3: Medium | C3: =_xlfn.CONCAT(A3,B3) -> OCRMedium | D3: 3 | E3: 2 | F3: 20 | G3: 4 | H3: 3 | I3: 2 | J3: 10 | K3: =SUM(D3:J3) -> 44 | L3: =K3/5 -> 8.8
A4: OCR | B4: Complex | C4: =_xlfn.CONCAT(A4,B4) -> OCRComplex | D4: 4 | E4: 2 | F4: 30 | G4: 5 | H4: 5 | I4: 2 | J4: 10 | K4: =SUM(D4:J4) -> 58 | L4: =K4/5 -> 11.6
A5: NON-OCR | B5: Simple | C5: =_xlfn.CONCAT(A5,B5) -> NON-OCRSimple | D5: 2 | E5: 1 | F5: 8 | G5: 1 | H5: 1 | I5: 1 | J5: 10 | K5: =SUM(D5:J5) -> 24 | L5: =K5/5 -> 4.8
A6: NON-OCR | B6: Medium | C6: =_xlfn.CONCAT(A6,B6) -> NON-OCRMedium | D6: 2 | E6: 1 | F6: 10 | G6: 3 | H6: =F6*20% -> 2 | I6: 1 | J6: 10 | K6: =SUM(D6:J6) -> 29 | L6: =K6/5 -> 5.8
A7: NON-OCR | B7: Complex | C7: =_xlfn.CONCAT(A7,B7) -> NON-OCRComplex | D7: 2 | E7: 2 | F7: 20 | G7: 5 | H7: 3 | I7: 1 | J7: 10 | K7: =SUM(D7:J7) -> 43 | L7: =K7/5 -> 8.6
C9: * Above estimatesion is based on 2 Developers 1 BA 1 QA 1 PM
